Workbook

Sheet AMBERIEU LAGNIEU
A2: Accompagnement des bénéficiaires du RSA - "CIP +" / 2025 | J2: Sortie + sous objectif (les noter en vert tant que vous les garder en suivi dans l'emploi)
A3: Territoire: CDS…. - LOT .../ CLPE ZONE … | J3: suspension remob
A5: Accompagnement des bénéficiaires du RSA - "CIP +" / 2025 | J5: Sortie + sous objectif (les noter en vert tant que vous les garder en suivi dans l'emploi)
A6: Territoire: CDS AMBERIEU/MEXIMIEUX…. - LOT 3.../ CLPE ZONE 3 | J6: suspension remob
A7: Nom de l'OPERATEUR : ALFA3A | J7: Cli
A8: CIP : HELENE VRAINE (arret à partir du 13/3 - arrivée Aviva le | H8: NOMBRE DE BRSA | I8: =+SUM(A12:A310) -> 115 | S8: SORTIES DU DISPOSITIF | X8: Positionnement actions / démarches
J9: DATE | M9: FREINS IDENTIFIES | U9: SORTIES + sous objectif
B10: H/F | C10: NOM | D10: PRENOM | E10: âge | F10: Niveau scolaire | G10: CDS | H10: DATE ORIENTATION | I10: DATE 1ER RDV fixé | J10: C.E SIGNE | K10: FIN CE 6 MOIS | L10: BILAN PARCOURS (7eme mois) | M10: 1 | N10: 2 | O10: autre | P10: NOMBRE D OFFRES D EMPLOI PROPOSEES (OE/INFO COLL/jobdating..) | Q10: NBRE D ENTRETIENS DE RECRUTEMENT OBTENUS SUITE A VOS OFFRES D EMPLOI | R10: PMSMP (1 = oui) | S10: Motif de sortie | T10: MOTIF de la REO | U10: types | V10: DATE SORTIE | W10: Saisie FSE | X10: FLE (GoOn-Ifra-Ville Bourg-centre social..) | Y10: Declic Emploi HBA | Z10: MIFE 01 | AA10: AIDE FINANCIERE | AB10: Conseillers numériques | AC10: GO ON | AD10: MOBILITE | AE10: ARIANE | AF10: AGENT DE SANTE | AG10: ADAPT | AH10: ORSAC | AI10: REPIT PARENTAL | AJ10: Clauses sociales | AK10: Autres (preciser) | AL10: COMMENTAIRES /OBSERVATION
AL11: Commentaires
A12: 1 | B12: Madame | C12: CHAOU | D12: Bouchra | E12: 35 | F12: Aucun diplômeAmbéreu | H12: 46006 | I12: 46035 | J12: 46035 | K12: =+J12+180 -> 46215 | L12: Renouvellement | M12: SANTE | W12: P1248
A13: 1 | B13: Monsieur | C13: KACZOROWSKI | D13: Gary | E13: 40 | F13: CAP, BEP | G13: Lagnieu | H13: 46007 | I13: 46028 | J13: 46048 | K13: =+J13+180 -> 46228 | M13: MOBILITE | W13: P1250
A14: 0 | B14: Monsieur | C14: PILCH | D14: Jean-Christophe | E14: 47 | F14: BAC PRO | G14: Lagnieu | H14: 46009 | I14: 46028 | J14: 46056 | K14: =+J14+180 -> 46236 | M14: SANTE | N14: MOBILITE | W14: 1 | AF14: 1 | AL14: Mr souhaite repartir en saison pour ne pas rester chez sa mère mais fragilité psy.
A15: 1 | B15: Monsieur | C15: CLOYER | D15: Jérémy | E15: 40 | F15: Aucun diplôme | G15: Ambérieu | H15: 46008 | I15: 46036 | J15: 46036 | K15: =+J15+180 -> 46216 | L15: Renouvellement | M15: SANTE | N15: MOBILITE | O15: LOGEMENT | W15: P1253 | AL15: En attente de réponse de la MDPH pour l'AAH. Relancer/médecin pour CM
A16: 1 | B16: Monsieur | C16: YILMAZ | D16: Mehmet | E16: 50 | F16: Aucun diplôme | G16: Ambérieu | H16: 45995 | I16: 46044 | J16: 46043 | K16: =+J16+180 -> 46223 | M16: Repasser le permis | Q16: , | W16: 1 | AL16: Evenement emploi "ferrovière"pas accepté niveau trop bas
A17: 0 | B17: Monsieur | C17: AL ALI | D17: Abdallah | E17: 41 | F17: Aucun diplôme | G17: Ambérieu | H17: 45811 | I17: 45873 | J17: 45873 | K17: =+J17+180 -> 46053 | M17: LANGUE | N17: SANTE | W17: P249 | AC17: 1 | AL17: analphabètisme en attente de CM -poursuite de GOON jusqu'à juin.
A18: 1 | B18: Madame | C18: ASLIMANI/LAAROUSSI | D18: Nasera | E18: 40 | F18: CAP, BEP | G18: Ambérieu | H18: 45929 | I18: 18/09/20025 | J18: 45968 | K18: =+J18+180 -> 46148 | M18: MOBILITE | N18: SANTE | W18: P1255 | AL18: Très active, participations ateliers jobdating / Animatrice diplôme belge - assistante maternelle agréée
A19: 1 | B19: Madame | C19: BAJRAMOVA | D19: Juksela | E19: 48 | F19: Aucun diplôme | G19: Ambérieu | H19: 45869 | I19: 45911 | J19: 45911 | K19: =+J19+180 -> 46091 | M19: LOGEMENT | N19: SANTE | O19: MOBILITE | P19: 4 | W19: P1246 | AL19: travaille avec STAFFMATCH (petites missions ménage, cuisine) participation atelier, jobdating
A20: 1 | B20: Madame | C20: BERNARDIN | D20: Gaëlle | E20: 43 | F20: Aucun diplôme | G20: Ambérieu | H20: 45812 | I20: 45881 | J20: 45897 | K20: =+J20+180 -> 46077 | L20: Renouvellement | M20: MAMAN SOLO | P20: 3 | W20: P257 | AL20: verifier si bilan envoyé tripartite (doc dep)
A21: 0 | B21: Madame | C21: BORKADI-KHALDI | D21: Cindy | E21: 33 | F21: aucun diplôme | G21: Ambérieu | H21: 45769 | I21: 46260 | J21: 45895 | K21: =+J21+180 -> 46075 | M21: MOBILITE | N21: enfant en situation d'handicap | O21: peu d'expérience professionnelle | P21: 2 | S21: Réorientation | T21: Social freins+ | W21: P435 | AI21: 1 | AL21: Peu disponible - Contrôle régulier de la PMI (1 enfant handicapé - en attente de la PCH) - FAIRE REO SOCIALE CF MAIL
A22: 0 | B22: Monsieur | C22: CLAIRET | D22: Patrice | E22: 43 | F22: Aucun diplôme | G22: Ambérieu | H22: 45820 | I22: 45894 | J22: 45909 | K22: =+J22+180 -> 46089 | M22: SANTE | N22: MOBILITE | S22: Réorientation | T22: Arret mal longue durée | W22: P64 | AL22: CM fourni réo faite le 06/02
A23: 0 | B23: Monsieur | C23: CREPALDI | D23: David | E23: 41 | F23: BAC PRO | G23: Lagnieu | H23: 45821 | I23: 45873 | J23: 45873 | K23: =+J23+180 -> 46053 | M23: SANTE | P23: 2 | Q23: 1 | S23: Réorientation | T23: Arret mal longue durée | W23: P108 | AL23: REO SOCIALE plusieurs hospitalisations
A24: 0 | B24: Monsieur | C24: FARINA | D24: Yann | E24: 42 | F24: Aucun diplôme | G24: Ambérieu | H24: 45814 | I24: 45901 | J24: 45945 | K24: =+J24+180 -> 46125 | M24: sans domicile | N24: frais de déplacement | P24: 3 | S24: Réorientation | T24: Social freins+ | W24: P252 | AL24: incurie
A25: 1 | B25: Madame | C25: FERNANDES | D25: Noemie | E25: 28 | F25: DEUG, BTS, DUT, DEUST | G25: Amberieu | H25: 45814 | I25: 45874 | J25: 45874 | K25: =+J25+180 -> 46054 | L25: Renouvellement | M25: SANTE | N25: Probl perso | P25: 2 | W25: P1249 | AL25: Mme a peur de son ex conjoint - se présente 1 fois sur 2 (remobilisation) ne se mobilise pas
A26: 1 | B26: Madame | C26: FOFANA | D26: Fanta | E26: 29 | F26: aucun diplôme | G26: Ambérieu | H26: 45820 | I26: 45868 | J26: 45912 | K26: =+J26+180 -> 46092 | M26: ECRIT | N26: santé | W26: P111 | AC26: 1 | AL26: Suivi par AGIR- parle tres bien le francais, ne sait pas lire ni ecrire / GO ON A convoquer
A27: 0 | B27: Madame | C27: HAMOT | D27: Whitney | E27: 28 | F27: DEUG, BTS, DUT, DEUST | G27: Lagnieu | H27: 45835 | I27: 45866 | J27: 45873 | K27: =+J27+180 -> 46053 | M27: Enfant bas age | P27: 2 | S27: Réorientation | T27: Social freins+ | W27: P105 | AL27: 4 enfants (3 à l'ecole) - mere celibataire - dernier enfant 18 mois - a été commerciale
A28: 1 | B28: Monsieur | C28: JUVENAL | D28: Cédric | E28: 48 | F28: CAP, BEP | G28: Lagnieu | H28: 45840 | I28: 45901 | J28: 45922 | K28: =+J28+180 -> 46102 | M28: SANTE | P28: 4 | W28: P1254 | AL28: Cdd 3 mois en garage non renouvelé - abs février refixer un rdv sinon REMOB - pas de cv !!
A29: 1 | B29: Madame | C29: KHALO / OMAR | D29: Hanifa | E29: 40 | F29: Aucun diplôme | G29: Ambérieu | H29: 45827 | I29: 45883 | J29: 45912 | K29: =+J29+180 -> 46092 | L29: Renouvellement | M29: LANGUE | N29: SANTE | O29: MOBILITE | W29: P61 | AK29: Léo Lagrange | AL29: CM : le medecin atteste qu elle peut travailler et peut suivre les cours Aintégré Léo Lagrange le 05/03
A30: 0 | B30: Madame | C30: KOUASSI | D30: Amoin Désirée Prudence | E30: 30 | F30: CAP, BEP | G30: Amberieu | H30: 45840 | I30: 45859 | J30: 45859 | K30: =+J30+180 -> 46039 | L30: Renouvellement | M30: SANTE | N30: VEHICULE | P30: 8 | S30: Positive | T30: FT acc pro | U30: SIAE (FT) | W30: P433 | AL30: Très active, PMSMP, achat de véhicule, petits boulots… A démarré LOGIN'S récupérer le contrat et suivre péride d'essai sortie FT
A31: 1 | B31: Madame | C31: LAHURE | D31: Belinda | E31: 47 | F31: Aucun diplôme | G31: Ambérieu | H31: 45832 | I31: 45896 | J31: 45896 | K31: =+J31+180 -> 46076 | L31: Renouvellement | M31: SANTE | N31: Permis en cours | P31: 5 | W31: P462 | AF31: 1 | AL31: Présente PEC pas retenue / petits boulots menage
A32: 1 | B32: Madame | C32: LYONNET | D32: Sandrine | E32: 46 | F32: CAP, BEP | G32: Ambérieu | H32: 45821 | I32: 45882 | J32: 45882 | K32: =+J32+180 -> 46062 | L32: Renouvellement | M32: SANTE | N32: pas de véhicule | P32: 3 | W32: P246 | AL32: en attente de réponse de la MDPH pour l'AAH / voir GPP avec Djamila
A33: 1 | B33: Madame | C33: MAHAMADOU | D33: Haoua | E33: 47 | F33: Aucun diplôme | G33: Ambérieu | H33: 45820 | I33: 45924 | J33: 45938 | K33: =+J33+180 -> 46118 | M33: LANGUE | N33: ISOLEE | O33: SANTE | W33: P245 | AC33: 1 | AL33: Orientée vers cours de français G0 ON - FAIRE REO SOCIALE OU BILAN TRIPARTITE - Personne seule pas de com possible
A34: 0 | B34: Madame | C34: MAHESHE NKUBONAGE | D34: Nicole | E34: 45 | F34: DEUG, BTS, DUT, DEUST | G34: Ambérieu | H34: 45811 | I34: 45902 | J34: 45902 | K34: =+J34+180 -> 46082 | M34: MOBILITE | N34: SANTE | P34: 7 | S34: Réorientation | T34: FT acc pro | V34: 46108 | W34: P464 | AL34: Candidate beaucoup - manque de confiance en soi
A35: 1 | B35: Monsieur | C35: MIGUEL | D35: Herve | E35: 45 | F35: Aucun diplôme | G35: Ambérieu | H35: 45798 | I35: 45873 | J35: 45873 | K35: =+J35+180 -> 46053 | M35: MOBILITE | N35: SANTE | O35: HEBERGEMENT | P35: 1 | AF35: 1 | AL35: voir LOGGINS - CACES a renouveler faire une immersion
A36: 0 | B36: Madame | C36: MOHAMAD | D36: Shirin | E36: 46 | F36: Aucun diplôme | G36: Ambérieu | H36: 45826 | I36: 45883 | J36: 45883 | K36: =+J36+180 -> 46063 | L36: Renouvellement | M36: MOBILITE | N36: SANTE | O36: LANGUE | S36: Réorientation | T36: FT acc pro | V36: 46248 | W36: P107 | AC36: 1 | AD36: 1 | AL36: GO ON, proposition fle/logistique FT2026 : a refusé
A37: 0 | B37: Monsieur | C37: MOTA | D37: Jean Michel | E37: 45 | G37: Lagnieu | H37: 45828 | I37: 45894 | K37: =+J37+180 -> 180 | AL37: Passé en CLI le 12/12/25 - sanctionné à 80% - pas de contact repris
A38: 1 | B38: Monsieur | C38: PIEDBOIS | D38: Youri | E38: 54 | F38: Baccalauréat | G38: Lagnieu | H38: 45821 | I38: 45908 | J38: 45908 | K38: =+J38+180 -> 46088 | L38: Renouvellement | M38: Hebergement | N38: santé | P38: 3 | W38: P566 | AL38: Mr était SDF. Il reprend sa vie en main. Contrat appui entreprise 2 OE proposées refusées
A39: 1 | B39: Monsieur | C39: POTENZIANI | D39: Nicolas | E39: 26 | F39: aucun diplôme | G39: Ambérieu | H39: 45812 | I39: 45887 | J39: 45890 | K39: =+J39+180 -> 46070 | M39: mobilité | N39: peu d'expérience pro | W39: P1262 | AL39: a réussi son code;conduite en cours - Attention Mr ne respecte pas . Prévoir un prochain rdv rapidement si absent REMOB
A40: 1 | B40: Monsieur | C40: PUVILLAN | D40: Cédric | E40: 48 | F40: DEUG, BTS, DUT, DEUST | G40: Amberieu | H40: 45777 | I40: 45866 | J40: 45866 | K40: =+J40+180 -> 46046 | L40: Renouvellement | M40: multiple projet | N40: santé | P40: 1 | W40: P429 | AL40: en interim jusqu'en décembre 2025 - cariste - formation caces 1 b35 ACTUAL - plus de nouvelle
A41: 0 | B41: Madame | C41: RAMDANI | D41: Ikram | E41: 43 | F41: BAC | G41: Lagnieu | H41: 45812 | I41: 45901 | J41: 45901 | K41: =+J41+180 -> 46081 | L41: Renouvellement | M41: maman solo | N41: santé | R41: 1 | S41: Réorientation | T41: FT acco glo | V41: 46266 | W41: P431 | AL41: demarche assistante maternelle ? Pmsmp à faire / aide à domicile / atsem
A42: 1 | B42: Madame | C42: RAMOS | D42: Audrey | E42: 36 | F42: CAP, BEP | G42: Ambérieu | H42: 45827 | I42: 45902 | J42: 45912 | K42: =+J42+180 -> 46092 | L42: Renouvellement | M42: séparation difficile | N42: maman solo | P42: 3 | W42: P106 | AL42: a CAP petite enfance - Chercher un autre projet professionnel
A43: 1 | B43: Madame | C43: RONGIER | D43: Marine | E43: 39 | F43: BP | G43: Ambérieu | H43: 45811 | I43: 45896 | J43: 45896 | K43: =+J43+180 -> 46076 | M43: SANTE | N43: maman solo | W43: P430 | AL43: Nrépond pas au tel , ni au mail A CONVOQUER sinon remob
A44: 1 | B44: Madame | C44: ROUSSEL | D44: Joanna | E44: 32 | F44: BAC PRO | G44: Ambérieu | H44: 45810 | I44: 45867 | J44: 45898 | K44: =+J44+180 -> 46078 | M44: SANTE | N44: MOBILITE | O44: enfant en bas âge | P44: 3 | W44: P250 | AL44: Beaucoup d'abs exc enfant malade, bus… / diplôme ds aide a domicileA RECONVOQUER en couple avec Mr Potenziani enfants sous mesure
A45: 0 | B45: Monsieur | C45: SANTANA | D45: Alexis | E45: 33 | F45: bac PRO | G45: Amberieu | H45: 45821 | I45: 45908 | J45: 46013 | K45: =+J45+180 -> 46193 | M45: santé | AL45: Missions intérim en décembre poursuite en janvier - reclamer tous les contrats et refixer un rdv
A46: 1 | B46: Madame | C46: SCHEID | D46: Marie | E46: 35 | F46: primaire | G46: Ambérieu | H46: 45832 | I46: 45888 | J46: 45888 | K46: =+J46+180 -> 46068 | M46: Peu d'expérience | N46: enfant en difficulté | P46: 2 | W46: P1353 | AL46: Mme a fait un CV, gens du voyage
A47: 1 | B47: Monsieur | C47: SEYE | D47: Mohamed | E47: 37 | F47: BAC+3 | G47: Amberieu | H47: 45867 | I47: 45889 | J47: 45904 | K47: =+J47+180 -> 46084 | M47: MOBILITE | N47: papa solo | P47: 4 | Q47: 1 | W47: P247 | AA47: 1 | AL47: / travaille en interim depuis décembre
A48: 0 | B48: Madame | C48: SOUADIA | D48: Sandrine | E48: 43 | G48: Lagnieu | H48: 45776 | I48: 45908 | K48: =+J48+180 -> 180 | AL48: Assistante familiale mais pas d'enfant à l heure actuelle jamais vue à convoquer d urgence
A49: 1 | B49: Madame | C49: TAHIRI | D49: Marsela | E49: 33 | F49: aucun diplôme | G49: Ambérieu | H49: 45834 | I49: 45867 | J49: 45897 | K49: =+J49+180 -> 46077 | M49: MOBILITE | N49: LANGUE | O49: SANTE | P49: 0 | W49: P110 | AL49: vue par une assistance sociale BILAN DE PARCOURS REO SOCIALE
A50: 0 | B50: Monsieur | C50: TALASH | D50: Mohamad | E50: 30 | G50: Ambérieu | H50: 45799 | I50: 45876 | J50: SDP | K50: =+J50+180 -> #VALUE! | AL50: SITUATION EN ATTENTE D'ETRE DEBLOQUEE FT - PRENDRE L ACCOMPANGNEMENT EN COURS A RECONVOQUER
A51: 1 | B51: Madame | C51: THEVENON-DANIERE | D51: Géraldine | E51: 44 | F51: BEP | G51: Ambérieu | H51: 45758 | I51: 45910 | J51: 45910 | K51: =+J51+180 -> 46090 | M51: pb lié au logement | N51: maman solo | O51: séparation difficile | R51: 1 | AL51: reprise VD .Aime la vente mais contraintes familiales / immersion ok / aide à domicile
A52: 1 | B52: Madame | C52: THOMASSON | D52: Amélie | E52: 47 | G52: Ambérieu | H52: 45867 | I52: 45889 | J52: 45929 | K52: =+J52+180 -> 46109 | L52: Renouvellement | M52: MOBILITE | N52: SANTE | W52: P1263 | AF52: 1 | AL52: Souvent malade proposer acco agent de santé - fripone ?
A53: 0 | B53: Madame | C53: TOURE | D53: Marie Agnes | E53: 43 | F53: bac | G53: Ambérieu | H53: 45821 | I53: 45910 | J53: 45910 | K53: =+J53+180 -> 46090 | M53: maman solo | N53: garde d'enfant | O53: Pas de véhicule | S53: Fin DD | V53: 46235 | W53: P1264 | AL53: intéressée formation SAMA
A54: 1 | B54: Madame | C54: TRONQUART | D54: Marie-Christine | E54: 51 | F54: CAP, BEP | G54: Ambérieu | H54: 45821 | I54: 45889 | J54: 45903 | K54: =+J54+180 -> 46083 | M54: MOBILITE | N54: Pas de médecin | P54: 4 | W54: P254 | AL54: a déjà travaillé en structure d'insertion -
A55: 0 | B55: Madame | C55: TUNCAY | D55: Esira | E55: 28 | F55: aucun diplôme | G55: Ambérieu | H55: 45813 | I55: 45866 | J55: 45905 | K55: =+J55+180 -> 46085 | M55: enfant en situation de handicap | N55: En coursd de divorce | W55: P1245 | AL55: fils qui n'a pas de place en IME / vue sur Mex / revoir son dossier MDPH pour son fils pour pch
A56: 1 | B56: Madame | C56: VOGELSGSANG | D56: Emilie | E56: 38 | F56: aucun diplôme | G56: Ambérieu | H56: 45821 | I56: 45882 | J56: 45882 | K56: =+J56+180 -> 46062 | L56: Renouvellement | M56: SANTE | N56: MOBILITE | O56: aucune exp pro | W56: P256 | AL56: BILAN TRIPARTITE
A57: 1 | B57: Madame | C57: YOUNES | D57: Sarah | E57: 33 | F57: BAC | G57: Ambérieu | H57: 45813 | I57: 45867 | J57: 45867 | K57: =+J57+180 -> 46047 | L57: Renouvellement | M57: ENFANTS | N57: Aide à parent malade | W57: P1230 | AL57: Aide à domicile / ash : aidant familila pour sa maman
A58: 1 | B58: Monsieur | C58: ZABLOT | D58: Arthur | E58: 30 | F58: BAC | G58: Ambérieu | H58: 45776 | I58: 45875 | J58: 45875 | K58: =+J58+180 -> 46055 | L58: Renouvellement | M58: RQTH | P58: 8 | Q58: 1 | W58: P451 | AL58: cariste -
A59: 0 | B59: Madame | C59: CHEKKI | D59: Islam | E59: 33 | F59: master | G59: Lagnieu | H59: 45876 | I59: 45929 | J59: 45929 | K59: =+J59+180 -> 46109 | M59: maman solo | S59: Réorientation | T59: FT acc pro | U59: Créa | W59: P563 | AL59: Autoentrepreneuse depuis 2021, a déjà eu un acco BGE - activité traductrice anglais + crs en ligne + missions informatique
A60: 1 | B60: Monsieur | C60: LAMANCHE | D60: Steve | E60: 33 | F60: BAC | G60: Lagnieu | H60: 45882 | I60: 45922 | J60: 45922 | K60: =+J60+180 -> 46102 | L60: Renouvellement | M60: MOBILITE | N60: Manque de confiance | W60: P1256 | AL60: CDD en décembre 2025 - AM jusqu'en fevrier car AT - CDI à venir ? A RAPPELER
A61: 0 | B61: Madame | C61: SLIMANI | D61: Lahouaria | E61: 53 | F61: BAC+3 | G61: Lagnieu | H61: 45890 | I61: 45929 | J61: 45930 | K61: =+J61+180 -> 46110 | M61: enfant autiste | AL61: En attente AEH:PCH à relancer
A62: 1 | B62: Madame | C62: MALIQI | D62: Qendrese | E62: 26 | F62: Aucun diplôme | G62: Ambérieu | H62: 45903 | I62: 45923 | J62: 45923 | K62: =+J62+180 -> 46103 | L62: Renouvellement | M62: MOBILITE | N62: SANTE | P62: 2 | W62: P1258 | AL62: a eu l'AAH ne l'a plu voir ENVOL .Agent de santé / Voir une formation
A63: 1 | B63: Madame | C63: MULLAEVA | D63: Malvina | E63: 37 | F63: aucun diplôme | G63: Ambérieu | H63: 45904 | I63: 45923 | J63: 45923 | K63: =+J63+180 -> 46103 | L63: Renouvellement | M63: LANGUE | N63: MOBILITE | W63: P1259 | AL63: suivie par AGIR. Français Llagrange. Inscription GOON - pas un mot de francais
A64: 1 | B64: Monsieur | C64: MICHALET | D64: Jean Louis | E64: 52 | F64: Aucun dipôme | G64: Lagnieu | H64: 45866 | I64: 45965 | J64: 45965 | K64: =+J64+180 -> 46145 | L64: Renouvellement | M64: SANTETDA | N64: aucune qualif | O64: MOBILITE | W64: P304 | AF64: 1 | AJ64: 1 | AL64: Comportement particulier!
A65: 0 | B65: Madame | C65: LOMBARD | D65: Aurelia | E65: 43 | G65: Lagnieu | H65: 45939 | I65: 45979 | K65: =+J65+180 -> 180 | S65: Fin DD | AL65: Aucun contact possible PREVOIR REMOB
A66: 1 | B66: Monsieur | C66: TEKIN | D66: Vural | E66: 44 | F66: CAP, BEP | G66: Ambérieu | H66: 45943 | I66: 45959 | J66: 45959 | K66: =+J66+180 -> 46139 | M66: SANTE | N66: Faire le deuil de son entreprise | W66: P522 | AJ66: 1 | AL66: A RECONVOQUER Mr voulait recommencerd'être à son compte, démarches non réalisées.
A67: 0 | B67: Monsieur | C67: VANEENOO | D67: Cedric | E67: 39 | F67: ucun diplôme | G67: Amberieu | H67: 45940 | I67: 45957 | J67: 1 | K67: =+J67+180 -> 181 | S67: Positive | T67: FT acc pro | U67: CDD +6mois >ou=254h | V67: 46223 | AL67: Mr VANEENOO est actuellement à l'emploi (CDD du 01/05/26 au 31/10/26)
A68: 1 | B68: Monsieur | C68: YOUSEF | D68: Siraj | E68: 52 | F68: Ingénieur | G68: Ambérieu | H68: 45943 | I68: 45959 | J68: 45959 | K68: =+J68+180 -> 46139 | M68: SANTE | N68: AGE | AL68: en attente de loggins + clauses sociales/ aeu sa RQTH
A69: 1 | B69: Madame | C69: OLRY | D69: Florence | E69: 49 | F69: Aucun diplôme | G69: Ambérieu | H69: 45943 | I69: 45964 | J69: 45973 | K69: =+J69+180 -> 46153 | M69: Difficultés financières | N69: enfant adulte handicapé | O69: mobilité | W69: P1260 | AL69: Mme a toujours été à son compte -
A70: 0 | B70: Madame | C70: TURPIN | D70: Océane | E70: 32 | F70: BEP | G70: Amberieu | H70: 45945 | I70: 45959 | J70: 45995 | K70: =+J70+180 -> 46175 | M70: Enfant autiste | N70: Menace | O70: Changement de situation | W70: P1266 | AL70: Sortie des D et D
A71: 1 | B71: Madame | C71: CHERON | D71: Carine | E71: 53 | F71: Sans diplôme | G71: Ambérieu | H71: 45964 | I71: 45987 | J71: 45987 | K71: =+J71+180 -> 46167 | L71: Renouvellement | M71: SANTE | N71: MOBILITE | W71: P1252 | AL71: travailler un projet pro - A RECONVOQUER
A72: 1 | B72: Monsieur | C72: BEN BRAHIM | D72: Ridha | E72: 49 | F72: master | G72: Lagnieu | I72: 46007 | J72: 46007 | K72: =+J72+180 -> 46187 | M72: MOBILITE | N72: dernier emploi ? | W72: 1 | AL72: en attente CM ? A CONVOQUER
A73: 0 | B73: Madame | C73: MESSAI/RIBEIRO | D73: Hadda | E73: 37 | F73: BAC | G73: Lagnieu | I73: 46007 | J73: 46007 | K73: =+J73+180 -> 46187 | M73: Congé parental | N73: Enfant de 18 mois | AL73: En attente de preuves congé parental… / RSA MAJORE
A74: 1 | B74: Madame | C74: VEUGLE | D74: Alison | E74: 26 | F74: CAP, BEP | G74: Ambérieu | H74: 45975 | I74: 45994 | J74: 46014 | K74: =+J74+180 -> 46194 | M74: LOGEMENT | N74: Enfant en bas age | W74: P506 | AL74: Recherche de solution de garde
A75: 0 | B75: Madame | C75: BLIN | D75: Françoise | E75: 63 | F75: Sans diplôme | G75: Ambérieu | H75: 45966 | I75: 45994 | J75: 45994 | K75: =+J75+180 -> 46174 | M75: AGE | N75: MOBILITE | W75: P460 | AL75: Dossier retraite envisagée A RECONVOQUER (erreur de ma part) REO SOCIALE/AGE?
A76: 1 | B76: Monsieur | C76: MARNY | D76: Christopher | E76: 36 | F76: Sans diplôme | G76: Ambérieu | H76: 45965 | I76: 45994 | J76: 45994 | K76: =+J76+180 -> 46174 | M76: MOBILITE | N76: SANTE | O76: ENFANTS JEUNES | W76: P1251
A77: 0 | B77: Madame | C77: PIOLAT | D77: Virginie | E77: 36 | F77: BAC | G77: Ambérieu | H77: 45909 | I77: 46001 | J77: 45940 | K77: =+J77+180 -> 46120 | L77: Renouvellement | M77: SANTE | W77: P1261
A78: 1 | B78: Monsieur | C78: CHARLIER | D78: William | E78: 49 | F78: CAP, BEP | G78: LAGNIEU | H78: 45980 | I78: 46007 | J78: 46009 | K78: =+J78+180 -> 46189 | M78: SANTE | N78: RECONVERSION | W78: P1243 | AL78: Mr est en attente d'une opération, en fonction des résultats MDPH
A79: 1 | B79: Monsieur | C79: HAMM | D79: Alexandre | E79: 31 | F79: BAC+2 | G79: Ambérieu | H79: 45985 | I79: 46008 | J79: 46008 | K79: =+J79+180 -> 46188 | M79: MOBILITE | W79: P494 | AL79: Poursuite du permis/envisage auto-entreprise
A80: 1 | B80: Monsieur | C80: BOISMENU | D80: David | E80: 52 | F80: BAC | G80: Ambérieu | H80: 45986 | I80: 46008 | J80: 46008 | K80: =+J80+180 -> 46188 | M80: LOGEMENT | N80: Surendettement | O80: SANTE | W80: P1247 | AD80: 1 | AL80: A fait parcours nuclèaire . Voir santé Agent de santé? Aide financière à prévoir si logement ou emploi.
A81: 1 | B81: Madame | C81: TOURNU | D81: Marie-Claude | E81: 45 | F81: BAC | G81: Ambérieu | H81: 25/11/20252 | I81: 46013 | J81: 46013 | K81: =+J81+180 -> 46193 | M81: Maman solo | N81: enfant en situation de handicap | W81: P1265 | AL81: aide soignante
A82: 1 | B82: Madame | C82: VULCAIN | D82: Alexandrine | E82: 39 | F82: bac | G82: Ambérieu | H82: 45985 | I82: 46013 | J82: 46013 | K82: =+J82+180 -> 46193 | M82: Santé | N82: Maman solo | W82: P508
A83: 1 | B83: Madame | C83: JUPITER | D83: Tanya | E83: 26 | F83: bacpro | G83: Ambérieu | H83: 45985 | I83: 46013 | J83: 46013 | K83: =+J83+180 -> 46193 | M83: problème psy | N83: mobilité | R83: 1 | W83: P496 | Z83: 1 | AL83: 4 ans de suivi Mission Locale… / suit agpp avec Djamila Zaied
A84: 1 | B84: Madame | C84: GASHI | D84: Ramize | E84: 41 | F84: BAC | G84: Ambérieu | H84: 46347 | I84: 46000 | J84: 45999 | K84: =+J84+180 -> 46179 | M84: français écrit | N84: Maman solo | W84: P255 | AL84: difficulté pour envoyer les candidatures A CONVOQUER
A85: 1 | B85: Mme | C85: KAHLAOUI | D85: Samira | E85: 49 | F85: Aucun diplôme | G85: Ambérieu | H85: 45975 | I85: 45992 | J85: 45992 | K85: =+J85+180 -> 46172 | M85: LANGUE | N85: PEU D'experience | W85: P434 | AL85: GOON
A86: 1 | B86: Monsieur | C86: VESPAZIANI | D86: Vincent | E86: 31 | F86: Bac | G86: Ambérieu | H86: 46339 | I86: 45987 | J86: 46051 | K86: =+J86+180 -> 46231 | AL86: Mr ne répond pas au mail/rdv fixé 29/01 entreprise bancale
A87: 1 | B87: Monsieur | C87: BASILE | D87: Kévin | E87: 42 | F87: Bac | G87: Ambérieu | H87: 46035 | I87: 46057 | J87: 46057 | K87: =+J87+180 -> 46237 | M87: MOBILITE | W87: P1225
A88: 1 | B88: Madame | C88: BLONDEAU | D88: Mandy | E88: 28 | G88: Ambérieu | H88: 46036 | I88: 46050 | J88: 46064 | K88: =+J88+180 -> 46244
A89: 0 | B89: Madame | C89: GUICHARD | D89: Marie | E89: 61 | F89: Baccalauréat | G89: Ambérieu | H89: 46038 | I89: 46057 | J89: 46063 | K89: =+J89+180 -> 46243 | M89: Financier | S89: Réorientation | T89: BGE | U89: Créa
A90: 1 | B90: Monsieur | C90: MANACH | D90: Victor | E90: 30 | F90: Aucun diplôme | G90: Ambérieu | H90: 46038 | I90: 46057 | J90: 46057 | K90: =+J90+180 -> 46237 | M90: LOGEMENT | N90: MOBILITE | W90: P1237
A91: 1 | B91: Monsieur | C91: LEBEAU | D91: Jonathan | E91: 35 | F91: Aucun diplôme | G91: Ambérieu | H91: 46037 | I91: 46057 | J91: 46057 | K91: =+J91+180 -> 46237 | M91: MOBILITE | N91: SANTE | W91: P1257 | AL91: A CONVOQUER Pris en SIAE a évoqué pb familial pour ne pas y aller
A92: 1 | B92: Monsieur | C92: GOUVERNEUR | D92: Nicolas | E92: 39 | F92: DEUG, BTS, DUT, DEUST | G92: Lagnieu | H92: 46037 | I92: 46049 | J92: 46077 | K92: =+J92+180 -> 46257 | M92: MOBILITE | W92: 1232
A93: 1 | B93: Madame | C93: TAOUCHE | D93: Malika | E93: 26 | G93: Ambérieu | H93: 46007 | J93: 46113 | K93: =+J93+180 -> 46293 | AL93: LEVER LA SANCTION REMOB vérifier que la personne se mobilise vraiment
A94: 1 | B94: Monsieur | C94: THOLLOT | D94: Florian | E94: 35 | F94: Aucun diplôme | G94: Lagnieu | H94: 46037 | I94: 46056 | J94: 46056 | K94: =+J94+180 -> 46236 | M94: MOBILITE | N94: ADDICTION | AL94: abs rdv addiction
A95: 1 | B95: Monsieur | C95: LABARRIERE | D95: Paul Emile | E95: 26 | F95: DEUG, BTS, DUT, DEUST | G95: Lagnieu | H95: 46051 | I95: 46084 | J95: 46084 | K95: =+J95+180 -> 46264 | M95: SANTE | N95: MOBILITE | AF95: 1 | AL95: TDH piste santé
A96: 0 | B96: Monsieur | C96: GUEPRATTE | D96: Ronny | E96: 27 | G96: Ambérieu | H96: 46055 | I96: 46076 | K96: =+J96+180 -> 180 | AL96: PREVOIR REMOB 2 absences non justifiées
A97: 1 | B97: Madame | C97: GABORIT | D97: Edwige | E97: 53 | G97: Ambérieu | H97: 46052 | I97: 46071 | J97: 46258 | K97: =+J97+180 -> 46438 | M97: MOBILITE | N97: SANTE | O97: illectronisme | AL97: SOUS CURATELLE
A98: 1 | B98: Madame | C98: KHAN | D98: Tahira | E98: 46 | F98: Aucun diplôme | G98: Ambérieu | H98: 46055 | I98: 46076 | J98: 46092 | K98: =+J98+180 -> 46272 | AC98: 1
A99: 1 | B99: Madame | C99: NDOJ | D99: Dava | E99: 63 | F99: Aucun diplôme | G99: Ambérieu | H99: 46058 | I99: 46078 | J99: 46078 | K99: =+J99+180 -> 46258 | M99: SANTE | N99: MOBILITE | AL99: DOSSIER MDPH envisagé
A100: 1 | B100: Monsieur | C100: VANEENOO | D100: Jérémy | E100: 33 | F100: Aucun diplôme | G100: Ambérieu | H100: 46001 | I100: 46050 | J100: 46050 | K100: =+J100+180 -> 46230 | M100: LOGEMENT | N100: MOBILITE
A101: 1 | B101: Madame | C101: GALLE | D101: Aurélie | E101: 31 | F101: Aucun diplôme | G101: Lagnieu | H101: 46058 | I101: 46070 | J101: 46070 | K101: =+J101+180 -> 46250 | AF101: 1 | AL101: Projet irréaliste/état de santé
A102: 1 | B102: Monsieur | C102: AROUMOUGAM | D102: Selvaperoumal | E102: 58 | G102: Lagnieu | H102: 46079 | I102: 46105 | J102: 46140 | K102: =+J102+180 -> 46320 | M102: langue | N102: RQTH | W102: P1224 | AL102: Peut prétendre à une retraite anticipé (il lui reste 2 ans sans comptabiliser sa RQTH)
...

Sheet BRSA SORTIES 
A2: Accompagnement des bénéficiaires du RSA - "CIP +" / 2025 | J2: Sortie + sous objectif (les noter en vert tant que vous les garder en suivi dans l'emploi)
A3: Territoire: CDS…. - LOT .../ CLPE ZONE … | J3: suspension remob
A5: Accompagnement des bénéficiaires du RSA - "CIP +" / 2025 | J5: Sortie + sous objectif (les noter en vert tant que vous les garder en suivi dans l'emploi)
A6: Territoire: CDS AMBERIEU/MEXIMIEUX…. - LOT 3.../ CLPE ZONE 3 | J6: suspension remob
A7: Nom de l'OPERATEUR : ALFA3A | J7: Cli
A8: CIP : HELENE VRAINE (arret à partir du 13/3 - arrivée Aviva le | H8: NOMBRE DE BRSA | I8: =+SUM(A12:A241) -> 81 | S8: SORTIES DU DISPOSITIF | X8: Positionnement actions / démarches
J9: DATE | M9: FREINS IDENTIFIES | U9: SORTIES + sous objectif
B10: H/F | C10: NOM | D10: PRENOM | E10: âge | F10: Niveau scolaire | G10: CDS | H10: DATE ORIENTATION | I10: DATE 1ER RDV fixé | J10: C.E SIGNE | K10: FIN CE 6 MOIS | L10: BILAN PARCOURS (7eme mois) | M10: 1 | N10: 2 | O10: autre | P10: NOMBRE D OFFRES D EMPLOI PROPOSEES (OE/INFO COLL/jobdating..) | Q10: NBRE D ENTRETIENS DE RECRUTEMENT OBTENUS SUITE A VOS OFFRES D EMPLOI | R10: PMSMP (1 = oui) | S10: Motif de sortie | T10: MOTIF de la REO | U10: types | V10: DATE SORTIE | W10: Saisie FSE | X10: FLE (GoOn-Ifra-Ville Bourg-centre social..) | Y10: Declic Emploi HBA | Z10: MIFE 01 | AA10: AIDE FINANCIERE | AB10: Conseillers numériques | AC10: GO ON | AD10: MOBILITE | AE10: ARIANE | AF10: AGENT DE SANTE | AG10: ADAPT | AH10: ORSAC | AI10: REPIT PARENTAL | AJ10: Clauses sociales | AK10: Autres (preciser) | AL10: COMMENTAIRES /OBSERVATION
AL11: Commentaires
A12: 1 | B12: Monsieur | C12: AL JOUMAA | D12: Hamoud | E12: 41 | F12: Aucun diplôme | G12: Ambérieu | H12: 45765 | I12: 45896 | K12: =+J12+180 -> 180 | S12: Réorientation | T12: FT acco glo | AL12: Mr AL JOUMAA est venu à son 1er RDV
A13: 1 | B13: Madame | C13: DIVRECHY / COMBEAU | D13: Noémie | E13: 29 | F13: Aucun diplôme | G13: Ambérieu | H13: 45828 | I13: 45894 | K13: =+J13+180 -> 180 | M13: Maman solo | N13: 4 enfants | S13: Fin DD | W13: P27 | AL13: REO BOURG ATTENION sous SDP Mme COMBEAU.Ne dépend plus du cds d'AMBERIEU mais BOURG
A14: 1 | B14: Madame | C14: ELAMBERT | D14: Adeline | E14: 30 | G14: Ambérieu | H14: 45743 | I14: 45869 | K14: =+J14+180 -> 180 | O14: 0 | S14: Réorientation | T14: FT acc pro | AL14: Mme est venue suivie par FT parcours pro
A15: 1 | B15: Madame | C15: ETEMI / ETEMOV | D15: Irmizat | E15: 30 | G15: Ambérieu | H15: 45811 | I15: 45901 | K15: =+J15+180 -> 180 | M15: maman solo | N15: enfant problème de santé | O15: enfant en bas âge | S15: Fin DD | AL15: Logisti+AI99que+AJ103:AQ106
A16: 1 | B16: Madame | C16: GORUR | D16: Andréa | E16: 30 | F16: CAP, BEP | G16: Lagnieu | H16: 45818 | I16: 45894 | K16: =+J16+180 -> 180 | S16: Réorientation | T16: BGE
A17: 1 | B17: Madame | C17: HOUMADI | D17: Mayi | E17: 39 | F17: Aucun diplôme | G17: Ambérieu | H17: 45800 | I17: 45901 | K17: =+J17+180 -> 180 | S17: Déménagement
A18: 1 | B18: Madame | C18: KANGABA-KOKESSE | D18: Michelle | E18: 33 | G18: Ambérieu | H18: 45828 | I18: 45883 | K18: =+J18+180 -> 180 | S18: Fin DD
A19: 1 | B19: Madame | C19: KOKOT | D19: Aude | E19: 36 | G19: Lagnieu | H19: 45819 | I19: 45894 | K19: =+J19+180 -> 180 | S19: Réorientation | T19: BGE
A20: 1 | B20: Monsieur | C20: KRELL | D20: Olivier | E20: 38 | G20: Ambérieu | H20: 45821 | K20: =+J20+180 -> 180 | S20: Réorientation | T20: Sociale AAH
A21: 1 | B21: Madame | C21: KRIACH | D21: Monia | E21: 46 | G21: Ambérieu | H21: 45810 | I21: 45881 | K21: =+J21+180 -> 180 | S21: Déménagement
A22: 1 | B22: Madame | C22: KULA | D22: Gulsun | E22: 40 | G22: Ambérieu | H22: 45758 | I22: 45881 | K22: =+J22+180 -> 180 | S22: Réorientation | T22: FT acc pro | AL22: France T
A23: 1 | B23: Madame | C23: LYONNET | D23: Soulin | E23: 44 | F23: Aucun diplôme | G23: Ambérieu | H23: 45777 | I23: 45889 | K23: =+J23+180 -> 180 | S23: Réorientation | T23: BGE | AL23: A RECONVOQUER
A24: 1 | B24: Monsieur | C24: MACON | D24: Julien | E24: 34 | G24: Lagnieu | H24: 45824 | I24: 45894 | K24: =+J24+180 -> 180 | S24: Réorientation | T24: FT acc pro | U24: FT SIAE
A25: 1 | B25: Madame | C25: MARBACH | D25: Anais | E25: 24 | G25: Ambérieu | H25: 45824 | I25: 45894 | K25: =+J25+180 -> 180 | S25: Déménagement | AL25: Déménagement autre département
A26: 1 | B26: Madame | C26: MARTINEAU | D26: Sandrine | E26: 56 | G26: Lagnieu | H26: 45821 | I26: 45894 | K26: =+J26+180 -> 180 | S26: Réorientation | T26: FT acc pro | U26: FT SIAE
A27: 1 | B27: Madame | C27: MONIER | D27: Lauren | E27: 30 | G27: Lagnieu | H27: 45819 | I27: 45894 | K27: =+J27+180 -> 180 | S27: Réorientation | T27: BGE
A28: 1 | B28: Madame | C28: MOSTEFAOUI | D28: Zaira | E28: 35 | G28: Lagnieu | H28: 45821 | I28: 45894 | K28: =+J28+180 -> 180 | S28: Réorientation | T28: Arret mal longue durée
A29: 1 | B29: Monsieur | C29: MOUSSAOUI | D29: Stéphane | E29: 42 | G29: Lagnieu | H29: 45825 | I29: 45901 | K29: =+J29+180 -> 180 | S29: Réorientation | T29: Arret mal longue durée
A30: 1 | B30: Madame | C30: MUSSARD-PARASKIOVA | D30: Marjorie | E30: 34 | G30: Lagnieu | H30: 45826 | I30: 45901 | K30: =+J30+180 -> 180 | S30: Réorientation | T30: FT acc pro | AL30: CDDde remplacement prolongé
A31: 1 | B31: Madame | C31: PONTANIER | D31: Laura | E31: 36 | F31: Baccalauréat | G31: Ambérieu | H31: 45820 | I31: 45901 | K31: =+J31+180 -> 180 | M31: SANTE | N31: environnement familial | O31: pas de véhicule | S31: Réorientation | T31: Sociale AAH | W31: P24
A32: 1 | B32: Monsieur | C32: RIVET | D32: Leo | E32: 28 | G32: Ambérieu | H32: 45758 | I32: 45910 | K32: =+J32+180 -> 180 | S32: Fin DD | AL32: A eu plusieurs missions intérim. RDV le 15/10
A33: 1 | B33: Madame | C33: ROUGER | D33: Emilie | E33: 28 | G33: Ambérieu | H33: 45777 | I33: 45908 | K33: =+J33+180 -> 180 | S33: Renonciation RSA
A34: 1 | B34: Madame | C34: SECCI | D34: Oceane | E34: 31 | G34: Ambérieu | H34: 45818 | I34: 45908 | K34: =+J34+180 -> 180 | S34: Réorientation | T34: FT acc pro | AL34: SIAE renouvellement L rénoverie
A35: 1 | B35: Madame | C35: SELEM | D35: Fathia | E35: 33 | G35: Lagnieu | H35: 45786 | I35: 45908 | K35: =+J35+180 -> 180 | S35: Réorientation | T35: Sociale maternité
A36: 1 | B36: Madame | C36: SERROUKH | D36: Fatima | E36: 50 | G36: Lagnieu | H36: 45825 | I36: 45901 | K36: =+J36+180 -> 180 | S36: Réorientation | T36: Arret mal longue durée
A37: 1 | B37: Madame | C37: SERVIOLES | D37: Vanessa | E37: 34 | G37: Lagnieu | H37: 45786 | I37: 45908 | K37: =+J37+180 -> 180 | S37: reorientation | T37: acc pro | AL37: Reprise de son emploi en CDI après congé parental
A38: 1 | B38: Madame | C38: TROTOT | D38: Estelle | E38: 28 | G38: Lagnieu | H38: 45821 | I38: 45922 | K38: =+J38+180 -> 180 | M38: SANTE | S38: Réorientation | T38: Arret mal longue durée | AL38: Mme a une réo sociale : certificat médical de son médecin.
A39: 1 | B39: Monsieur | C39: VERNE | D39: Jean-Michel | E39: 32 | G39: Ambérieu | H39: 45821 | I39: 38603 | K39: =+J39+180 -> 180 | S39: Réorientation | T39: Sociale AAH
A40: 1 | B40: Monsieur | C40: VIN | D40: Romain | E40: 36 | G40: Ambérieu | H40: 45748 | I40: 38603 | K40: =+J40+180 -> 180 | S40: Réorientation | T40: FT acco glo | U40: France Travail
A41: 1 | B41: Madame | C41: MOAMMIN | D41: Nadia | E41: 49 | G41: Ambérieu | H41: 45880 | I41: 45916 | K41: =+J41+180 -> 180 | S41: Fin DD
A42: 1 | B42: Madame | C42: SCHEID | D42: Mélanie | E42: 62 | F42: pas de diplôme | G42: Ambérieu | H42: 45881 | I42: 45915 | K42: =+J42+180 -> 180 | S42: Réorientation | T42: Sociale retraite | AL42: J'ai le récépissé de demande de demande de retraite dossier bloqué
A43: 1 | B43: Madame | C43: VENCESLAU FERNANDES | D43: Rute | E43: 33 | G43: Ambérieu | H43: 45881 | I43: 45915 | K43: =+J43+180 -> 180 | S43: Déménagement | AL43: Mme est venue au rdv et a déménagé dans une autre région.
A44: 1 | B44: Monsieur | C44: DE STEFANO | D44: Loïc | E44: 30 | F44: Bac | G44: Ambérieu | H44: 45925 | I44: 45933 | K44: =+J44+180 -> 180 | M44: soutien de sa compagne | S44: Renonciation RSA
A45: 1 | B45: Madame | C45: MALLET | D45: Emmanuelle | E45: 35 | F45: CAP, BEP | G45: Lagnieu | H45: 45841 | I45: 45894 | K45: =+J45+180 -> 180 | M45: LOGEMENT | N45: MOBILITE | S45: Déménagement | W45: P28 | AL45: Déménagement CHRS Péronnas
A46: 1 | B46: Monsieur | C46: AL AWAD | D46: Yasser | E46: 41 | F46: Aucun diplôme | G46: Amberieu | H46: 45790 | I46: 45873 | J46: 45873 | K46: =+J46+180 -> 46053 | M46: LANGUE | S46: Positive | T46: BGE | W46: P458 | AL46: Toujours à GOON . Autoentreprise démarre janvier 26
A47: 1 | B47: Madame | C47: BARBEREUX | D47: Sabrina | E47: 29 | F47: CAP, BEP | G47: Ambérieu | H47: 45820 | I47: 45905 | J47: 45905 | K47: =+J47+180 -> 46085 | M47: LOGEMENT | N47: MAMAN SOLO | O47: Surendettement | S47: Déménagement | W47: P251 | AL47: Déménagement à Chalamon. Reprise VALHORIZON
A48: 1 | B48: Madame | C48: AYUREK | D48: MELEK | E48: 53 | F48: Aucun diplôme | G48: Lagnieu | H48: 45835 | I48: 45887 | J48: 45923 | K48: =+J48+180 -> 46103 | M48: SANTE | N48: MOBILITE | S48: reorientation | T48: Arret mal longue durée | W48: P456 | AB48: 1 | AL48: Certificat médical contre-indication à l'emploi. En attente MDPH
A49: 1 | B49: Monsieur | C49: CHEKKI | D49: Radouane | E49: 36 | F49: DEUG, BTS, DUT, DEUST | G49: Lagnieu | H49: 45890 | I49: 45929 | J49: 45929 | K49: =+J49+180 -> 46109 | M49: SANTE | S49: Positive | T49: formation | U49: Formation certifiante ou qualifiante | W49: P553 | AL49: Parcours nuclèaire
A50: 1 | B50: Monsieur | C50: BOITIER | D50: Anthony | E50: 33 | F50: Aucun diplôme | G50: Lagnieu | H50: 45821 | I50: 45894 | K50: =+J50+180 -> 180 | S50: Réorientation | T50: Arret mal longue durée | W50: 1
A51: 1 | B51: Monsieur | C51: BORDIER | D51: Rémi | E51: 34 | F51: CAP, BEP | G51: Lagnieu | H51: 45833 | I51: 38603 | J51: 45924 | K51: =+J51+180 -> 46104 | M51: SANTE | N51: MOBILITE | S51: Positive | T51: BGE | W51: P253 | AL51: CM fourni /en cure dès le 9 décembre
A52: 1 | B52: Monsieur | C52: MAANANI | D52: Fouad | E52: 58 | F52: Baccalauréat | G52: Lagnieu | H52: 45868 | I52: 45922 | J52: 45908 | K52: =+J52+180 -> 46088 | M52: Pas de véhicule | N52: SANTE | S52: Réorientation | T52: Arret mal longue durée | W52: 1 | AL52: menuisier / missions à faire et voir clauses sociales
A53: 1 | B53: Madame | C53: MALIQI | D53: Mirsade | E53: 44 | F53: Aucun diplôme | G53: Ambérieu | H53: 45832 | I53: 45894 | J53: 45943 | K53: =+J53+180 -> 46123 | M53: santé | N53: âge | S53: Réorientation | T53: Arret mal longue durée | W53: P1244 | AL53: CM
A54: 1 | B54: Monsieur | C54: MOLINA GAY | D54: Romuald | E54: 46 | F54: Aucun diplôme | G54: Ambérieu | H54: 45743 | J54: 45894 | K54: =+J54+180 -> 46074 | M54: LANGUE | N54: MOBILITE | O54: SANTE | S54: Déménagement | AL54: Pas de cours de langue. Préinscription GOON Pas contente
A55: 1 | B55: Madame | C55: OUVRIER BUFFET | D55: Marilou | E55: 27 | F55: CAP, BEP | G55: Lagnieu | H55: 45819 | I55: 45901 | K55: =+J55+180 -> 180 | S55: Réorientation | T55: Sociale AAH | W55: P303 | AL55: st dans la Loire A l'emploi jusqu'en septembre. Impossible à joindre
A56: 1 | B56: Monsieur | C56: PASQUIER | D56: Yann | E56: 28 | F56: DEUG, BTS, DUT, DEUST | G56: Lagnieu | H56: 45860 | I56: 45908 | J56: 45901 | K56: =+J56+180 -> 46081 | M56: SANTE | N56: MOBILITE | S56: Renonciation RSA | W56: 1 | AL56: certif medical suivi cmp reo social (agoraphobe)
A57: 1 | B57: Monsieur | C57: RODI | D57: Florian | I57: 45993 | J57: 45908 | K57: =+J57+180 -> 46088 | M57: MOBILITE | N57: SANTE | S57: Déménagement | AL57: contrat benevole 4 mois - voir agri 01
A58: 1 | B58: Madame | C58: RUIVET | D58: Corinne | E58: 59 | G58: Lagnieu | H58: 45867 | I58: 45901 | K58: =+J58+180 -> 180 | S58: Réorientation | T58: Arret mal longue durée | AL58: Mr a déménagé depuis 2 mois dans l'Isère
A59: 1 | B59: Madame | C59: THOMASSIN | D59: Ashley | E59: 28 | F59: aucun diplôme | G59: Ambérieu | H59: 45799 | I59: 45868 | K59: =+J59+180 -> 180 | M59: SANTE | N59: MOBILITE | S59: Réorientation | T59: Arret mal longue durée | W59: P104 | AL59: cf agent de santé: médecin en arrêt rdv en nov. Mme ne peut pas marcher seule! CM en attente
A60: 1 | B60: Madame | C60: ISLAMI | D60: Haxhere | I60: 46001 | J60: 45868 | K60: =+J60+180 -> 46048 | M60: santé | N60: maman solo | S60: Fin DD | AL60: Problème de santé+, en attente de logement dans le 03
A61: 1 | B61: Monsieur | C61: ZOGHLAMI | D61: Ali | E61: 57 | F61: ingénieur | G61: Lagnieu | H61: 45868 | I61: 45922 | K61: =+J61+180 -> 180 | S61: Fin DD | AL61: A l'emploi
A62: 1 | B62: Madame | C62: TIEPOHEO | D62: Josy Nina | F62: aucun diplômeAmbérieu | J62: 45929 | K62: =+J62+180 -> 46109 | S62: Réorientation | T62: Arret mal longue durée | AB62: 1 | AL62: Mr ZOGHLAMI est en CDI depuis septembre, fin de période d'essai +
A63: 1 | B63: Madame | C63: PERRON | D63: Pauline | E63: 37 | F63: CAP, BEP | G63: Lagnieu | H63: 45883 | I63: 45929 | J63: 45889 | K63: =+J63+180 -> 46069 | M63: SANTE | S63: Fin DD | W63: P559
A64: 1 | B64: Madame | C64: CASSINOTTI | D64: Barbara | E64: 39 | G64: Lagnieu | H64: 45954 | I64: 45979 | J64: 45929 | K64: =+J64+180 -> 46109 | M64: Jeunes enfants | S64: Fin DD | AL64: mme veut assister son conjoint qui a une entreprise
A65: 1 | B65: Monsieur | C65: RUMIANO | D65: Aurélien | E65: 37 | F65: BAC+2 | G65: Ambérieu | I65: 46041 | K65: =+J65+180 -> 180 | S65: reorientaion | T65: BGE | AL65: Mme a prévenue Polel de sa situation
A66: 1 | B66: Madame | C66: GIROD | D66: Gwennaelle | E66: 44 | G66: Ambérieu | H66: 45881 | I66: 45915 | K66: =+J66+180 -> 180 | M66: SANTE | S66: Fin DD | AL66: réo BGE
A67: 1 | B67: Madame | C67: REZAEIPOUR | D67: Fatemeh | E67: 30 | G67: Ambérieu | H67: 45881 | I67: 45916 | K67: =+J67+180 -> 180 | S67: Réorientation | T67: Arret mal longue durée | AL67: Mme GIROD a un contrat de remplacement prolongé jusqu'au 07/11/25
A68: 1 | B68: Madame | C68: VLERICK | D68: Anne | E68: 55 | F68: Pas de diplôme | G68: Lagnieu | H68: 45875 | I68: 45922 | J68: 45992 | K68: =+J68+180 -> 46172 | M68: LANGUE | N68: Maman solo | S68: Fin DD | W68: P301 | AL68: Arrêt jusqu'à novembre ENVOI COURRIER 01/12 - CM
A69: 1 | B69: Madame | C69: BOYER | D69: Ghislaine | E69: 56 | G69: Lagnieu | H69: 45916 | I69: 45943 | J69: 45922 | K69: =+J69+180 -> 46102 | M69: SANTE | N69: Pas de qualif | S69: Fin DD | AL69: Mme souhaite faire une formation agent d'accueil/immersion urgente
A70: 1 | B70: Monsieur | C70: ARNAISE | D70: Guillaume | E70: 27 | F70: BAC | G70: Ambérieu | H70: 45944 | I70: 45959 | K70: =+J70+180 -> 180 | S70: Réorientation | T70: Social freins+
A71: 1 | B71: Madame | C71: MONGERAND | D71: Jhamalie | E71: 26 | F71: CAP, BEP | G71: Ambérieu | H71: 45964 | I71: 45986 | J71: 45959 | K71: =+J71+180 -> 46139 | S71: reorientation | T71: Maternité | AL71: Faire réo social CM médecin
A72: 1 | B72: Monsieur | C72: SAIRAZADA | D72: Zahibullah | J72: 45986 | K72: =+J72+180 -> 46166 | M72: MATERNITE | S72: Réorientation | T72: FT acc pro | U72: FT SIAE | AL72: Réo à faire arrêt pas doc AMELI
A73: 1 | B73: Monsieur | C73: BORRON | D73: Loic | E73: 32 | F73: BAC | G73: LAGNIEU | I73: 46007 | K73: =+J73+180 -> 180 | S73: Réorientation | T73: FT acc pro | U73: FT SIAE | AL73: travaille Brigades natures
A74: 1 | B74: Monsieur | C74: HUSSEIN | D74: Abdu | E74: 30 | F74: BAC+3 | G74: Ambérieu | H74: 45964 | J74: 45897 | K74: =+J74+180 -> 46077 | M74: LOGEMENT | S74: positive | T74: FT acc pro | U74: FT SIAE | W74: P454 | AL74: formation fle logistique pas fonctionné -démarre à la rénoverie / AGIR
A75: 1 | B75: Madame | C75: ETEMOV | D75: Nevrija | E75: 32 | G75: Lagnieu | H75: 45819 | I75: 45968 | J75: 45897 | K75: =+J75+180 -> 46077 | S75: Fin DD | AL75: A l'emploi chez CHECHOIX, redemander fiches de paie
A76: 1 | B76: Madame | C76: ANAYAT | D76: Safreen | E76: 53 | F76: Aucun diplôme | M76: SANTE | N76: LANGUE | O76: MOBILITE | S76: Réorientation | T76: Arret mal longue durée | AK76: 1 | AL76: cours de français avec bénévole CS de Saint Rambert. SORTIE
A77: 1 | B77: Monsieur | C77: MARSIGLIA | D77: Stéphane | E77: 53 | S77: Fin DD
A78: 1 | B78: Monsieur | C78: LARCHER | D78: Yannick | E78: 45 | F78: CAP, BEP | G78: Ambérieu | H78: 46135 | I78: 46163 | J78: 46163 | K78: =+J78+180 -> 46343 | S78: Réorientation | T78: BGE | V78: 46171 | AL78: entreprrise créée / suivi par le BGE
A79: 1 | B79: Monsieur | C79: TACHDJIAN | D79: Khatchik | E79: 41 | F79: Aucun diplôme | G79: Lagnieu | H79: 45918 | I79: 45943 | J79: 45943 | K79: =+J79+180 -> 46123 | Q79: changement de ref | S79: Radié suite CLI | AL79: ATTENTION PROBLEMATIQUE
A80: 1 | B80: Monsieur | C80: ENNAOURA | D80: Riyad | E80: 26 | F80: BAC+3 | G80: Amberieu | H80: 45945 | I80: 45959 | J80: 45959 | K80: =+J80+180 -> 46139 | M80: indu CAF | S80: Positive | T80: FT acc pro | U80: Interim>ou= à 970h cumulées / an | W80: 1 | AL80: Interim facteur poursuite possible en décembre
A81: 1 | B81: Madame | C81: HAMDANY / SAGGAI | D81: Sephora | E81: 27 | F81: BAC+2 | G81: Ambérieu | H81: 45945 | I81: 45966 | J81: 45966 | K81: =+J81+180 -> 46146 | M81: enfant en bas âge | S81: Déménagement | AL81: Souhaite déménager vers Lyon
A82: 1 | B82: Monsieur | C82: BALME | D82: Xavier | E82: 62 | F82: BAC+2 | G82: Lagnieu | H82: 45916 | I82: 45943 | J82: 45943 | K82: =+J82+180 -> 46123 | M82: Aucun accèsb numérique | N82: motivation | S82: Réorientation | T82: Social freins+ | W82: P302 | AL82: REO SOCIALE FAITE EN ACCORD AVEC INSERTION
A83: 1 | B83: Monsieur | C83: SOULIER | D83: Pierre | E83: 32 | F83: BAC | G83: Ambérieu | H83: 45985 | I83: 46008 | J83: 46008 | K83: =+J83+180 -> 46188 | S83: Fin DD | AL83: en formation DAEU souhaite etre pretre perçoit des ARE
A84: 1 | B84: Madame | C84: LACOSSE | D84: Alexandra | E84: 45 | F84: CAP, BEP | G84: Ambérieu | H84: 45832 | I84: 45881 | J84: 45881 | K84: =+J84+180 -> 46061 | M84: Repasser son permis | N84: Pas de formation | S84: Fin DD | W84: P65 | AL84: A des difficultés à repasser son code. Bientôt non DD - plus de RSA - touche depuis 6 mois Ne répond pas au mail, ni tel
A85: 1 | B85: Madame | C85: GRAMMATICO | D85: Valérie | E85: 62 | F85: Aucun diplôme | G85: Lagnieu | H85: 46037 | I85: 46056 | J85: 46056 | K85: =+J85+180 -> 46236 | M85: SANTE | S85: Réorientation | T85: arrêt longue maladie | AL85: reo sociale au 1er rdv. CM
A86: 1 | B86: Madame | C86: MORALES | D86: Georgie | E86: 40 | F86: Baccalauréat | G86: Ambérieu | H86: 46042 | I86: 46057 | J86: 46057 | K86: =+J86+180 -> 46237 | M86: SANTE | N86: 2 enfants AEH | S86: réorientation | T86: freins+ | W86: 1 | AI86: 1
A87: 1 | B87: Monsieur | C87: REBELO RAMALHO | D87: Luis | E87: 53 | F87: Aucun diplôme | G87: Lagnieu | H87: 46051 | K87: =+J87+180 -> 180 | S87: réorientation | T87: Arrêt longue maladie
A88: 1 | B88: Madame | C88: HAYRAPETYAN | D88: Anush | E88: 38 | F88: Master, diplôme d'études approfondies, diplôme d'études supérieures spécialisées, diplôme d'ingénieur | G88: Ambérieu | H88: 06//02/2026 | I88: 46085 | J88: 46085 | K88: =+J88+180 -> 46265 | M88: LANGUE | N88: LOGEMENT | O88: MOBILITE | S88: Déménagement | AL88: Suit formation GOON (OFII), acco CADA, AGIR
A89: 1 | B89: Monsieur | C89: BENAMARA | D89: Bounouar | E89: 50 | F89: DEUG, BTS, DUT, DEUST | G89: Ambérieu | H89: 46106 | I89: 46153 | J89: 46153 | K89: =+J89+180 -> 46333 | M89: santé | S89: Réorientation | T89: FT acc pro | AL89: Actuellement en CDI intérim, a basculé au RSA suite a un arret de travail supérieur à 1 an. Dans l'attente d'un licenciment pour inaptitude
A90: 1 | B90: Madame | C90: HIRAUX | D90: Annabelle | E90: 33 | G90: Ambérieu | H90: 45986 | I90: 46013 | K90: =+J90+180 -> 180 | M90: enfant situation de handicap | S90: Déménagement | AL90: Attente de doc AJPP DE catégorie 4
A91: 1 | B91: Madame | C91: GUILE | D91: Rolande | G91: Amberieu | I91: 46006 | K91: =+J91+180 -> 180 | S91: Déménagement | AL91: Mme travaille sur Lyon en attente de son contrat(AGIR) CONTRAT PAS TRANSMIS
A92: 1 | B92: Madame | C92: GYSSELS | D92: Emeline | E92: 26 | G92: Ambérieu | H92: 46036 | I92: 46048 | K92: =+J92+180 -> 180 | S92: Réorientation | T92: FT acc pro | AL92: Mme a un contrat intérim éventuellement jusqu'à mars.
A93: 0 | B93: Madame | C93: TOURE | D93: Marie Agnes | E93: 43 | F93: bac | G93: Ambérieu | H93: 45821 | I93: 45910 | J93: 45910 | K93: =+J93+180 -> 46090 | M93: maman solo | N93: garde d'enfant | O93: Pas de véhicule | W93: P1264 | AL93: intéressée formation SAMA
K94: =+J94+180 -> 180
K95: =+J95+180 -> 180
K96: =+J96+180 -> 180
K97: =+J97+180 -> 180
K98: =+J98+180 -> 180
K99: =+J99+180 -> 180
K100: =+J100+180 -> 180
K101: =+J101+180 -> 180
K102: =+J102+180 -> 180
...

Sheet Sanctions + absence 
C1: Absence avant signature CE | E1: Absences 2026 cumulées par mois (rdv-atelier-forum-jobdating..) Après signature CE | Q1: Niveau 1 : AVERTISSEMENT AVANT SUSPENSION | W1: Niveau 2 : suspension remobilisation | Z1: Etape 3 : Etape pluridisciplinaire CLI | AA1: 2 eme manquement (process direct etape 3)
A2: Exemple: | C2: 1 | G2: 1 | Q2: 1 | R2: 46084 | S2: 46089 | T2: =S2+15 -> 46104 | U2: 0 | V2: 1 | W2: =T2+35 -> 46139 | X2: 0 | Y2: 1 | Z2: 46147 | AC2: =AB2+35 -> 35
A3: Nom | B3: Prénom | C3: 1ER RDV | D3: 2EME | E3: 1er mois | F3: 2e mois | G3: 3e mois | H3: 4e mois | I3: 5e mois | J3: 6e mois | K3: 7e mois | L3: 8e mois | M3: 9e mois | N3: 10e mois | O3: 11e mois | P3: 12e mois | Q3: Dde etude de situation. | R3: date de la demande | S3: Date courrier CDS (voir extraction transmise) | T3: Délai 15 jours pour contact | U3: Contact BRSA - 15 jours | V3: Mail INFO CDS | W3: Délai de 35 jours pour reprendre contact | X3: le BRSA s'est manifesté ? | Y3: Mail d'info au CDS manifestation ou non dans les 35 jours | Z3: Date CLI si le BRSA ne s'est pas manifesté au bout des 35 jours | AA3: date demande étude de situation (Mail CDS) | AB3: DATE courrier CDS | AC3: 35j pour reprendre contact date butoire | AD3: DATE CLI
A4: =+'AMBERIEU LAGNIEU'!C12 -> CHAOU | B4: =+'AMBERIEU LAGNIEU'!D12 -> Bouchra | T4: =S4+15 -> 15 | W4: =T4+35 -> 50 | AC4: =AB4+35 -> 35
A5: =+'AMBERIEU LAGNIEU'!C13 -> KACZOROWSKI | B5: =+'AMBERIEU LAGNIEU'!D13 -> Gary | C5: 1 | S5: 46225 | T5: =S5+15 -> 46240 | W5: =S5+50 -> 46275 | AC5: =AB5+35 -> 35
A6: =+'AMBERIEU LAGNIEU'!C14 -> PILCH | B6: =+'AMBERIEU LAGNIEU'!D14 -> Jean-Christophe | C6: 1 | T6: =S6+15 -> 15 | W6: =S6+50 -> 50 | AC6: =AB6+35 -> 35
A7: =+'AMBERIEU LAGNIEU'!C15 -> CLOYER | B7: =+'AMBERIEU LAGNIEU'!D15 -> Jérémy | T7: =S7+15 -> 15 | W7: =S7+50 -> 50 | AC7: =AB7+35 -> 35
A8: =+'AMBERIEU LAGNIEU'!C16 -> YILMAZ | B8: =+'AMBERIEU LAGNIEU'!D16 -> Mehmet | C8: 1 | T8: =S8+15 -> 15 | W8: =S8+50 -> 50 | AC8: =AB8+35 -> 35
A9: =+'AMBERIEU LAGNIEU'!C17 -> AL ALI | B9: =+'AMBERIEU LAGNIEU'!D17 -> Abdallah | T9: =S9+15 -> 15 | W9: =S9+50 -> 50 | AC9: =AB9+35 -> 35
A10: =+'AMBERIEU LAGNIEU'!C18 -> ASLIMANI/LAAROUSSI | B10: =+'AMBERIEU LAGNIEU'!D18 -> Nasera | T10: =S10+15 -> 15 | W10: =S10+50 -> 50 | AC10: =AB10+35 -> 35
A11: =+'AMBERIEU LAGNIEU'!C18 -> ASLIMANI/LAAROUSSI | B11: =+'AMBERIEU LAGNIEU'!D18 -> Nasera | T11: =S11+15 -> 15 | W11: =S11+50 -> 50 | AC11: =AB11+35 -> 35
A12: =+'AMBERIEU LAGNIEU'!C19 -> BAJRAMOVA | B12: =+'AMBERIEU LAGNIEU'!D19 -> Juksela | T12: =S12+15 -> 15 | W12: =S12+50 -> 50 | AC12: =AB12+35 -> 35
A13: =+'AMBERIEU LAGNIEU'!C20 -> BERNARDIN | B13: =+'AMBERIEU LAGNIEU'!D20 -> Gaëlle | C13: 1 | T13: =S13+15 -> 15 | W13: =S13+50 -> 50 | AC13: =AB13+35 -> 35
A14: =+'AMBERIEU LAGNIEU'!C21 -> BORKADI-KHALDI | B14: =+'AMBERIEU LAGNIEU'!D21 -> Cindy | T14: =S14+15 -> 15 | W14: =S14+50 -> 50 | AC14: =AB14+35 -> 35
A15: =+'AMBERIEU LAGNIEU'!C22 -> CLAIRET | B15: =+'AMBERIEU LAGNIEU'!D22 -> Patrice | C15: 1 | D15: 1 | T15: =S15+15 -> 15 | W15: =S15+50 -> 50 | AC15: =AB15+35 -> 35
A16: =+'AMBERIEU LAGNIEU'!C23 -> CREPALDI | B16: =+'AMBERIEU LAGNIEU'!D23 -> David | T16: =S16+15 -> 15 | W16: =S16+50 -> 50 | AC16: =AB16+35 -> 35
A17: =+'AMBERIEU LAGNIEU'!C24 -> FARINA | B17: =+'AMBERIEU LAGNIEU'!D24 -> Yann | C17: 1 | T17: =S17+15 -> 15 | W17: =S17+50 -> 50 | AC17: =AB17+35 -> 35
A18: =+'AMBERIEU LAGNIEU'!C25 -> FERNANDES | B18: =+'AMBERIEU LAGNIEU'!D25 -> Noemie | T18: =S18+15 -> 15 | W18: =S18+50 -> 50 | AC18: =AB18+35 -> 35
A19: =+'AMBERIEU LAGNIEU'!C26 -> FOFANA | B19: =+'AMBERIEU LAGNIEU'!D26 -> Fanta | C19: 1 | T19: =S19+15 -> 15 | W19: =S19+50 -> 50 | AC19: =AB19+35 -> 35
A20: =+'AMBERIEU LAGNIEU'!C27 -> HAMOT | B20: =+'AMBERIEU LAGNIEU'!D27 -> Whitney | C20: 1 | T20: =S20+15 -> 15 | W20: =S20+50 -> 50 | AC20: =AB20+35 -> 35
A21: =+'AMBERIEU LAGNIEU'!C28 -> JUVENAL | B21: =+'AMBERIEU LAGNIEU'!D28 -> Cédric | C21: 1 | D21: 1 | T21: =S21+15 -> 15 | W21: =S21+50 -> 50 | AC21: =AB21+35 -> 35
A22: =+'AMBERIEU LAGNIEU'!C29 -> KHALO / OMAR | B22: =+'AMBERIEU LAGNIEU'!D29 -> Hanifa | C22: 1 | T22: =S22+15 -> 15 | W22: =S22+50 -> 50 | AC22: =AB22+35 -> 35 | AD22: 46266
A23: =+'AMBERIEU LAGNIEU'!C30 -> KOUASSI | B23: =+'AMBERIEU LAGNIEU'!D30 -> Amoin Désirée Prudence | T23: =S23+15 -> 15 | W23: =S23+50 -> 50 | AC23: =AB23+35 -> 35
A24: =+'AMBERIEU LAGNIEU'!C31 -> LAHURE | B24: =+'AMBERIEU LAGNIEU'!D31 -> Belinda | T24: =S24+15 -> 15 | W24: =S24+50 -> 50 | AC24: =AB24+35 -> 35
A25: =+'AMBERIEU LAGNIEU'!C32 -> LYONNET | B25: =+'AMBERIEU LAGNIEU'!D32 -> Sandrine | T25: =S25+15 -> 15 | W25: =S25+50 -> 50 | AC25: =AB25+35 -> 35
A26: =+'AMBERIEU LAGNIEU'!C33 -> MAHAMADOU | B26: =+'AMBERIEU LAGNIEU'!D33 -> Haoua | C26: 1 | T26: =S26+15 -> 15 | W26: =S26+50 -> 50 | AC26: =AB26+35 -> 35
A27: =+'AMBERIEU LAGNIEU'!C34 -> MAHESHE NKUBONAGE | B27: =+'AMBERIEU LAGNIEU'!D34 -> Nicole | T27: =S27+15 -> 15 | W27: =S27+50 -> 50 | AC27: =AB27+35 -> 35
A28: =+'AMBERIEU LAGNIEU'!C35 -> MIGUEL | B28: =+'AMBERIEU LAGNIEU'!D35 -> Herve | T28: =S28+15 -> 15 | W28: =S28+50 -> 50 | AC28: =AB28+35 -> 35
A29: =+'AMBERIEU LAGNIEU'!C36 -> MOHAMAD | B29: =+'AMBERIEU LAGNIEU'!D36 -> Shirin | T29: =S29+15 -> 15 | W29: =S29+50 -> 50 | AC29: =AB29+35 -> 35
A30: =+'AMBERIEU LAGNIEU'!C37 -> MOTA | B30: =+'AMBERIEU LAGNIEU'!D37 -> Jean Michel | C30: 1 | D30: 1 | T30: =S30+15 -> 15 | W30: =S30+50 -> 50 | AC30: =AB30+35 -> 35
A31: =+'AMBERIEU LAGNIEU'!C38 -> PIEDBOIS | B31: =+'AMBERIEU LAGNIEU'!D38 -> Youri | T31: =S31+15 -> 15 | W31: =S31+50 -> 50 | AC31: =AB31+35 -> 35
A32: =+'AMBERIEU LAGNIEU'!C39 -> POTENZIANI | B32: =+'AMBERIEU LAGNIEU'!D39 -> Nicolas | C32: 1 | T32: =S32+15 -> 15 | W32: =S32+50 -> 50 | AC32: =AB32+35 -> 35
A33: =+'AMBERIEU LAGNIEU'!C40 -> PUVILLAN | B33: =+'AMBERIEU LAGNIEU'!D40 -> Cédric | T33: =S33+15 -> 15 | W33: =S33+50 -> 50 | AC33: =AB33+35 -> 35
A34: =+'AMBERIEU LAGNIEU'!C41 -> RAMDANI | B34: =+'AMBERIEU LAGNIEU'!D41 -> Ikram | T34: =S34+15 -> 15 | W34: =S34+50 -> 50 | AC34: =AB34+35 -> 35
A35: =+'AMBERIEU LAGNIEU'!C42 -> RAMOS | B35: =+'AMBERIEU LAGNIEU'!D42 -> Audrey | T35: =S35+15 -> 15 | W35: =S35+50 -> 50 | AC35: =AB35+35 -> 35
A36: =+'AMBERIEU LAGNIEU'!C43 -> RONGIER | B36: =+'AMBERIEU LAGNIEU'!D43 -> Marine | T36: =S36+15 -> 15 | W36: =S36+50 -> 50 | AC36: =AB36+35 -> 35
A37: =+'AMBERIEU LAGNIEU'!C44 -> ROUSSEL | B37: =+'AMBERIEU LAGNIEU'!D44 -> Joanna | T37: =S37+15 -> 15 | W37: =S37+50 -> 50 | AC37: =AB37+35 -> 35
A38: =+'AMBERIEU LAGNIEU'!C45 -> SANTANA | B38: =+'AMBERIEU LAGNIEU'!D45 -> Alexis | C38: 1 | D38: 1 | T38: =S38+15 -> 15 | W38: =S38+50 -> 50 | AC38: =AB38+35 -> 35
A39: =+'AMBERIEU LAGNIEU'!C46 -> SCHEID | B39: =+'AMBERIEU LAGNIEU'!D46 -> Marie | T39: =S39+15 -> 15 | W39: =S39+50 -> 50 | AC39: =AB39+35 -> 35
A40: =+'AMBERIEU LAGNIEU'!C47 -> SEYE | B40: =+'AMBERIEU LAGNIEU'!D47 -> Mohamed | C40: 1 exc | T40: =S40+15 -> 15 | W40: =S40+50 -> 50 | AC40: =AB40+35 -> 35
A41: =+'AMBERIEU LAGNIEU'!C48 -> SOUADIA | B41: =+'AMBERIEU LAGNIEU'!D48 -> Sandrine | C41: 1 | D41: 1 | T41: =S41+15 -> 15 | W41: =S41+50 -> 50 | AC41: =AB41+35 -> 35
A42: =+'AMBERIEU LAGNIEU'!C49 -> TAHIRI | B42: =+'AMBERIEU LAGNIEU'!D49 -> Marsela | C42: 1 | T42: =S42+15 -> 15 | W42: =S42+50 -> 50 | AC42: =AB42+35 -> 35
A43: =+'AMBERIEU LAGNIEU'!C50 -> TALASH | B43: =+'AMBERIEU LAGNIEU'!D50 -> Mohamad | T43: =S43+15 -> 15 | W43: =S43+50 -> 50 | AC43: =AB43+35 -> 35
A44: =+'AMBERIEU LAGNIEU'!C51 -> THEVENON-DANIERE | B44: =+'AMBERIEU LAGNIEU'!D51 -> Géraldine | T44: =S44+15 -> 15 | W44: =S44+50 -> 50 | AC44: =AB44+35 -> 35
A45: =+'AMBERIEU LAGNIEU'!C52 -> THOMASSON | B45: =+'AMBERIEU LAGNIEU'!D52 -> Amélie | T45: =S45+15 -> 15 | W45: =S45+50 -> 50 | AC45: =AB45+35 -> 35
A46: =+'AMBERIEU LAGNIEU'!C53 -> TOURE | B46: =+'AMBERIEU LAGNIEU'!D53 -> Marie Agnes | Q46: 1 | R46: 46189 | S46: 46204 | T46: =S46+15 -> 46219 | W46: =S46+50 -> 46254 | Z46: 46241 | AC46: =AB46+35 -> 35
A47: =+'AMBERIEU LAGNIEU'!C54 -> TRONQUART | B47: =+'AMBERIEU LAGNIEU'!D54 -> Marie-Christine | C47: 1 | T47: =S47+15 -> 15 | W47: =S47+50 -> 50 | AC47: =AB47+35 -> 35
A48: =+'AMBERIEU LAGNIEU'!C55 -> TUNCAY | B48: =+'AMBERIEU LAGNIEU'!D55 -> Esira | C48: 1 exc | I48: 1 | J48: 1 | Q48: 1 | R48: 46185 | T48: =S48+15 -> 15 | W48: =S48+50 -> 50 | AC48: =AB48+35 -> 35
A49: =+'AMBERIEU LAGNIEU'!C56 -> VOGELSGSANG | B49: =+'AMBERIEU LAGNIEU'!D56 -> Emilie | T49: =S49+15 -> 15 | W49: =S49+50 -> 50 | AC49: =AB49+35 -> 35
A50: =+'AMBERIEU LAGNIEU'!C57 -> YOUNES | B50: =+'AMBERIEU LAGNIEU'!D57 -> Sarah | T50: =S50+15 -> 15 | W50: =S50+50 -> 50 | AC50: =AB50+35 -> 35
A51: =+'AMBERIEU LAGNIEU'!C58 -> ZABLOT | B51: =+'AMBERIEU LAGNIEU'!D58 -> Arthur | T51: =S51+15 -> 15 | W51: =S51+50 -> 50 | AC51: =AB51+35 -> 35
A52: =+'AMBERIEU LAGNIEU'!C59 -> CHEKKI | B52: =+'AMBERIEU LAGNIEU'!D59 -> Islam | T52: =S52+15 -> 15 | W52: =S52+50 -> 50 | AC52: =AB52+35 -> 35
A53: =+'AMBERIEU LAGNIEU'!C60 -> LAMANCHE | B53: =+'AMBERIEU LAGNIEU'!D60 -> Steve | T53: =S53+15 -> 15 | W53: =S53+50 -> 50 | AC53: =AB53+35 -> 35
A54: =+'AMBERIEU LAGNIEU'!C61 -> SLIMANI | B54: =+'AMBERIEU LAGNIEU'!D61 -> Lahouaria | T54: =S54+15 -> 15 | W54: =S54+50 -> 50 | AC54: =AB54+35 -> 35
A55: =+'AMBERIEU LAGNIEU'!#REF! -> #REF! | B55: =+'AMBERIEU LAGNIEU'!#REF! -> #REF! | Q55: 1 | R55: 46116 | S55: 46128 | T55: =S55+15 -> 46143 | U55: 0 | V55: 1 | W55: =S55+50 -> 46178 | AC55: =AB55+35 -> 35
A56: =+'AMBERIEU LAGNIEU'!C62 -> MALIQI | B56: =+'AMBERIEU LAGNIEU'!D62 -> Qendrese | T56: =S56+15 -> 15 | W56: =S56+50 -> 50 | AC56: =AB56+35 -> 35
A57: =+'AMBERIEU LAGNIEU'!C63 -> MULLAEVA | B57: =+'AMBERIEU LAGNIEU'!D63 -> Malvina | T57: =S57+15 -> 15 | W57: =S57+50 -> 50 | AC57: =AB57+35 -> 35
A58: =+'AMBERIEU LAGNIEU'!#REF! -> #REF! | B58: =+'AMBERIEU LAGNIEU'!#REF! -> #REF! | T58: =S58+15 -> 15 | W58: =S58+50 -> 50 | AC58: =AB58+35 -> 35
A59: =+'AMBERIEU LAGNIEU'!C64 -> MICHALET | B59: =+'AMBERIEU LAGNIEU'!D64 -> Jean Louis | T59: =S59+15 -> 15 | W59: =S59+50 -> 50 | AC59: =AB59+35 -> 35
A60: =+'AMBERIEU LAGNIEU'!C65 -> LOMBARD | B60: =+'AMBERIEU LAGNIEU'!D65 -> Aurelia | C60: 1 | D60: 1 | T60: =S60+15 -> 15 | W60: =S60+50 -> 50 | AC60: =AB60+35 -> 35
A61: =+'AMBERIEU LAGNIEU'!C66 -> TEKIN | B61: =+'AMBERIEU LAGNIEU'!D66 -> Vural | T61: =S61+15 -> 15 | W61: =S61+50 -> 50 | AC61: =AB61+35 -> 35
A62: =+'AMBERIEU LAGNIEU'!C67 -> VANEENOO | B62: =+'AMBERIEU LAGNIEU'!D67 -> Cedric | C62: 1 | D62: 1 | T62: =S62+15 -> 15 | W62: =S62+50 -> 50 | AC62: =AB62+35 -> 35
A63: =+'AMBERIEU LAGNIEU'!C68 -> YOUSEF | B63: =+'AMBERIEU LAGNIEU'!D68 -> Siraj | T63: =S63+15 -> 15 | W63: =S63+50 -> 50 | AC63: =AB63+35 -> 35
A64: =+'AMBERIEU LAGNIEU'!C69 -> OLRY | B64: =+'AMBERIEU LAGNIEU'!D69 -> Florence | T64: =S64+15 -> 15 | W64: =S64+50 -> 50 | AC64: =AB64+35 -> 35
A65: =+'AMBERIEU LAGNIEU'!#REF! -> #REF! | B65: =+'AMBERIEU LAGNIEU'!#REF! -> #REF! | T65: =S65+15 -> 15 | W65: =S65+50 -> 50 | AC65: =AB65+35 -> 35
A66: =+'AMBERIEU LAGNIEU'!C70 -> TURPIN | B66: =+'AMBERIEU LAGNIEU'!D70 -> Océane | C66: 1 | T66: =S66+15 -> 15 | W66: =S66+50 -> 50 | AC66: =AB66+35 -> 35
A67: =+'AMBERIEU LAGNIEU'!#REF! -> #REF! | B67: =+'AMBERIEU LAGNIEU'!#REF! -> #REF! | T67: =S67+15 -> 15 | W67: =S67+50 -> 50 | AC67: =AB67+35 -> 35
A68: =+'AMBERIEU LAGNIEU'!C71 -> CHERON | B68: =+'AMBERIEU LAGNIEU'!D71 -> Carine | T68: =S68+15 -> 15 | W68: =S68+50 -> 50 | AC68: =AB68+35 -> 35
A69: =+'AMBERIEU LAGNIEU'!C72 -> BEN BRAHIM | B69: =+'AMBERIEU LAGNIEU'!D72 -> Ridha | T69: =S69+15 -> 15 | W69: =S69+50 -> 50 | AC69: =AB69+35 -> 35
A70: =+'AMBERIEU LAGNIEU'!C73 -> MESSAI/RIBEIRO | B70: =+'AMBERIEU LAGNIEU'!D73 -> Hadda | T70: =S70+15 -> 15 | W70: =S70+50 -> 50 | AC70: =AB70+35 -> 35
A71: =+'AMBERIEU LAGNIEU'!C74 -> VEUGLE | B71: =+'AMBERIEU LAGNIEU'!D74 -> Alison | C71: 1 | T71: =S71+15 -> 15 | W71: =S71+50 -> 50 | AC71: =AB71+35 -> 35
A72: =+'AMBERIEU LAGNIEU'!C75 -> BLIN | B72: =+'AMBERIEU LAGNIEU'!D75 -> Françoise | T72: =S72+15 -> 15 | W72: =S72+50 -> 50 | AC72: =AB72+35 -> 35
A73: =+'AMBERIEU LAGNIEU'!C76 -> MARNY | B73: =+'AMBERIEU LAGNIEU'!D76 -> Christopher | J73: 1 | T73: =S73+15 -> 15 | W73: =S73+50 -> 50 | AC73: =AB73+35 -> 35
A74: =+'AMBERIEU LAGNIEU'!C77 -> PIOLAT | B74: =+'AMBERIEU LAGNIEU'!D77 -> Virginie | T74: =S74+15 -> 15 | W74: =S74+50 -> 50 | AC74: =AB74+35 -> 35
A75: =+'AMBERIEU LAGNIEU'!#REF! -> #REF! | B75: =+'AMBERIEU LAGNIEU'!#REF! -> #REF! | T75: =S75+15 -> 15 | W75: =S75+50 -> 50 | AC75: =AB75+35 -> 35
A76: =+'AMBERIEU LAGNIEU'!C78 -> CHARLIER | B76: =+'AMBERIEU LAGNIEU'!D78 -> William | C76: 1 | T76: =S76+15 -> 15 | W76: =S76+50 -> 50 | AC76: =AB76+35 -> 35
A77: =+'AMBERIEU LAGNIEU'!#REF! -> #REF! | B77: =+'AMBERIEU LAGNIEU'!#REF! -> #REF! | T77: =S77+15 -> 15 | W77: =S77+50 -> 50 | AC77: =AB77+35 -> 35
A78: =+'AMBERIEU LAGNIEU'!C79 -> HAMM | B78: =+'AMBERIEU LAGNIEU'!D79 -> Alexandre | T78: =S78+15 -> 15 | W78: =S78+50 -> 50 | AC78: =AB78+35 -> 35
A79: =+'AMBERIEU LAGNIEU'!C80 -> BOISMENU | B79: =+'AMBERIEU LAGNIEU'!D80 -> David | T79: =S79+15 -> 15 | W79: =S79+50 -> 50 | AC79: =AB79+35 -> 35
A80: =+'AMBERIEU LAGNIEU'!C81 -> TOURNU | B80: =+'AMBERIEU LAGNIEU'!D81 -> Marie-Claude | I80: 1 | T80: =S80+15 -> 15 | W80: =S80+50 -> 50 | AC80: =AB80+35 -> 35
A81: =+'AMBERIEU LAGNIEU'!#REF! -> #REF! | B81: =+'AMBERIEU LAGNIEU'!#REF! -> #REF! | T81: =S81+15 -> 15 | W81: =S81+50 -> 50 | AC81: =AB81+35 -> 35
A82: =+'AMBERIEU LAGNIEU'!C82 -> VULCAIN | B82: =+'AMBERIEU LAGNIEU'!D82 -> Alexandrine | T82: =S82+15 -> 15 | W82: =S82+50 -> 50 | AC82: =AB82+35 -> 35
A83: =+'AMBERIEU LAGNIEU'!C83 -> JUPITER | B83: =+'AMBERIEU LAGNIEU'!D83 -> Tanya | T83: =S83+15 -> 15 | W83: =S83+50 -> 50 | AC83: =AB83+35 -> 35
A84: =+'AMBERIEU LAGNIEU'!C84 -> GASHI | B84: =+'AMBERIEU LAGNIEU'!D84 -> Ramize | T84: =S84+15 -> 15 | W84: =S84+50 -> 50 | AC84: =AB84+35 -> 35
A85: =+'AMBERIEU LAGNIEU'!#REF! -> #REF! | B85: =+'AMBERIEU LAGNIEU'!#REF! -> #REF! | T85: =S85+15 -> 15 | W85: =S85+50 -> 50 | AC85: =AB85+35 -> 35
A86: =+'AMBERIEU LAGNIEU'!C85 -> KAHLAOUI | B86: =+'AMBERIEU LAGNIEU'!D85 -> Samira | J86: 1 | T86: =S86+15 -> 15 | W86: =S86+50 -> 50 | AC86: =AB86+35 -> 35
A87: =+'AMBERIEU LAGNIEU'!C86 -> VESPAZIANI | B87: =+'AMBERIEU LAGNIEU'!D86 -> Vincent | C87: 1 | T87: =S87+15 -> 15 | W87: =S87+50 -> 50 | AC87: =AB87+35 -> 35
A88: =+'AMBERIEU LAGNIEU'!#REF! -> #REF! | B88: =+'AMBERIEU LAGNIEU'!#REF! -> #REF! | T88: =S88+15 -> 15 | W88: =S88+50 -> 50 | AC88: =AB88+35 -> 35
A89: =+'AMBERIEU LAGNIEU'!#REF! -> #REF! | B89: =+'AMBERIEU LAGNIEU'!#REF! -> #REF! | T89: =S89+15 -> 15 | W89: =S89+50 -> 50 | AC89: =AB89+35 -> 35
A90: =+'AMBERIEU LAGNIEU'!C87 -> BASILE | B90: =+'AMBERIEU LAGNIEU'!D87 -> Kévin | T90: =S90+15 -> 15 | W90: =S90+50 -> 50 | AC90: =AB90+35 -> 35
A91: =+'AMBERIEU LAGNIEU'!C88 -> BLONDEAU | B91: =+'AMBERIEU LAGNIEU'!D88 -> Mandy | C91: 1 | T91: =S91+15 -> 15 | W91: =S91+50 -> 50 | AC91: =AB91+35 -> 35
A92: =+'AMBERIEU LAGNIEU'!C89 -> GUICHARD | B92: =+'AMBERIEU LAGNIEU'!D89 -> Marie | C92: 1 | T92: =S92+15 -> 15 | W92: =S92+50 -> 50 | AC92: =AB92+35 -> 35
A93: =+'AMBERIEU LAGNIEU'!C90 -> MANACH | B93: =+'AMBERIEU LAGNIEU'!D90 -> Victor | T93: =S93+15 -> 15 | W93: =S93+50 -> 50 | AC93: =AB93+35 -> 35
A94: =+'AMBERIEU LAGNIEU'!C91 -> LEBEAU | B94: =+'AMBERIEU LAGNIEU'!D91 -> Jonathan | T94: =S94+15 -> 15 | W94: =S94+50 -> 50 | AC94: =AB94+35 -> 35
A95: =+'AMBERIEU LAGNIEU'!C92 -> GOUVERNEUR | B95: =+'AMBERIEU LAGNIEU'!D92 -> Nicolas | T95: =S95+15 -> 15 | W95: =S95+50 -> 50 | AC95: =AB95+35 -> 35
A96: =+'AMBERIEU LAGNIEU'!#REF! -> #REF! | B96: =+'AMBERIEU LAGNIEU'!#REF! -> #REF! | T96: =S96+15 -> 15 | W96: =S96+50 -> 50 | AC96: =AB96+35 -> 35
A97: =+'AMBERIEU LAGNIEU'!C93 -> TAOUCHE | B97: =+'AMBERIEU LAGNIEU'!D93 -> Malika | T97: =S97+15 -> 15 | W97: =S97+50 -> 50 | AC97: =AB97+35 -> 35
A98: =+'AMBERIEU LAGNIEU'!C94 -> THOLLOT | B98: =+'AMBERIEU LAGNIEU'!D94 -> Florian | T98: =S98+15 -> 15 | W98: =S98+50 -> 50 | AC98: =AB98+35 -> 35
A99: =+'AMBERIEU LAGNIEU'!#REF! -> #REF! | B99: =+'AMBERIEU LAGNIEU'!#REF! -> #REF! | T99: =S99+15 -> 15 | W99: =S99+50 -> 50 | AC99: =AB99+35 -> 35
A100: =+'AMBERIEU LAGNIEU'!#REF! -> #REF! | B100: =+'AMBERIEU LAGNIEU'!#REF! -> #REF! | T100: =S100+15 -> 15 | W100: =S100+50 -> 50 | AC100: =AB100+35 -> 35
...

Sheet bilan de parcours  + démarches
A1: Exemples | C1: 5 | D1: 7 | E1: 9 | F1: 12 | G1: 15 | H1: 15 | I1: Renouvellement | J1: 46084 | K1: 1 | L1: 15 | M1: 15 | N1: 15 | O1: 15 | P1: 15 | Q1: 15 | R1: 46268 | S1: Reo FT
C3: nombres de démarches / par semaine | I3: 7 eme mois Bilan fin de parcours | L3: nombres de démarches / par semaine | R3: 14éme mois Bilan définitif
A4: nom | B4: prenom | C4: 1er mois | D4: 2e mois | E4: 3e mois | F4: 4e mois | G4: 5e mois | H4: 6e mois | I4: demande | J4: Date | K4: Renouvellement | L4: 8e mois | M4: 9e mois | N4: 10e mois | O4: 11e mois | P4: 12e mois | Q4: 13e mois | R4: Date | S4: Préco Réo
A5: =+'AMBERIEU LAGNIEU'!C12 -> CHAOU | B5: =+'AMBERIEU LAGNIEU'!D12 -> Bouchra
A6: =+'AMBERIEU LAGNIEU'!C13 -> KACZOROWSKI | B6: =+'AMBERIEU LAGNIEU'!D13 -> Gary
A7: =+'AMBERIEU LAGNIEU'!C14 -> PILCH | B7: =+'AMBERIEU LAGNIEU'!D14 -> Jean-Christophe
A8: =+'AMBERIEU LAGNIEU'!C15 -> CLOYER | B8: =+'AMBERIEU LAGNIEU'!D15 -> Jérémy
A9: =+'AMBERIEU LAGNIEU'!C16 -> YILMAZ | B9: =+'AMBERIEU LAGNIEU'!D16 -> Mehmet
A10: =+'AMBERIEU LAGNIEU'!C17 -> AL ALI | B10: =+'AMBERIEU LAGNIEU'!D17 -> Abdallah
A11: =+'AMBERIEU LAGNIEU'!#REF! -> #REF! | B11: =+'AMBERIEU LAGNIEU'!#REF! -> #REF!
A12: =+'AMBERIEU LAGNIEU'!C18 -> ASLIMANI/LAAROUSSI | B12: =+'AMBERIEU LAGNIEU'!D18 -> Nasera
A13: =+'AMBERIEU LAGNIEU'!C19 -> BAJRAMOVA | B13: =+'AMBERIEU LAGNIEU'!D19 -> Juksela
A14: =+'AMBERIEU LAGNIEU'!C20 -> BERNARDIN | B14: =+'AMBERIEU LAGNIEU'!D20 -> Gaëlle
A15: =+'AMBERIEU LAGNIEU'!C21 -> BORKADI-KHALDI | B15: =+'AMBERIEU LAGNIEU'!D21 -> Cindy
A16: =+'AMBERIEU LAGNIEU'!C22 -> CLAIRET | B16: =+'AMBERIEU LAGNIEU'!D22 -> Patrice
A17: =+'AMBERIEU LAGNIEU'!C23 -> CREPALDI | B17: =+'AMBERIEU LAGNIEU'!D23 -> David
A18: =+'AMBERIEU LAGNIEU'!C24 -> FARINA | B18: =+'AMBERIEU LAGNIEU'!D24 -> Yann
A19: =+'AMBERIEU LAGNIEU'!C25 -> FERNANDES | B19: =+'AMBERIEU LAGNIEU'!D25 -> Noemie
A20: =+'AMBERIEU LAGNIEU'!C26 -> FOFANA | B20: =+'AMBERIEU LAGNIEU'!D26 -> Fanta
A21: =+'AMBERIEU LAGNIEU'!C27 -> HAMOT | B21: =+'AMBERIEU LAGNIEU'!D27 -> Whitney
A22: =+'AMBERIEU LAGNIEU'!C28 -> JUVENAL | B22: =+'AMBERIEU LAGNIEU'!D28 -> Cédric
A23: =+'AMBERIEU LAGNIEU'!C29 -> KHALO / OMAR | B23: =+'AMBERIEU LAGNIEU'!D29 -> Hanifa
... A55: =+'AMBERIEU LAGNIEU'!C61 -> SLIMANI | B55: =+'AMBERIEU LAGNIEU'!D61 -> Lahouaria
A56: =+'AMBERIEU LAGNIEU'!#REF! -> #REF! | B56: =+'AMBERIEU LAGNIEU'!#REF! -> #REF!
A57: =+'AMBERIEU LAGNIEU'!C62 -> MALIQI | B57: =+'AMBERIEU LAGNIEU'!D62 -> Qendrese
A58: =+'AMBERIEU LAGNIEU'!C63 -> MULLAEVA | B58: =+'AMBERIEU LAGNIEU'!D63 -> Malvina
A59: =+'AMBERIEU LAGNIEU'!#REF! -> #REF! | B59: =+'AMBERIEU LAGNIEU'!#REF! -> #REF!
A60: =+'AMBERIEU LAGNIEU'!C64 -> MICHALET | B60: =+'AMBERIEU LAGNIEU'!D64 -> Jean Louis
A61: =+'AMBERIEU LAGNIEU'!C65 -> LOMBARD | B61: =+'AMBERIEU LAGNIEU'!D65 -> Aurelia
A62: =+'AMBERIEU LAGNIEU'!C66 -> TEKIN | B62: =+'AMBERIEU LAGNIEU'!D66 -> Vural
A63: =+'AMBERIEU LAGNIEU'!C67 -> VANEENOO | B63: =+'AMBERIEU LAGNIEU'!D67 -> Cedric
A64: =+'AMBERIEU LAGNIEU'!C68 -> YOUSEF | B64: =+'AMBERIEU LAGNIEU'!D68 -> Siraj
A65: =+'AMBERIEU LAGNIEU'!C69 -> OLRY | B65: =+'AMBERIEU LAGNIEU'!D69 -> Florence
A66: =+'AMBERIEU LAGNIEU'!#REF! -> #REF! | B66: =+'AMBERIEU LAGNIEU'!#REF! -> #REF!
A67: =+'AMBERIEU LAGNIEU'!C70 -> TURPIN | B67: =+'AMBERIEU LAGNIEU'!D70 -> Océane
A68: =+'AMBERIEU LAGNIEU'!#REF! -> #REF! | B68: =+'AMBERIEU LAGNIEU'!#REF! -> #REF!
A69: =+'AMBERIEU LAGNIEU'!C71 -> CHERON | B69: =+'AMBERIEU LAGNIEU'!D71 -> Carine
A70: =+'AMBERIEU LAGNIEU'!C72 -> BEN BRAHIM | B70: =+'AMBERIEU LAGNIEU'!D72 -> Ridha
A71: =+'AMBERIEU LAGNIEU'!C73 -> MESSAI/RIBEIRO | B71: =+'AMBERIEU LAGNIEU'!D73 -> Hadda
A72: =+'AMBERIEU LAGNIEU'!C74 -> VEUGLE | B72: =+'AMBERIEU LAGNIEU'!D74 -> Alison
A73: =+'AMBERIEU LAGNIEU'!C75 -> BLIN | B73: =+'AMBERIEU LAGNIEU'!D75 -> Françoise
A74: =+'AMBERIEU LAGNIEU'!C76 -> MARNY | B74: =+'AMBERIEU LAGNIEU'!D76 -> Christopher
A75: =+'AMBERIEU LAGNIEU'!C77 -> PIOLAT | B75: =+'AMBERIEU LAGNIEU'!D77 -> Virginie
A76: =+'AMBERIEU LAGNIEU'!#REF! -> #REF! | B76: =+'AMBERIEU LAGNIEU'!#REF! -> #REF!
A77: =+'AMBERIEU LAGNIEU'!C78 -> CHARLIER | B77: =+'AMBERIEU LAGNIEU'!D78 -> William
A78: =+'AMBERIEU LAGNIEU'!#REF! -> #REF! | B78: =+'AMBERIEU LAGNIEU'!#REF! -> #REF!
A79: =+'AMBERIEU LAGNIEU'!C79 -> HAMM | B79: =+'AMBERIEU LAGNIEU'!D79 -> Alexandre
A80: =+'AMBERIEU LAGNIEU'!C80 -> BOISMENU | B80: =+'AMBERIEU LAGNIEU'!D80 -> David
A81: =+'AMBERIEU LAGNIEU'!C81 -> TOURNU | B81: =+'AMBERIEU LAGNIEU'!D81 -> Marie-Claude
A82: =+'AMBERIEU LAGNIEU'!#REF! -> #REF! | B82: =+'AMBERIEU LAGNIEU'!#REF! -> #REF!
A83: =+'AMBERIEU LAGNIEU'!C82 -> VULCAIN | B83: =+'AMBERIEU LAGNIEU'!D82 -> Alexandrine
A84: =+'AMBERIEU LAGNIEU'!C83 -> JUPITER | B84: =+'AMBERIEU LAGNIEU'!D83 -> Tanya
A85: =+'AMBERIEU LAGNIEU'!C84 -> GASHI | B85: =+'AMBERIEU LAGNIEU'!D84 -> Ramize
A86: =+'AMBERIEU LAGNIEU'!#REF! -> #REF! | B86: =+'AMBERIEU LAGNIEU'!#REF! -> #REF!
A87: =+'AMBERIEU LAGNIEU'!C85 -> KAHLAOUI | B87: =+'AMBERIEU LAGNIEU'!D85 -> Samira
A88: =+'AMBERIEU LAGNIEU'!C86 -> VESPAZIANI | B88: =+'AMBERIEU LAGNIEU'!D86 -> Vincent
A89: =+'AMBERIEU LAGNIEU'!#REF! -> #REF! | B89: =+'AMBERIEU LAGNIEU'!#REF! -> #REF!
A90: =+'AMBERIEU LAGNIEU'!#REF! -> #REF! | B90: =+'AMBERIEU LAGNIEU'!#REF! -> #REF!
A91: =+'AMBERIEU LAGNIEU'!C87 -> BASILE | B91: =+'AMBERIEU LAGNIEU'!D87 -> Kévin
A92: =+'AMBERIEU LAGNIEU'!C88 -> BLONDEAU | B92: =+'AMBERIEU LAGNIEU'!D88 -> Mandy
A93: =+'AMBERIEU LAGNIEU'!C89 -> GUICHARD | B93: =+'AMBERIEU LAGNIEU'!D89 -> Marie
A94: =+'AMBERIEU LAGNIEU'!C90 -> MANACH | B94: =+'AMBERIEU LAGNIEU'!D90 -> Victor
A95: =+'AMBERIEU LAGNIEU'!C91 -> LEBEAU | B95: =+'AMBERIEU LAGNIEU'!D91 -> Jonathan
A96: =+'AMBERIEU LAGNIEU'!C92 -> GOUVERNEUR | B96: =+'AMBERIEU LAGNIEU'!D92 -> Nicolas
A97: =+'AMBERIEU LAGNIEU'!#REF! -> #REF! | B97: =+'AMBERIEU LAGNIEU'!#REF! -> #REF!
A98: =+'AMBERIEU LAGNIEU'!C93 -> TAOUCHE | B98: =+'AMBERIEU LAGNIEU'!D93 -> Malika
A99: =+'AMBERIEU LAGNIEU'!C94 -> THOLLOT | B99: =+'AMBERIEU LAGNIEU'!D94 -> Florian
A100: =+'AMBERIEU LAGNIEU'!#REF! -> #REF! | B100: =+'AMBERIEU LAGNIEU'!#REF! -> #REF!
A101: =+'AMBERIEU LAGNIEU'!#REF! -> #REF! | B101: =+'AMBERIEU LAGNIEU'!#REF! -> #REF!
A102: =+'AMBERIEU LAGNIEU'!C95 -> LABARRIERE | B102: =+'AMBERIEU LAGNIEU'!D95 -> Paul Emile
A103: =+'AMBERIEU LAGNIEU'!C96 -> GUEPRATTE | B103: =+'AMBERIEU LAGNIEU'!D96 -> Ronny
A104: =+'AMBERIEU LAGNIEU'!C97 -> GABORIT | B104: =+'AMBERIEU LAGNIEU'!D97 -> Edwige
A105: =+'AMBERIEU LAGNIEU'!C98 -> KHAN | B105: =+'AMBERIEU LAGNIEU'!D98 -> Tahira
A106: =+'AMBERIEU LAGNIEU'!C99 -> NDOJ | B106: =+'AMBERIEU LAGNIEU'!D99 -> Dava
A107: =+'AMBERIEU LAGNIEU'!#REF! -> #REF! | B107: =+'AMBERIEU LAGNIEU'!#REF! -> #REF!
A108: =+'AMBERIEU LAGNIEU'!C100 -> VANEENOO | B108: =+'AMBERIEU LAGNIEU'!D100 -> Jérémy
A109: =+'AMBERIEU LAGNIEU'!C101 -> GALLE | B109: =+'AMBERIEU LAGNIEU'!D101 -> Aurélie
A110: =+'AMBERIEU LAGNIEU'!C102 -> AROUMOUGAM | B110: =+'AMBERIEU LAGNIEU'!D102 -> Selvaperoumal
A111: =+'AMBERIEU LAGNIEU'!C103 -> GROSSEPIECE | B111: =+'AMBERIEU LAGNIEU'!D103 -> Laetitia
A112: =+'AMBERIEU LAGNIEU'!C104 -> MESSAHEL | B112: =+'AMBERIEU LAGNIEU'!D104 -> Malika
A113: =+'AMBERIEU LAGNIEU'!C105 -> CHTOPCZYK | B113: =+'AMBERIEU LAGNIEU'!D105 -> Johan
A114: =+'AMBERIEU LAGNIEU'!C106 -> CHAPUIS | B114: =+'AMBERIEU LAGNIEU'!D106 -> Hervé
A115: =+'AMBERIEU LAGNIEU'!C107 -> Mendes Vaz Amarante | B115: =+'AMBERIEU LAGNIEU'!D107 -> Kévin
A116: =+'AMBERIEU LAGNIEU'!C108 -> SONTHONNAX | B116: =+'AMBERIEU LAGNIEU'!D108 -> Alexandre
A117: =+'AMBERIEU LAGNIEU'!C109 -> LAROUI | B117: =+'AMBERIEU LAGNIEU'!D109 -> Nadia
A118: =+'AMBERIEU LAGNIEU'!C110 -> KHENDOUDI | B118: =+'AMBERIEU LAGNIEU'!D110 -> Samera
A119: =+'AMBERIEU LAGNIEU'!C111 -> POGGI | B119: =+'AMBERIEU LAGNIEU'!D111 -> Melvin
A120: =+'AMBERIEU LAGNIEU'!#REF! -> #REF! | B120: =+'AMBERIEU LAGNIEU'!#REF! -> #REF!
A121: =+'AMBERIEU LAGNIEU'!C112 -> DONER | B121: =+'AMBERIEU LAGNIEU'!D112 -> Zehra
A122: =+'AMBERIEU LAGNIEU'!C113 -> CORNIGLION | B122: =+'AMBERIEU LAGNIEU'!D113 -> Didier
A123: =+'AMBERIEU LAGNIEU'!C114 -> DESORMAIS | B123: =+'AMBERIEU LAGNIEU'!D114 -> Dorian
A124: =+'AMBERIEU LAGNIEU'!C127 -> DUWAT | B124: =+'AMBERIEU LAGNIEU'!D127 -> Grégory
A125: =+'AMBERIEU LAGNIEU'!C128 -> GROUX | B125: =+'AMBERIEU LAGNIEU'!D128 -> Séverine
A126: =+'AMBERIEU LAGNIEU'!C134 -> DUROSIER | B126: =+'AMBERIEU LAGNIEU'!D134 -> Noella
A127: =+'AMBERIEU LAGNIEU'!#REF! -> #REF! | B127: =+'AMBERIEU LAGNIEU'!#REF! -> #REF!
A128: =+'AMBERIEU LAGNIEU'!#REF! -> #REF! | B128: =+'AMBERIEU LAGNIEU'!#REF! -> #REF!
A129: =+'AMBERIEU LAGNIEU'!#REF! -> #REF! | B129: =+'AMBERIEU LAGNIEU'!#REF! -> #REF!
A130: =+'AMBERIEU LAGNIEU'!#REF! -> #REF! | B130: =+'AMBERIEU LAGNIEU'!#REF! -> #REF!
A131: =+'AMBERIEU LAGNIEU'!#REF! -> #REF! | B131: =+'AMBERIEU LAGNIEU'!#REF! -> #REF!
A132: =+'AMBERIEU LAGNIEU'!#REF! -> #REF! | B132: =+'AMBERIEU LAGNIEU'!#REF! -> #REF!
...

Sheet Tableau croisé NE PAS TOUCHER
A3: Sanction et Absence | E3: Bilan de parcours + démarches
A4: Nombre de 1ER RDV | B4: 31 | E4: Somme de 1er mois
A5: Somme de 2EME | B5: 7 | E5: Somme de 2e mois
A6: Nombre de 1er mois | E6: Somme de 3e mois
A7: Nombre de 2e mois | E7: Somme de 4e mois
A8: Somme de 3e mois | E8: Somme de 5e mois
A9: Somme de 4e mois | E9: Somme de 6e mois
A10: Somme de 5e mois | B10: 2 | E10: Nombre de demande
A11: Nombre de 6e mois | B11: 3 | E11: Somme de Renouvellement
A12: Nombre de 7e mois | E12: Somme de 8e mois
A13: Nombre de 8e mois | E13: Somme de 9e mois
A14: Nombre de 9e mois | E14: Somme de 10e mois
A15: Nombre de 10e mois | E15: Somme de 11e mois
A16: Nombre de 11e mois | E16: Somme de 12e mois
A17: Nombre de 12e mois | E17: Somme de Préco Réo
A18: Somme de date demande étude de situation (Mail CDS)
A19: Somme de Dde etude de situation. | B19: 1
A21: Valeurs | C21: SEXE | D21: Nombre de H/F | E21: SORTIES | F21: Nombre de Motif de sortie | G21: Nombre de MOTIF de la REO
A22: Moyenne de âge | B22: 39.275449 | C22: Madame | D22: 56 | E22: autre | F22: 1 | G22: 1
A23: Nombre de C.E SIGNE | B23: 110 | C23: Monsieur | D23: 44 | E23: Arret mal longue durée | F23: 1 | G23: 1
A24: Nombre de BILAN PARCOURS (7eme mois) | C24: (vide) | E24: Fin DD | F24: 1
A25: Somme de PMSMP (1 = oui) | C25: Madame | D25: 8 | E25: (vide) | F25: 1
A26: Nombre de H/F | B26: 177 | C26: Mme | D26: 1 | E26: Réorientation | F26: 1 | G26: 1
A27: Nombre de Saisie FSE | B27: 51 | C27: Monsieur | D27: 4 | E27: arrêt longue maladie | F27: 1 | G27: 1
A28: Nombre de AIDE FINANCIERE | C28: Total général | D28: 113 | E28: (vide)
E29: (vide)
E30: reorientation | F30: 1 | G30: 1
A31: SORTIES POSITIVES | B31: Nombre de types | E31: FT acc pro | F31: 1 | G31: 1
A32: (vide) | E32: Total général | F32: 4 | G32: 3
A33: Total général

Sheet liste deroulante
A1: Années après le Bac | B1: Titre du diplôme | C1: Niveau de diplôme | F1: Réorientation | H1: Motifs Sorties | J1: Sorties
B2: Aucun diplôme | F2: Sociale AAH | G2: Emploi | H2: Positive | J2: CDI >ou= 24h
A3: - | B3: CAP, BEP | C3: 3 (anciennement V) | E3: H | F3: Sociale retraite | G3: Formation | H3: Réorientation | J3: CDD +6mois >ou=254h
A4: Bac | B4: Baccalauréat | C4: 4 (anciennement IV) | E4: F | F4: Sociale maternité | G4: Créa entreprise | H4: Déménagement | J4: Créa
A5: Bac+2 | B5: DEUG, BTS, DUT, DEUST | C5: 5 (anciennement III) | F5: Social freins+ | G5: France Travail | H5: Fin DD | J5: Interim>ou= à 970h cumulées / an
A6: Bac+3 | B6: Licence, licence professionnelle | C6: 6 (anciennement II) | F6: Arret mal longue durée | H6: Décès | J6: Stagiaire de la formation
A7: Bac+4 | B7: Maîtrise, master 1 | C7: 6 (anciennement II) | F7: BGE | H7: Renonciation RSA | J7: SIAE (FT)
A8: Bac+5 | B8: Master, diplôme d'études approfondies, diplôme d'études supérieures spécialisées, diplôme d'ingénieur | C8: 7 (anciennement I) | F8: MSA | H8: Incarcération
A9: Bac+8 | B9: Doctorat, habilitation à diriger des recherches | C9: 8 (anciennement I) | F9: FT acc pro | H9: Mauvaise orientation
F10: FT acco glo | H10: Fin bilan parcours
D11: CLI | H11: Radié suite CLI
B12: freins | D12: 1
B13: mobilité | D13: 0
B14: garde enfants
E15: OUI
A16: CDS | B16: Oyonnax | E16: NON | G16: Resultat bilan parcours
B17: Nantua | G17: Réo FT | H17: Reo FT
B18: Belley | G18: Renouvellement | H18: Réo sociale
B19: Valserhone | G19: Tripartite
B20: Pays de Gex | G20: BGE
B21: Croix Blanche
B22: Pierre Goujon
B23: Montrevel
B24: Pont de Vaux
B25: St Didier sur Chalaronne
B26: Trevoux
B27: Chatillon sur Chalaronne
B28: Amberieu
B29: Lagnieu
B30: Miribel

Sheet CODIFICATION ACTIVITE
A3: Besoin
A4: Ordre | B4: Code | C4: Libellé | D4: Libellé | E4: Libellé | F4: Volume horaire Hedbomadaire
A5: 1 | B5: P01 | C5: Choisir un métier | D5: Identification de ses points forts et de ses compétences | E5: Identifier ses points forts et ses compétences | F5: 3
D6: Information sur un métier ou un secteur d'activité | E6: S'informer sur un métier ou un secteur d'activité | F6: 3
D7: Observation en entreprise | E7: Réaliser une observation en entreprise | F7: 3
D8: Enquête métier afin de mieux connaître un métier | E8: Réaliser une enquête métier | F8: 3
D9: Participation à un salon ou un forum pour s'informer sur un métier | E9: Participer à un salon ou un forum pour s'informer sur un métier | F9: 3
A10: 2 | B10: P02 | C10: Se former | D10: Information sur un projet de formation ou de Validation des acquis de l'expérience | E10: S'informer sur un projet de formation ou de validation des acquis de l'expérience | F10: 3
D11: Montage d'un dossier d’inscription à une formation | E11: Monter son dossier de formation | F11: 3
D12: Participation à une formation | E12: Participer à une formation | F12: 35
D13: Participation à un salon ou un forum formation | E13: Participer à un salon ou un forum formation | F13: 3
D14: Initiation à l'informatique ou à Internet | E14: S'initier à l'informatique ou à Internet | F14: 3
D15: Participation à un dispositif d'insertion | E15: Participer à un dispositif d'insertion | F15: 35
A16: 3 | B16: P03 | C16: Préparer sa candidature | D16: Réalisation d'une démarche de VAE | E16: Réaliser une démarche de VAE | F16: 3
D17: Préparation de ses candidatures (CV, lettre de motivation, book) | E17: Réaliser ou mettre à jour son CV sa lettre de motivation ou son portfolio | F17: 3
E18: Développer son réseau | F18: 3
E19: S'inscrire ou compléter son profil sur un réseau professionnel | F19: 3
E20: Réaliser des activités de bénévolat | F20: 5
E21: Organiser ses démarches de recherche d’emploi | F21: 3
E22: Compléter ou publier son profil de compétence | F22: 3
A23: 4 | C23: Trouver un emploi | D23: Recherche d'offres d'emploi ou d'entreprises | E23: Rechercher des offres d'emploi ou d'entreprises | F23: 3
D24: Participation à un salon ou un forum pour rechercher des offres | E24: Participer à un salon ou un forum pour rechercher des offres d'emploi | F24: 3
D25: Réponse à des offres d'emploi | E25: Répondre à des offres d'emploi | F25: 3
D26: Candidatures spontanées | E26: Effectuer des candidatures spontanées | F26: 3
D27: Réalisation du suivi de ses candidatures et relance des recruteurs | E27: Réaliser le suivi de ses candidatures et relancer des recruteurs | F27: 3
D28: Préparation des entretiens d'embauche | E28: Préparer un entretien d'embauche | F28: 3
D29: Réalisation d'entretiens d'embauche | E29: Réaliser un entretien d'embauche | F29: 3
D30: Passation de tests de recrutement (concours, casting…) | E30: Passer des tests de recrutement (concours, casting…) | F30: 3
D31: Réalisation d'une mise en situation professionnelle dans une entreprise | E31: Réaliser une mise en situation professionnelle dans une entreprise | F31: 35
D32: Recherche de missions de service civique | E32: Rechercher des missions de service civique | F32: 3
E33: S'inscrire sur une plateforme de recrutement (agence d'intérim, cabinet de recrutement, site spécialisé…) | F33: 3
A34: 5 | B34: P05 | C34: Ma création et reprise d'entreprise | D34: Recherches pour créer ou reprendre une entreprise | E34: Effectuer des recherches pour créer ou reprendre une entreprise | F34: 3
D35: Réalisation d'une étude de marché auprès de prospects/clients /fournisseurs | E35: Réaliser une étude de marché auprès de prospects/clients /fournisseurs | F35: 3
D36: Participation à un salon ou forum pour s'informer sur la création entreprise | E36: Participer à un salon ou forum pour s'informer sur la création d'entreprise | F36: 3
D37: Réalisation d'un business plan afin de préparer la création de son entreprise | E37: Réaliser un business plan afin de préparer la création de son entreprise | F37: 3
D38: Prise de RDV avec des organismes financiers | E38: Prendre rendez-vous avec des organismes financiers | F38: 3
D39: Réalisation de démarches juridiques de création d'entreprise | E39: Réaliser des démarches juridiques de création d'entreprise | F39: 3
D40: Réalisation d'actions de communication pour faire connaitre son entreprise | E40: Réaliser des actions de communication pour faire connaître son entreprise | F40: 3
D41: Prospection pour développer sa clientèle | E41: Prospecter pour développer sa clientèle | F41: 3
D42: Développement de nouveaux partenariats | E42: Développer de nouveaux partenariats | F42: 3
D43: Mise en œuvre d'actions de fidélisation de ses clients ou utilisateurs | E43: Mettre en œuvre des actions de fidélisation de ses clients ou utilisateurs | F43: 3
D44: Organisation de son activité de dirigeant et de gestion de son entreprise | E44: Organiser son activité de dirigeant et la gestion de son entreprise | F44: 3
D45: Diversification de ses activités en proposant de nouveaux services ou produits | E45: Développer son entreprise en diversifiant ses activités | F45: 3
D46: Développement de son entreprise en procédant à des recrutements | E46: Développer son entreprise en procédant à des recrutements | F46: 3
D47: Réalisation d'autres actions pour développer son entreprise | E47: Réaliser d'autres actions pour développer son entreprise | F47: 3
A48: 6 | B48: P06 | C48: Entretiens avec un conseiller | D48: Réaliser un entretien avec un conseiller | E48: Réaliser un entretien avec un conseiller | F48: 1
A49: 8 | B49: P08 | C49: Développer sa mobilité | E49: Réaliser une démarche pour accéder aux transports en commun | F49: 1
E50: Mobiliser le réseau de transports à la demande | F50: 3
E51: Acquérir un moyen de locomotion | F51: 2
E52: Mobiliser un garage solidaire | F52: 3
E53: Constituer un dossier de financement pour l'achat d'un véhicule | F53: 5
E54: Louer un moyen de locomotion | F54: 1
E55: Participer à un rendez-vous avec un partenaire mobilité | F55: 1
E56: Constituer un dossier d'aide à la mobilité | F56: 3
E57: Résoudre ses problématiques de mobilité psychologique | F57: 3
E58: Entretenir ou réparer son véhicule | F58: 3
E59: Mettre en place une solution de covoiturage | F59: 3
E60: S'inscrire en auto-école | F60: 1
E61: Participer à un cours de code/conduite | F61: 1
... E64: Récupérer son permis de conduire | F64: 1
A65: 9 | B65: P09 | C65: Accéder au numérique et en maîtriser les fondamentaux | E65: Acquérir un équipement informatique | F65: 3
E66: Accéder à une connexion Internet | F66: 3
E67: Réaliser le test PIX | F67: 1
E68: Participer à un rendez-vous avec un partenaire "numérique" | F68: 1
E69: Participer à un cours d'initiation à l'informatique/internet | F69: 5
E70: S'informer/se former à la confidentialité sur internet (RGPD…) | F70: 3
E71: Solliciter l'écrivain public numérique | F71: 2
E72: Participer à une formation numérique (PIX) | F72: 7
D73: Evaluation des compétences numériques | E73: Évaluer ses compétences numériques | F73: 1
A74: 10 | B74: P10 | C74: Faire face à des difficultés administratives et juridiques | E74: S'informer sur les voies de recours suite à une discrimination | F74: 3
E75: Réaliser des démarches administratives liées à l'état civil | F75: 3
E76: Participer à un rendez-vous avec un partenaire "administratif" | F76: 1
E77: Réaliser une demande de procédure judiciaire | F77: 2
E78: Participer à un rendez-vous avec un partenaire "juridique" | F78: 1
E79: Faire une demande d'aide juridictionnelle, conseil juridique | F79: 3
E80: Réaliser une déclaration de situation (impôt, CAF…) | F80: 1
E81: Réaliser une demande à la préfecture | F81: 4
E82: Classer ses documents administratifs | F82: 2
E83: Réaliser une demande de prestation ou droit (CAF, MSA…) | F83: 3
E84: Accéder aux informations et aides disponibles pour les aidants | F84: 3
E85: S'actualiser et rester inscrit à France Travail | F85: 1
A86: 11 | B86: P11 | C86: Faire face à des difficultés de logement | E86: Participer à un rendez-vous avec un partenaire logement | F86: 1
E87: Réaliser un diagnostic de précarité énergétique | F87: 5
E88: Réaliser une demande d'aide d'amélioration de l'habitat | F88: 3
E89: Monter un dossier de demande d'aide au logement (DALO, DAHO…) | F89: 3
E90: Appeler le 115 | F90: 2
E91: Réaliser une demande de logement social | F91: 3
E92: Réaliser une visite de logement | F92: 3
E93: Réaliser une demande de domiciliation auprès d'un CCAS | F93: 3
E94: Réaliser des démarches dans le cadre du maintien dans le logement | F94: 3
E95: Effectuer des démarches dans le cadre d'une procédure d'expulsion | F95: 3
A96: 12 | B96: P12 | C96: Faire face à des difficultés financières | E96: Réaliser une demande de plan de surendettement | F96: 5
E97: Faire valoir ses droits à une pension (retraite, réversion...) | F97: 2
E98: Réaliser une demande d'aide alimentaire | F98: 1
E99: Participer à un rendez-vous avec un partenaire "Budget/Finance" | F99: 1
E100: Ouvrir un compte bancaire | F100: 3
E101: Réaliser une demande de micro-crédit social | F101: 2
E102: Réaliser une demande de carte solidaire (SNCF, Pass Solidaire) | F102: 3
E103: Monter un dossier financier (microcrédit, FIP, FSL, FAJ...) | F103: 8
E104: Se rendre dans un point conseil budget | F104: 3
...

Sheet Feuil1
A1: Nom | B1: Prénom | C1: 1er mois | D1: 2e mois | E1: 3e mois | F1: 4e mois | G1: 5e mois | H1: 6e mois | I1: 7e mois | J1: 8e mois | K1: 9e mois | L1: 10e mois | M1: 11e mois | N1: 12e mois | O1: Dde etude de situation. | P1: date de la demande | Q1: Date courrier CDS (voir extraction transmise) | R1: Délai 15 jours pour contact | S1: Contact BRSA - 15 jours | T1: Mail INFO CDS | U1: Délai de 35 jours pour reprendre contact | V1: le BRSA s'est manifesté ? | W1: Mail d'info au CDS manifestation ou non dans les 35 jours | X1: Date CLI si le BRSA ne s'est pas manifesté au bout des 35 jours | Y1: date demande étude de situation (Mail CDS) | Z1: DATE courrier CDS | AA1: 35j pour reprendre contact date butoire | AB1: DATE CLI
A2: AHAMADA | B2: Fatima | E2: 1 | F2: 1 | O2: 1 | P2: 46052 | Q2: 46057 | R2: 46072 | S2: 0 | T2: 1 | U2: 46107 | Y2: 1 | Z2: 46122 | AA2: 46157
A3: XHAFAJ | B3: IGBALLE | R3: 15 | U3: 50 | AA3: 35
A4: AKKAOUI | B4: Badr | O4: 1 | P4: 46049 | Q4: 46054 | R4: 46069 | U4: 46104 | AA4: 35
A5: ALI ABDULLEH | B5: Maymoun | R5: 15 | U5: 50 | AA5: 35
A6: AMIRAT | B6: Saliha | R6: 15 | U6: 50 | AA6: 35
A7: BA | B7: N Dela | F7: 1 | G7: 1 | O7: 1 | P7: 46049 | Q7: 46054 | R7: 46069 | S7: 1 | T7: 1 | U7: 46104 | AA7: 35
A8: BAKHTOKHIL | B8: Hayatullah | E8: 5 | R8: 15 | U8: 50 | AA8: 35
A9: BAUDHUIN | B9: Claire | G9: 5 | R9: 15 | U9: 50 | AA9: 35
A10: BENOIT GONIN | B10: Lucas | R10: 15 | U10: 50 | AA10: 35
A11: BOUJLOUD | B11: Zeneb | R11: 15 | U11: 50 | AA11: 35
A12: CANI | B12: Rilinda | R12: 15 | U12: 50 | AA12: 35
A13: CELEBI | B13: Bekir | G13: 5 | R13: 15 | U13: 50 | AA13: 35
A14: CERVANTES | B14: Sabrina | R14: 15 | U14: 50 | AA14: 35
A15: CHANAL-MOGUET | B15: Virginie | D15: 5 | R15: 15 | U15: 50 | AA15: 35
A16: CHAUME | B16: Stephanie | R16: 15 | U16: 50 | AA16: 35
A17: DAMIRON | B17: Arthur | O17: 1 | P17: 46049 | Q17: 46054 | R17: 46069 | S17: 1 | T17: 1 | U17: 46104 | AA17: 35
A18: EL ARKOUBI | B18: Touria | R18: 15 | U18: 50 | AA18: 35
A19: EL BAHMANI | B19: Naima | R19: 15 | U19: 50 | AA19: 35
A20: ERASLAN | B20: Eren | O20: 1 | P20: 46049 | Q20: 46054 | R20: 46069 | U20: 46104 | AA20: 35
A21: GILBERT | B21: Stéphanie | R21: 15 | U21: 50 | AA21: 35
A22: HIDA | B22: Soumaya | O22: 1 | P22: 46049 | Q22: 46054 | R22: 46069 | U22: 46104 | AA22: 35
A23: HUMBERT | B23: Jolan | O23: 1 | P23: 46049 | Q23: 46054 | R23: 46069 | U23: 46104 | AA23: 35
A24: KABA | B24: M'balou | R24: 15 | U24: 50 | AA24: 35
A25: KACEM | B25: Houaria | R25: 15 | U25: 50 | AA25: 35
A26: KASEMRATH | B26: Melanie | R26: 15 | U26: 50 | AA26: 35
A27: LAHJAR | B27: Nadia | R27: 15 | U27: 50 | AA27: 35
A28: LAHU | B28: Fabien | R28: 15 | U28: 50 | AA28: 35
A29: LAZRAK | B29: Rajae | R29: 15 | U29: 50 | AA29: 35
A30: MALKI | B30: Hanane | R30: 15 | U30: 50 | AA30: 35
A31: MITKOVA | B31: Marusya | O31: 1 | P31: 46049 | Q31: 46054 | R31: 46069 | S31: 1 | T31: 1 | U31: 46104 | AA31: 35
A32: M'MADI | B32: Zaidine | R32: 15 | U32: 50 | AA32: 35
A33: PATEL | B33: Virginie | R33: 15 | U33: 50 | AA33: 35
A34: ROBERT | B34: Olivier | R34: 15 | U34: 50 | AA34: 35
A35: SIOUDA | B35: Tourkia | R35: 15 | U35: 50 | AA35: 35
A36: SOEUM | B36: Justine | R36: 15 | U36: 50 | AA36: 35
A37: SOUCANE | B37: Pascale | R37: 15 | U37: 50 | AA37: 35
A38: SYED RASHAD | B38: Ayesha | R38: 15 | U38: 50 | AA38: 35
A39: YILMAZ | B39: Talip | R39: 15 | U39: 50 | AA39: 35
A40: AIT YOUSSEF | B40: Maryam | R40: 15 | U40: 50 | AA40: 35
A41: BAGHDADI | B41: Edith | R41: 15 | U41: 50 | AA41: 35
A42: BOUCHIAR | B42: Sérine | R42: 15 | U42: 50 | AA42: 35
A43: CARMINATI | B43: Pierre Yves | R43: 15 | U43: 50 | AA43: 35
A44: CHENET | B44: Maxime | R44: 15 | U44: 50 | AA44: 35
A45: DURAND RAPPELER RANDSTAD | B45: Loren | O45: 1 | P45: 46071 | R45: 15 | U45: 50 | AA45: 35
A46: MESE | B46: Hafiza | R46: 15 | U46: 50 | AA46: 35
A47: RIFATI | B47: Bajram | O47: 1 | P47: 46049 | Q47: 46054 | R47: 46069 | S47: 1 | T47: 1 | U47: 46104 | AA47: 35
A48: SOK | B48: Huy | R48: 15 | U48: 50 | AA48: 35
A49: ESCOBAR | B49: Simon | R49: 15 | U49: 50 | AA49: 35
A50: OKUMUS | B50: OKAN | R50: 15 | U50: 50 | AA50: 35
A51: MOUSTAID | B51: Hichem | O51: 1 | P51: 46049 | Q51: 46054 | R51: 46069 | U51: 46104 | AA51: 35
A52: CAO | B52: Marie | R52: 15 | U52: 50 | AA52: 35
A53: ATTAR | B53: Karim | R53: 15 | U53: 50 | AA53: 35
A54: MARNISSI | B54: Nesrine | R54: 15 | U54: 50 | AA54: 35
A55: BARROS | B55: Mélanie | R55: 15 | U55: 50 | AA55: 35
A56: FABBRI | B56: Kelly | R56: 15 | U56: 50 | AA56: 35
A57: MAHAMAT ABDALLAH | B57: Wossil | R57: 15 | U57: 50 | AA57: 35
A58: AZZAOUI | B58: Hafida | R58: 15 | U58: 50 | AA58: 35
A59: BENJAHA | B59: Hafida | R59: 15 | U59: 50 | AA59: 35
A60: GJONGECAJ | B60: Anxhela | R60: 15 | U60: 50 | AA60: 35
A61: TEIXEIRA FERREIRA | B61: Antonio | R61: 15 | U61: 50 | AA61: 35
A62: HINDI | B62: Sihame | O62: 1 | P62: 46049 | Q62: 46054 | R62: 46069 | U62: 46104 | AA62: 35
A63: AOURAGH | B63: Salima | R63: 15 | U63: 50 | AA63: 35
A64: DIAS LANDIM | B64: Vania | R64: 15 | U64: 50 | AA64: 35
A65: RENARD | B65: Anaïs | R65: 15 | U65: 50 | AA65: 35
A66: MARQUES | B66: Patrick | R66: 15 | U66: 50 | AA66: 35
A67: KARA | B67: Fadime | R67: 15 | U67: 50 | AA67: 35
A68: MARGAROLI | B68: Marie-Astrid | R68: 15 | U68: 50 | AA68: 35
A69: EL HACHMI | B69: Fadoua | R69: 15 | U69: 50 | AA69: 35
A70: VARELA LOPES | B70: Joao Domingos | R70: 15 | U70: 50 | AA70: 35
A71: DANTAN | B71: Théo | R71: 15 | U71: 50 | AA71: 35
A72: DERARIDJ | B72: Karl | R72: 15 | U72: 50 | AA72: 35
A73: DAYI | B73: Gulseren | R73: 15 | U73: 50 | AA73: 35
A74: BEDIR | B74: Murat | R74: 15 | U74: 50 | AA74: 35
... A102: KHOUAKHI | B102: Jihane | R102: 15 | U102: 50 | AA102: 35
A103: ERASLAN | B103: Mustafa | O103: 1 | R103: 15 | U103: 50 | AA103: 35
A104: GATINEAU | B104: Richard | R104: 15 | U104: 50 | AA104: 35
A105: BOIS | B105: ALEXIS | R105: 15 | U105: 50 | AA105: 35
A106: D'ORAZIO | B106: ENZO | R106: 15 | U106: 50 | AA106: 35
A107: VELON | B107: Alicia | R107: 15 | U107: 50 | AA107: 35
A108: SOGOJEVA | B108: Kushtrim | R108: 15 | U108: 50 | AA108: 35
A109: AOUDIA | B109: Nouara | R109: 15 | U109: 50 | AA109: 35
