Workbook

Sheet CROIX BLANCHE PG
A2: Accompagnement des bénéficiaires du RSA - "CIP +" / 2025 | J2: Sortie + sous objectif (les noter en vert tant que vous les garder en suivi dans l'emploi)
A3: Territoire: CDS…. - LOT .../ CLPE ZONE 1 | J3: suspension remob
A4: Nom de l'OPERATEUR : ALFA3A | J4: Cli
A5: CIP : SOILIE TISSERAND | C5: Nombre de BRSA | D5: =+SUM(A9:A457) -> 92 | U5: SORTIES DU DISPOSITIF | Z5: Positionnement actions / démarches
J6: DATE | M6: DATE | O6: FREINS IDENTIFIES | W6: SORTIES + sous objectif
B7: H/F | C7: NOM | D7: PRENOM | E7: âge | F7: Niveau scolaire | G7: CDS | H7: DATE ORIENTATION | I7: DATE 1ER RDV fixé | J7: C.E SIGNE | K7: FIN CE 6 MOIS | L7: BILAN PARCOURS (7eme mois) | M7: C.E SIGNE | N7: FIN CE 12 MOIS | O7: 1 | P7: 2 | Q7: autre | R7: NOMBRE D OFFRES D EMPLOI PROPOSEES (OE/INFO COLL/jobdating..) | S7: NBRE D ENTRETIENS DE RECRUTEMENT OBTENUS SUITE A VOS OFFRES D EMPLOI | T7: PMSMP (1 = oui) | U7: Motif de sortie | V7: MOTIF de la REO | W7: types | X7: DATE SORTIE | Y7: Saisie FSE | Z7: FLE (GoOn-Ifra-Ville Bourg-centre social..) | AA7: Declic Emploi HBA | AB7: MIFE 01 | AC7: AIDE FINANCIERE | AD7: Conseillers numériques | AE7: GO ON | AF7: MOBILITE | AG7: ARIANE | AH7: AGENT DE SANTE | AI7: ADAPT | AJ7: ORSAC | AK7: REPIT PARENTAL | AL7: Clauses sociales | AM7: Autres (preciser) | AN7: COMMENTAIRES /OBSERVATION
L8: SITUATION | R8: (chiffres à cumuler / mois | S8: (chiffres à cumuler / mois | AN8: Commentaires | AP8: PROJET PRO
A9: 1 | B9: Madame | C9: AHMADI | D9: Diba | E9: 36 | F9: Master, diplôme d'études approfondies, diplôme d'études supérieures spécialisées, diplôme d'ingénieur | G9: Pierre Goujon | H9: 45903 | I9: 45931 | J9: 45931 | K9: =+J9+180 -> 46111 | L9: Renouvellement | M9: 46114 | N9: =M9+180 -> 46294 | O9: Langue | R9: 1 | S9: 1 | Y9: P281 | Z9: 1 | AN9: CE OK / Candidature envoyée le 01/10/25 pour poste couturière chez Tremplin | AP9: SIAE COUTURE | AQ9: AHMADI | AR9: Diba | AS9: rohullahaslamy477@gmail.com
A10: 1 | B10: Madame | C10: ACHBAKOU | D10: Naïma | E10: 46 | F10: Aucun diplôme | G10: Pierre Goujon | H10: 46086 | I10: 46188 | J10: 46188 | K10: =+J10+180 -> 46368 | N10: =M10+180 -> 180 | O10: Langue | P10: Mobilité | AP10: AIDE A DOMICILE
B11: madame | C11: ALI
A12: 1 | B12: Madame | C12: ALVES | D12: Merryl | E12: 26 | F12: CAP, BEP | G12: Croix Blanche | H12: 46197 | I12: 46205 | O12: Permis | AP12: CAP EAPE
A13: 1 | B13: Madame | C13: AMARI | D13: Yamina | E13: 49 | F13: Aucun diplôme | G13: Croix Blanche | H13: 45874 | I13: 45922 | J13: 45951 | K13: =+J13+180 -> 46131 | L13: Renouvellement | M13: 46134 | N13: =M13+180 -> 46314 | O13: Langue | P13: Aidante (époux) | R13: 3 | Y13: P358 | AN13: REO SOCIALE A ENVISAGER | AP13: SERVICES PERISCOLAIRES | AQ13: AMARI | AR13: Yamina | AS13: noredine.amari@outlook.fr
A14: 1 | B14: Madame | C14: ARIFI | D14: Sabrina | E14: 25 | F14: Baccalauréat | G14: Croix Blanche | H14: 45866 | I14: 46049 | J14: 46049 | K14: =+J14+180 -> 46229 | L14: Renouvellement | M14: 46230 | N14: =M14+180 -> 46410 | R14: 3 | Y14: P873 | AN14: Entrée en formation CAP AEPE 21/09/26 ENSEIS | AP14: CAP PETITE ENFANCE | AQ14: ARIFI | AR14: Sabrina | AS14: sabrina_arifi@outlook.fr
A15: 1 | B15: Madame | C15: AROUTUNOVA | D15: Suzanna | E15: 40 | O15: Santé | AP15: REO SOCIALE
A16: 1 | B16: Madame | C16: ATHOUMANI | D16: Marie | E16: 38 | F16: Aucun diplôme | G16: Croix Blanche | H16: 45812 | I16: 45890 | J16: 45890 | K16: =+J16+180 -> 46070 | L16: Renouvellement | M16: 46115 | N16: =M16+180 -> 46295 | O16: Langue | P16: Garde enfant | Q16: Logement | R16: 2 | Y16: P338 | AN16: CE OK / Absence injustifiée RDV 3 mail envoyé le 311025 | AP16: HOTELLERIE AIDE A DOMICILE | AQ16: ATHOUMANI | AR16: Marie | AS16: marie13051987@gmail.com
A17: 1 | B17: Madame | C17: AYACH | D17: Samia | E17: 26 | F17: CAP, BEP | G17: Croix Blanche | H17: 46104 | I17: 46153 | J17: 46153 | K17: =+J17+180 -> 46333 | N17: =M17+180 -> 180 | O17: Santé | Y17: P1159 | AN17: SR si absence 15/09 | AP17: AIDE A DOMICILE
A18: 1 | B18: Monsieur | C18: BA | D18: Saïkou | E18: 33 | F18: CAP, BEP | G18: Croix Blanche | I18: 46261 | O18: Santé | AP18: CHAUFFEUR LIVREUR
A19: 1 | B19: Madame | C19: BACAR | D19: Mariata | E19: 27 | F19: Baccalauréat | G19: Pierre Goujon | H19: 45800 | I19: 45960 | J19: 45960 | K19: =+J19+180 -> 46140 | L19: Renouvellement | M19: 46143 | N19: =M19+180 -> 46323 | O19: Permis | R19: 11 | S19: 2 | Y19: P337 | AB19: 1 | AM19: Cap Rebond | AP19: LOGISTIQUE GRANDE DISTRIBUTION | AQ19: BACAR | AR19: Mariata | AS19: mariata.bcr98@gmail.com
A20: 1 | B20: Madame | C20: BAHAR | D20: Laura | E20: 32 | F20: Aucun diplôme | G20: Croix Blanche | I20: 46050 | J20: 46049 | K20: =+J20+180 -> 46229 | L20: Renouvellement | M20: 46231 | N20: =M20+180 -> 46411 | O20: Santé | R20: 1 | Y20: P871 | AM20: CPA | AN20: REO SOCIALE A ENVISAGER | AO20: PMSMP | AP20: MILIEU CARCERAL | AQ20: BAHAR | AR20: Laura | AS20: bahar-l@hotmail.fr
A21: 1 | B21: Monsieur | C21: BANTADIA | D21: Ulrich | E21: 27 | G21: Pierre Goujon | H21: 46029 | I21: 46049 | J21: 46049 | K21: 46235 | L21: Renouvellement | M21: 46231 | N21: =M21+180 -> 46411 | O21: Permis | Y21: P1404 | AN21: Projet formation TP logistique Aftral 0926 | AP21: LOGISTIQUE | AS21: bandatiaulrich@gmail.com
A22: 1 | B22: Madame | C22: BARRY | D22: Aissatou | E22: 29 | F22: Aucun diplôme | G22: Pierre Goujon | H22: 46183 | I22: 46197 | J22: 46197 | K22: =J22+180 -> 46377 | O22: Enfant bas age | Y22: P1414 | AP22: MENAGE
A23: 1 | B23: Monsieur | C23: BASSUS | D23: Jason | E23: 35 | F23: CAP, BEP | G23: Croix Blanche | H23: 46098 | I23: 46113 | J23: 46113 | K23: =+J23+180 -> 46293 | N23: =M23+180 -> 180 | O23: Mobilité | AP23: INDUSTRIE
A24: 1 | B24: Madame | C24: BEAURY | D24: Virginie | E24: 53 | G24: Croix Blanche | H24: 46090 | I24: 46121 | J24: 46121 | K24: =+J24+180 -> 46301 | N24: =M24+180 -> 180
A25: 1 | B25: Madame | C25: BEKELE | D25: Eteferahu | E25: 55 | F25: Aucun diplôme | G25: Pierre Goujon | H25: 45979 | I25: 45993 | J25: 46009 | K25: =+J25+180 -> 46189 | L25: Tripartite | N25: =M25+180 -> 180 | O25: Langue | P25: Illetrisme | Y25: P778 | Z25: 1 | AM25: Cap Rebond | AN25: CE OK / SIAE | AP25: MENAGE/TRI | AQ25: BEKELE | AR25: Eteferahu
A26: 1 | B26: Madame | C26: BELFASSI | D26: Maria Dolores | E26: 43 | F26: Aucun diplôme | G26: Croix Blanche | H26: 45959 | I26: 45992 | J26: 45992 | K26: =+J26+180 -> 46172 | N26: =M26+180 -> 180 | O26: Santé | P26: Enfant TSA | Q26: Langue | Y26: P777 | AN26: CE OK | AP26: SR si absence 21/04 | AQ26: BELFASSI | AR26: Maria Dolores | AS26: 1981belfassi@gmail.com
A27: 1 | B27: Madame | C27: BENAISSA | D27: Radia | E27: 53 | F27: Aucun diplôme | G27: Croix Blanche | H27: 45940 | I27: 45981 | J27: 45981 | K27: =+J27+180 -> 46161 | L27: Renouvellement | M27: 46163 | N27: =M27+180 -> 46343 | Y27: P348 | AN27: CE OK / Couturière indépendante immatriculée CMA / Projet développement activité | AO27: developp activité / Combien d'heures par semaine ? Entreprise aide à domicile + CESU | AP27: COUTURIERE INDEPENDANTE DEV ACTIVITE | AQ27: BENAISSA | AR27: Rabia | AS27: rabia.benaissa@sfr.fr
A28: 1 | B28: Madame | C28: BENCHENAA | D28: Mansouria | E28: 55 | F28: Aucun diplôme | G28: Croix Blanche | H28: 46086 | I28: 46262 | J28: 46262 | K28: =+J28+180 -> 46442 | O28: Santé | P28: Santé mentale | AN28: REO SOCIALE A ENVISAGER
A29: 1 | B29: Monsieur | C29: BEN EL OUALI | D29: Anouar | E29: 27 | F29: CAP, BEP | G29: Pierre Goujon | H29: 45827 | I29: 46049 | J29: 46049 | K29: =+J29+180 -> 46229 | L29: Renouvellement | M29: 46231 | N29: =M29+180 -> 46411 | O29: Permis | Y29: P997 | AN29: CE OK / Projet formation CAP chaudronnier soudeur | AO29: bracelet permis poids lourd | AP29: INDUSTRIE PREPA COMMANDE | AQ29: BEN EL OUALI | AR29: Anouar | AS29: maroquiii01@icloud.com
A30: 1 | B30: Monsieur | C30: BENMELLOUK BENMOUSSA | D30: Abdelkader | E30: 47 | F30: Aucun diplôme | G30: Croix Blanche | H30: 46097 | I30: 46120 | J30: 46120 | K30: =+J30+180 -> 46300 | N30: =M30+180 -> 180 | S30: 1 | Y30: P1105 | AN30: SR SI ABSENCE 24/07
A31: 1 | B31: Monsieur | C31: BENOIT | D31: Xavier | E31: 36 | F31: Aucun diplôme | G31: Pierre Goujon | H31: 45903 | I31: 45925 | J31: 46050 | K31: =+J31+180 -> 46230 | N31: =M31+180 -> 180 | R31: 2 | Y31: P941 | AN31: CLI / CE OK | AO31: aidant familial chauffeur livreur | AP31: CHAUFFEUR LIVREUR | AQ31: BENOIT | AR31: Xavier | AS31: allessio2022@gmail.com
A32: 1 | B32: Monsieur | C32: BENZEKHROUFA | D32: Abdelghani | E32: 49 | F32: CAP, BEP | G32: Pierre Goujon | H32: 46045 | I32: 46065 | J32: 46065 | K32: =+J32+180 -> 46245 | N32: =M32+180 -> 180 | R32: 1 | AN32: CE OK | AO32: INCARCERATION Soumis D& D voir insertion | AP32: RESTAURATION COLLECTIVE | AQ32: BENZEKHROUFA | AR32: Abdelghani | AS32: audir9299@gmail.com
A33: 1 | B33: Madame | C33: BERGER | D33: Stéphanie | E33: 48 | F33: DEUG, BTS, DUT, DEUST | G33: Croix Blanche | H33: 46105 | I33: 46127 | J33: 46127 | K33: =+J33+180 -> 46307 | N33: =M33+180 -> 180 | Y33: P1179 | AN33: Projet CESU 24h/semaine + presta ent nettoyage de bureau | AO33: CDI 22,75H/S annualisé | AP33: MENAGE
A34: 1 | B34: Madame | C34: BERTHILLOT | D34: Léa | E34: 27 | F34: CAP, BEP | G34: Croix Blanche | H34: 46059 | I34: 46078 | J34: 46078 | K34: =+J34+180 -> 46258 | L34: Renouvellement | M34: 46260 | N34: =M34+180 -> 46440 | O34: Santé | R34: 2 | S34: 1 | Y34: P1020 | AN34: CE OK | AO34: CDD jusqu'à fin 0926 28h/semaine | AP34: AIDE A DOMICILE | AQ34: BERTHILLOT | AR34: Léa | AS34: leacaronath01@hotmail.com
A35: 1 | B35: Monsieur | C35: BIDET | D35: Rodolphe | E35: 27 | F35: Baccalauréat | G35: Pierre Goujon | H35: 46133 | I35: 46163 | J35: 46227 | K35: =+J35+180 -> 46407 | N35: =M35+180 -> 180 | R35: 2 | Y35: P1415 | AN35: Statut intermittent en cours | AP35: INGENIEUR DU SON
A36: 1 | B36: Monsieur | C36: BOUFIM | D36: Fouad | E36: 42 | F36: CAP, BEP | G36: Pierre Goujon | H36: 46141 | I36: 46169 | J36: 46182 | K36: =+J36+180 -> 46362 | N36: =M36+180 -> 180 | O36: Suspension permis | R36: 1 | Y36: P1416 | AP36: SOUDURE | AS36: foueddz0119@gmail.com
A37: 1 | B37: Madame | C37: BOUTAIB | D37: Hafida | E37: 46 | G37: Croix Blanche | H37: 46185 | I37: 46204 | J37: 46204 | K37: =+J37+180 -> 46384 | O37: Langue | AP37: ELS
A38: 1 | B38: Madame | C38: BOUZIANE | D38: Fatima | E38: 44 | F38: Baccalauréat | G38: Croix Blanche | H38: 46230 | I38: 46266 | J38: 46266 | K38: =+J38+180 -> 46446 | R38: 1 | AP38: COMPTABILITE
B39: Monsieur | C39: BOUZIDI | D39: El Houcine | E39: 32 | G39: Croix Blanche
B40: Monsieur | C40: BOUZIT | D40: Oycime | E40: 32 | G40: Croix Blanche
A41: 1 | B41: Madame | C41: BOYRAZ | D41: Merve | E41: 28 | G41: Pierre Goujon | H41: 46086 | I41: 46112 | J41: 46112 | K41: =+J41+180 -> 46292 | N41: =M41+180 -> 180 | Y41: P1076 | AO41: 10h/s CESU | AP41: AIDE A DOMICILE
A42: 1 | B42: Madame | C42: BRUZEAU | D42: Laura | E42: 25 | G42: Pierre Goujon | H42: 45903 | I42: 45931 | J42: 45931 | K42: =+J42+180 -> 46111 | L42: Tripartite | M42: 46114 | N42: =M42+180 -> 46294 | O42: Aidante | P42: Enfant handicapé | Y42: P333 | AN42: Réo sociale à envisager ??/ Enfant autiste AEEH PCH | AO42: reo social ? | AP42: CONSEILLERE FUNERAIRE | AQ42: BRUZEAU | AR42: Laura | AS42: laurabruzeau@hotmail.fr
A43: 1 | B43: Madame | C43: BUATTIER | D43: Christelle | E43: 51 | F43: Baccalauréat | G43: Croix Blanche | H43: 45846 | I43: 45910 | J43: 45910 | K43: =+J43+180 -> 46090 | N43: =M43+180 -> 180 | O43: Santé | Y43: P776 | AN43: CE OK / Chirurgie avec convalescence le 10/10/25 / AM jusqu'au 251125 / Absence injustifiée / Mail envoyé le 210126 / Attente certificat incapacité mail envoyé 270226 | AO43: SR | AQ43: BUATTIER | AR43: Christelle
A44: 1 | B44: Monsieur | C44: CARTIA | D44: Giuseppe
A45: 1 | B45: Madame | C45: CHARNAY | D45: Cindy | G45: Croix Blanche | H45: 45995 | I45: 46014 | K45: =+J45+180 -> 180 | N45: =M45+180 -> 180 | AN45: RDV 22/01/2026 | AO45: SUSPENSION REMOB
A46: 1 | B46: Monsieur | C46: CHAVE | D46: Baptiste | E46: 31 | F46: Baccalauréat | G46: Pierre Goujon | H46: 45905 | I46: 45931 | J46: 45931 | K46: =+J46+180 -> 46111 | L46: Renouvellement | M46: 46114 | N46: =M46+180 -> 46294 | O46: Santé | P46: Conduite | R46: 2 | Y46: P271 | AB46: 1 | AO46: CAF ? / PMSMP Domaliance | AP46: PEC HYGIENE BOURG | AQ46: CHAVE | AR46: Baptiste | AS46: chaveb1994@gmail.com
A47: 1 | B47: Madame | C47: DANIELE | D47: Coralie | G47: Pierre Goujon | AP47: GRANDE DISTRIBUTION SOCIAL
A48: 1 | B48: Monsieur | C48: DA SILVA GONCALVES | D48: Samuel | E48: 30 | F48: CAP, BEP | G48: Pierre Goujon | H48: 45891 | I48: 45923 | J48: 45923 | K48: =+J48+180 -> 46103 | L48: Renouvellement | M48: 46105 | N48: =M48+180 -> 46285 | O48: Santé | R48: 2 | Y48: P351 | AN48: CDD DEPUIS JUIN 2026 | AP48: INFORMATIQUE | AQ48: DA SILVA GONCALVES | AR48: Samuel | AS48: sdasilvagoncalves1@gmail.com
A49: 1 | B49: Madame | C49: DBIJA | D49: Hafida | E49: 50 | F49: CAP, BEP | G49: Pierre Goujon | H49: 46059 | I49: 46078 | J49: 46078 | K49: =+J49+180 -> 46258 | L49: Renouvellement | M49: 46260 | N49: =M49+180 -> 46440 | O49: Santé | Y49: P1019 | AN49: CE OK / AIDE MENAGERE A SON COMPTE EN CESU | AO49: 13h/ s Fin D&D ? | AP49: AIDE MENAGERE CESU + Structure aide à dom | AQ49: DBIJA | AR49: Hafida | AS49: hafida-db@hotmail.fr
A50: 1 | B50: Madame | C50: DECAILLON | D50: Candide | E50: 54 | F50: Aucun diplôme | G50: Pierre Goujon | H50: 45870 | I50: 45908 | J50: 45908 | K50: =+J50+180 -> 46088 | L50: Renouvellement | M50: 46090 | N50: =M50+180 -> 46270 | Y50: P278 | AH50: 1 | AN50: CDI Assistante maternelle / Projet formation AESH / Absence RDV 4 relance envoyée 270226 | AO50: Orientation Annick / Djamila | AP50: Aide à dom / ASH | AQ50: DECAILLON | AR50: Candide
A51: 1 | B51: Madame | C51: DUCLOS | D51: Delphine | H51: 46199 | I51: 46226 | J51: 46226 | K51: =+J51+180 -> 46406 | AP51: Formation IA
A52: 1 | B52: Madame | C52: DUPUPED | D52: Nathalie | E52: 47 | F52: CAP, BEP | G52: Croix Blanche | H52: 46147 | I52: 46185 | J52: 46185 | K52: =+J52+180 -> 46365 | N52: =M52+180 -> 180 | O52: Santé | AN52: REO SOCIALE A ENVISAGER
B53: Madame | C53: ENDALE | D53: Marie | E53: 26 | H53: 46223 | I53: 46248
B54: Madame | C54: EL BOUHALI | D54: Kaoutar | E54: 42 | G54: Pierre Goujon
A55: 1 | B55: Monsieur | C55: EL MOUSTAOUI | D55: Sadik | E55: 42 | G55: Croix Blanche | H55: 45887 | I55: 45916 | J55: 45953 | K55: =+J55+180 -> 46133 | N55: =M55+180 -> 180 | O55: Santé mentale | AN55: Préconisation ESAT / REO SOCIALE A ENVISAGER - CIP orsac | AO55: reo social a faire | AQ55: EL MOUSTAOUI | AR55: Sadik
A56: 1 | B56: Madame | C56: FETET | D56: Jennifer | E56: 35 | F56: Aucun diplôme | G56: Croix Blanche | H56: 45875 | I56: 45910 | J56: 45910 | K56: =+J56+180 -> 46090 | L56: Renouvellement | M56: 46092 | N56: =M56+180 -> 46272 | Y56: P159 | AN56: Projet créa entreprise / Acco BGE Business plan en cours / Abence RDV 3 / Mail envoyé 011225 | AO56: Projet création | AP56: COUTURE | AQ56: FETET | AR56: Jennifer | AS56: jenniferfetet00@gmail.com
A57: 1 | B57: Monsieur | C57: FIEMS | D57: Grégory | E57: 38 | F57: CAP, BEP | G57: Pierre Goujon | H57: 46133 | I57: 46153 | J57: 46177 | K57: =+J57+180 -> 46357 | N57: =M57+180 -> 180 | O57: Véhicule | P57: Santé mentale | Y57: P1417 | AN57: CDD DEPUIS 08/2026 | AS57: fiems.gregory@gmail.com
A58: 1 | B58: Madame | C58: GASHI | D58: Melihate | E58: 46 | G58: Croix Blanche | H58: 46170 | I58: 46185 | J58: 46185 | K58: =+J58+180 -> 46365 | N58: =M58+180 -> 180 | O58: Santé mentale | AN58: REO SOCIALE A ENVISAGER | AP58: REO SOCIALE A ENVISAGER
A59: 1 | B59: Madame | C59: GOBERT | D59: Edwige | E59: 33 | F59: CAP, BEP | G59: Croix Blanche | H59: 46004 | I59: 45926 | J59: 45926 | K59: =+J59+180 -> 46106 | L59: Renouvellement | M59: 46108 | N59: =M59+180 -> 46288 | O59: Garde enfant | P59: Santé | Y59: P290 | AN59: CE OK / REO SOCIALE A ENVISAGER - justif medical en attente | AO59: crèche pour le dernier | AP59: REO SOCIALE A ENVISAGER | AQ59: GOBERT | AR59: Edwige | AS59: gbtedwige01@gmail.com
A60: 1 | B60: Monsieur | C60: HADZI-ALIJA | D60: Erdan | E60: 32 | F60: Aucun diplôme | G60: Croix Blanche | H60: 45873 | I60: 45908 | J60: 46080 | K60: =+J60+180 -> 46260 | N60: =M60+180 -> 180 | S60: 1 | Y60: P1042 | AN60: SR SI ABSENCE 24/07 | AO60: Cariste RT (a passé école des métiers) | AQ60: HADZI-ALIJA | AR60: Erdan
A61: 1 | B61: Monsieur | C61: HAMMAMI | D61: Faysal | E61: 51 | F61: CAP, BEP | G61: Pierre Goujon | H61: 46149 | I61: 46174 | J61: 46204 | K61: =+J61+180 -> 46384 | O61: Santé | P61: Logement | Q61: Mobilité
A62: 1 | B62: Monsieur | C62: HAMMOUMI | D62: Mohammed | E62: 29 | F62: Baccalauréat | G62: Croix Blanche | H62: 46029 | I62: 46043 | J62: 46043 | K62: =+J62+180 -> 46223 | L62: Renouvellement | N62: =M62+180 -> 180 | S62: 2 | Y62: P868 | AN62: CE OK / Autoentrepreneur souhaite revenir au salariat | AO62: Formation diplômante | AP62: INFORMATIQUE | AQ62: HAMMOUMI | AR62: Mohammed | AS62: amine.hamo@outlook.com
B63: Monsieur | C63: HANINI | D63: Hichem | E63: 38 | G63: Pierre Goujon
A64: 1 | B64: Madame | C64: HASSANI | D64: Koulthoumi | E64: 42 | F64: Aucun diplôme | G64: Croix Blanche | H64: 45938 | I64: 45670 | J64: 46035 | K64: =+J64+180 -> 46215 | L64: Renouvellement | M64: 46217 | N64: =M64+180 -> 46397 | O64: Santé | R64: 5 | Y64: P866 | AJ64: 1 | AN64: CDDUSAGE AINTERJOB DEPUIS 03072026 | AP64: Agent d'entretien et cantine | AQ64: HASSANI | AR64: Koulthoumi | AS64: koulouthoumihassani@yahoo.fr
A65: 1 | B65: Madame | C65: HOUICHI | D65: Hikmet | E65: 44 | F65: Doctorat, habilitation à diriger des recherches | G65: Pierre Goujon | H65: 45891 | I65: 45923 | J65: 45923 | K65: =+J65+180 -> 46103 | L65: Renouvellement | M65: 46105 | N65: =M65+180 -> 46285 | S65: 1 | Y65: P938 | AN65: CE OK | AO65: voir educ nationale | AP65: ENSEIGNEMENT | AQ65: HOUICHI | AR65: Hikmet | AS65: houichihikmet@gmail.com
A66: 1 | B66: Madame | C66: IBADIOUNE | D66: Jamila | E66: 44 | G66: Croix Blanche | H66: 45952 | I66: 46093 | J66: 46093 | K66: =+J66+180 -> 46273 | N66: =M66+180 -> 180 | O66: Garde enfants | P66: Permis | R66: 4 | S66: 1 | Y66: P1070 | AP66: NETTOYAGE
A67: 1 | B67: Madame | C67: IMMEDIATO | D67: Eva | E67: 41 | F67: Baccalauréat | G67: Pierre Goujon | H67: 46090 | I67: 46135 | J67: 46135 | K67: =+J67+180 -> 46315 | N67: =M67+180 -> 180 | O67: Véhicule | R67: 4 | Y67: P1180 | AP67: RESTAURATION
A68: 1 | B68: Monsieur | C68: KALINDA | D68: Léopold | E68: 28 | F68: Master, diplôme d'études approfondies, diplôme d'études supérieures spécialisées, diplôme d'ingénieur | G68: Croix Blanche | H68: 46051 | I68: 46065 | J68: 46065 | K68: =+J68+180 -> 46245 | L68: Renouvellement | M68: 46247 | N68: =M68+180 -> 46427 | O68: Permis | Y68: P986 | AN68: CE OK / | AO68: CDD TPS PLEIN | AP68: ASH / FORMATION INF | AQ68: KALINDA | AR68: Léopold | AS68: lerob.hotmail.fr@gmail.com
A69: 1 | B69: Madame | C69: KARADAVUT | D69: Pembe | E69: 56 | F69: Aucun diplôme | G69: Croix Blanche | H69: 46003 | I69: 46049 | J69: 46058 | K69: =+J69+180 -> 46238 | L69: Renouvellement | M69: 46240 | N69: =M69+180 -> 46420 | O69: Santé | R69: 1 | Y69: P984 | AB69: 1 | AJ69: 1 | AN69: CE OK | AP69: PETITE MANUTENTION | AQ69: KARADAVUT | AR69: Pembe | AS69: pembekaradavut1@gmail.com
A70: 1 | B70: Madame | C70: KASEMI | D70: Elsaïda | E70: 25 | F70: Baccalauréat | G70: Croix Blanche | H70: 46005 | I70: 46013 | J70: 46027 | K70: =+J70+180 -> 46207 | L70: Renouvellement | M70: 46209 | N70: =M70+180 -> 46389 | O70: Garde enfant | P70: Permis | R70: 1 | S70: 1 | Y70: P1100 | AN70: CE OK | AP70: INFIRMIERE / AIDE SOIGNANTE | AQ70: KASEMI | AR70: Elsaïda | AS70: elisea.kasemi1@gmail.com
A71: 1 | B71: Monsieur | C71: KIM | D71: Stéphane | E71: 55 | F71: CAP, BEP | G71: Croix Blanche | H71: 46051 | I71: 46072 | J71: 46072 | K71: =+J71+180 -> 46252 | L71: Renouvellement | M71: 46254 | N71: =M71+180 -> 46434 | O71: Santé | Y71: P1023 | AN71: REO SOCIALE A ENVISAGER | AP71: BURALISTE
A72: 1 | B72: Madame | C72: KULIKOVA | D72: Oléna | E72: 44 | G72: Croix Blanche | H72: 45866 | I72: 45939 | J72: 46050 | K72: =+J72+180 -> 46230 | L72: Renouvellement | M72: 46232 | N72: =M72+180 -> 46412 | O72: Langue | Y72: P775 | AQ72: KULIKOVA | AR72: Oléna | AS72: 123456kulikova@gmail.com
A73: 1 | B73: Monsieur | C73: MARRET | D73: Alan | E73: 26 | F73: CAP, BEP | G73: Pierre Goujon | H73: 46052 | I73: 46069 | J73: 46069 | K73: =+J73+180 -> 46249 | L73: Renouvellement | M73: 46251 | N73: =M73+180 -> 46431 | R73: 1 | Y73: P1071 | AB73: 1 | AN73: CE OK | AP73: FIBRE OPTIQUE
A74: 1 | B74: Monsieur | C74: MCHINDRA | D74: Yancoub | E74: 30 | F74: Aucun diplôme | G74: Croix Blanche | H74: 45854 | I74: 45922 | J74: 45959 | K74: =+J74+180 -> 46139 | L74: Renouvellement | M74: 46142 | N74: =M74+180 -> 46322 | Y74: P1072 | AB74: 1 | AP74: NETTOYAGE | AQ74: MCHINDRA | AR74: Yancoub
A75: 1 | B75: Monsieur | C75: MEKOUN | D75: Ozias | E75: 28 | F75: CAP, BEP | G75: Croix Blanche | H75: 46233 | I75: 46260 | J75: 46260 | K75: =+J75+180 -> 46440 | O75: Santé | R75: 8 | AP75: VENTE NETTOYAGE INDUSTRIE
A76: 1 | B76: Monsieur | C76: MENIHEYA | D76: Zakaria | E76: 32 | F76: CAP, BEP | G76: Pierre Goujon | H76: 46168 | I76: 46184 | J76: 46184 | K76: =+J76+180 -> 46364 | N76: =M76+180 -> 180 | Y76: P1418 | AN76: REO SOCIALE A ENVISAGER
A77: 1 | B77: Madame | C77: MMADI | D77: Nasbata | E77: 36 | F77: Titre pro | G77: Croix Blanche | H77: 46140 | I77: 46170 | J77: 46170 | K77: =+J77+180 -> 46350 | N77: =M77+180 -> 180 | O77: Permis | P77: Mère isolée | Y77: P1419 | AP77: AIDE A DOMICILE
B78: Monsieur | C78: MOHEBBI | D78: Najibullah | G78: Croix Blanche | H78: 46202 | I78: 46259
A79: 1 | B79: Monsieur | C79: MOLL | D79: Armand | E79: 59 | F79: CAP, BEP | G79: Croix Blanche | H79: 46042 | I79: 46050 | J79: 46050 | K79: =+J79+180 -> 46230 | L79: Renouvellement | M79: 46232 | N79: =M79+180 -> 46412 | O79: Mobilité | R79: 2 | Y79: P989 | AN79: CE OK aidant familial | AO79: SR si absent 2705 | AP79: CHAUFFEUR INDUSTRIE | AQ79: MOLL | AR79: Armand | AS79: armandmoll66@gmail.com
A80: 1 | B80: Madame | C80: MOLLA | D80: Romina | E80: 35 | F80: Baccalauréat | G80: Pierre Goujon | H80: 45908 | I80: 46014 | J80: 46014 | K80: =+J80+180 -> 46194 | L80: Renouvellement | M80: 46197 | N80: =M80+180 -> 46377 | O80: Langue | P80: Aidante | R80: 1 | Y80: P751 | Z80: 1 | AN80: CE OK | AP80: CANTINE SCOLAIRE | AQ80: MOLLA | AR80: Romina | AS80: duroromina400@gmail.com
A81: 1 | B81: Monsieur | C81: MOSES | D81: Jal | E81: 27 | F81: Aucun diplôme | G81: Pierre Goujon | H81: 46010 | I81: 46036 | J81: 46036 | K81: =+J81+180 -> 46216 | L81: Renouvellement | M81: 46218 | N81: =M81+180 -> 46398 | O81: Mobilité | R81: 2 | S81: 10 | Y81: P774 | AB81: 1 | AN81: CE OK : Besoin Caces 1, 3, 5 | AO81: CDD jusqu'au 130926 | AP81: PREPARATION COMMANDES | AQ81: MOSES | AR81: Jal | AS81: mosesjal98@gmail.com
A82: 1 | B82: Madame | C82: MOUSTOIFFA | D82: Zaïna | E82: 59 | F82: Aucun diplôme | G82: Pierre Goujon | H82: 46002 | I82: 46010 | J82: 46010 | K82: =+J82+180 -> 46190 | L82: Renouvellement | M82: 46193 | N82: =M82+180 -> 46373 | O82: Santé | P82: Langue | Y82: P1074 | AH82: 1 | AO82: SR si absence 11/09 | AQ82: MOUSTOIFFA | AR82: Zaïna
A83: 1 | B83: Monsieur | C83: MTIMET | D83: Ridha | E83: 55 | G83: Croix Blanche | H83: 45833 | I83: 45953 | J83: 46043 | K83: =+J83+180 -> 46223 | L83: Renouvellement | M83: 46225 | N83: =M83+180 -> 46405 | O83: Santé | R83: 1 | Y83: P872 | AH83: 1 | AN83: CLI passée ok retour/ SIAE | AP83: Réo sociale à envisager | AQ83: MTIMET | AR83: Ridha | AS83: mtimetridha@yahoo.fr
A84: 1 | B84: Monsieur | C84: NUTIN | D84: Killian | E84: 34 | F84: CAP, BEP | G84: Croix Blanche | H84: 46233 | I84: 46259 | J84: 46259 | K84: =+J84+180 -> 46439 | R84: 4 | AP84: PREPARATEUR DE COMMANDE INDUSTRIE | AS84: killiannutin01@gmail.com
A85: 1 | B85: Madame | C85: OSIPOVA | D85: Margarita | E85: 43 | G85: Croix Blanche | H85: 46220 | I85: 46169 | J85: 46169 | K85: =+J85+180 -> 46349 | N85: =M85+180 -> 180 | O85: Langue
A86: 1 | B86: Monsieur | C86: OULD KADA | D86: Nadji | E86: 55 | F86: Baccalauréat | G86: Croix Blanche | H86: 46202 | I86: 46227 | J86: 46227 | K86: =+J86+180 -> 46407 | O86: Mobilité | P86: Santé mentale | AN86: Projet formation auxiliaire ambulancier AFTRAL | AP86: AUXILIAIRE AMBULANCIER
A87: 1 | B87: Madame | C87: OULAD AYAD | D87: Loubna | E87: 49 | F87: Licence, licence professionnelle | G87: Pierre Goujon | H87: 46064 | I87: 46079 | J87: 46079 | K87: =+J87+180 -> 46259 | N87: =M87+180 -> 180 | R87: 1 | S87: 1 | Y87: P1021 | AN87: CDD agent technique école de St Just | AO87: CIP
A88: 1 | B88: Monsieur | C88: OUSMANE | D88: Tidiane | E88: 30 | F88: CAP, BEP | G88: Croix Blanche | H88: 46044 | I88: 46048 | J88: 46058 | K88: =+J88+180 -> 46238 | N88: =M88+180 -> 180 | O88: Santé mentale | Y88: P1027 | AN88: CE OK / AS Caroline GIMENEZ / 07-63-47-14-09 / MASP | AO88: Annick / Jamila | AP88: INDUSTRIE | AQ88: OUSMANE | AR88: Tidiane | AS88: tidianeousmane82@gmail.com
A89: 1 | B89: Madame | C89: PAGE | D89: Francesca | E89: 32 | F89: CAP, BEP | G89: Croix Blanche | H89: 45947 | I89: 45960 | J89: 45960 | K89: =+J89+180 -> 46140 | L89: Renouvellement | M89: 46143 | N89: =M89+180 -> 46323 | O89: Permis | R89: 2 | Y89: P307 | AB89: 1 | AN89: CE OK / Candidature Tremplin envoyée 251125 | AO89: CAF | AP89: ADMINISTRATIF | AQ89: PAGE | AR89: Francesca | AS89: francescapage7@gmail.com
A90: 1 | B90: Madame | C90: PAUVIL | D90: Pauline | E90: 58 | F90: Aucun diplôme | G90: Pierre Goujon | H90: 45825 | I90: 45930 | J90: 45930 | K90: =+J90+180 -> 46110 | L90: Renouvellement | M90: 46112 | N90: =M90+180 -> 46292 | O90: Santé | P90: Illetrisme | Q90: Logement | Y90: P346 | AN90: CE OK / Absence RDV 2 / Mail envoyé le 021225 / Relance 220126 /Injoignable | AP90: REO SOCIALE A ENVISAGER | AQ90: PAUVIL | AR90: Pauline
B91: Madame | C91: PAYET | D91: Ouafae
B92: Monsieur | C92: PELLETIER | D92: Killian | E92: 26 | G92: Pierre Goujon
B93: Madame | C93: PERNET | D93: Océane | E93: 27 | H93: 46240 | I93: 46266
A94: 1 | B94: Monsieur | C94: PERRIAUD | D94: Thomas | E94: 38 | F94: Baccalauréat | G94: Pierre Goujon | H94: 46128 | I94: 46199 | J94: 46199 | K94: =+J94+180 -> 46379 | O94: Santé mentale | P94: Logement | AP94: SIAE PETITE MANUTENTION
A95: 1 | B95: Monsieur | C95: PIERRE-LOUIS | D95: Stephen | E95: 33 | F95: CAP, BEP | G95: Pierre Goujon | H95: 46031 | I95: 46048 | J95: 46048 | K95: =+J95+180 -> 46228 | L95: Renouvellement | M95: 46230 | N95: =M95+180 -> 46410 | O95: Santé | Y95: P1024 | AN95: CE OK | AP95: PETITE ENFANCE / ATSEM AESH | AQ95: PIERRE-LOUIS | AR95: Stephen | AS95: mr.pierrelouis.s@gmail.com
A96: 1 | B96: Monsieur | C96: PINTO | D96: Jason | E96: 29 | F96: Aucun diplôme | G96: Croix Blanche | H96: 45897 | I96: 45951 | J96: 45951 | K96: =+J96+180 -> 46131 | L96: Renouvellement | M96: 46134 | N96: =M96+180 -> 46314 | O96: Permis | R96: 5 | S96: 1 | Y96: P330 | AN96: CE OK travaille chez basic fit en interim / cdi ?? | AP96: ADMINISTRATIF | AQ96: PINTO | AR96: Jason | AS96: jason.pinto@hotmail.fr
B97: Monsieur | C97: POCAUD | D97: Gabriel | E97: 36 | G97: Croix Blanche | H97: 46241
A98: 1 | B98: Madame | C98: POCHEBONNE | D98: Prescillia | E98: 33 | F98: CAP, BEP | G98: Croix Blanche | H98: 46084 | I98: 46114 | J98: 46114 | K98: =+J98+180 -> 46294 | N98: =M98+180 -> 180 | O98: Enfant malade | P98: Monoparentalité | Y98: P1120 | AP98: Projet création entreprise
A99: 1 | B99: Monsieur | C99: PUZIN | D99: Jacky | E99: 39 | F99: Aucun diplôme | G99: Pierre Goujon | H99: 45828 | I99: 45891 | J99: 45891 | K99: =+J99+180 -> 46071 | L99: Renouvellement | N99: =M99+180 -> 180 | O99: Permis | Y99: P329 | AN99: En CDDI 8h / semaine - premières heures Tremplin / A reconvoquer | AO99: RADIE FT | AP99: BILAN + REINSCRIPTION FT | AQ99: PUZIN | AR99: Jacky
A100: 1 | B100: Monsieur | C100: RAMOUL | D100: Mohcin | E100: 40 | F100: Aucun diplôme | G100: Croix Blanche | H100: 46072 | I100: 46113 | J100: 46113 | K100: =+J100+180 -> 46293 | N100: =M100+180 -> 180 | O100: Santé | Y100: P1181 | AN100: Projet création entreprise + formation SNCF | AP100: AGENT SCNF
A101: 1 | B101: Monsieur | C101: RHAZI | D101: Abdelhakim | E101: 54 | F101: Aucun diplôme | G101: Croix Blanche | H101: 45846 | I101: 45854 | J101: 45854 | K101: =+J101+180 -> 46034 | L101: Renouvellement | M101: 46039 | N101: =M101+180 -> 46219 | O101: Santé | AH101: 1 | AN101: REO SOCIALE A ENVISAGER - transfert de dossier d'oyonnax | AO101: en attente cm | AP101: ORSAC | AQ101: RAHZI | AR101: Abdelhakim
...

Sheet BRSA SORTIES
A2: Accompagnement des bénéficiaires du RSA - "CIP +" / 2025 | J2: Sortie + sous objectif (les noter en vert tant que vous les garder en suivi dans l'emploi)
A3: Territoire: CDS…. - LOT .../ CLPE ZONE 1 | J3: suspension remob
A4: Nom de l'OPERATEUR : ALFA3A | J4: Cli
A5: CIP : SOILIE TISSERAND | C5: Nombre de BRSA | D5: =+SUM(A9:A312) -> 110 | U5: SORTIES DU DISPOSITIF | Z5: Positionnement actions / démarches
J6: DATE | M6: DATE | O6: FREINS IDENTIFIES | W6: SORTIES + sous objectif
B7: H/F | C7: NOM | D7: PRENOM | E7: âge | F7: Niveau scolaire | G7: CDS | H7: DATE ORIENTATION | I7: DATE 1ER RDV fixé | J7: C.E SIGNE | K7: FIN CE 6 MOIS | L7: BILAN PARCOURS (7eme mois) | M7: C.E SIGNE | N7: FIN CE 12 MOIS | O7: 1 | P7: 2 | Q7: autre | R7: NOMBRE D OFFRES D EMPLOI PROPOSEES (OE/INFO COLL/jobdating..) | S7: NBRE D ENTRETIENS DE RECRUTEMENT OBTENUS SUITE A VOS OFFRES D EMPLOI | T7: PMSMP (1 = oui) | U7: Motif de sortie | V7: MOTIF de la REO | W7: types | X7: DATE SORTIE | Y7: Saisie FSE | Z7: FLE (GoOn-Ifra-Ville Bourg-centre social..) | AA7: Declic Emploi HBA | AB7: MIFE 01 | AC7: AIDE FINANCIERE | AD7: Conseillers numériques | AE7: GO ON | AF7: MOBILITE | AG7: ARIANE | AH7: AGENT DE SANTE | AI7: ADAPT | AJ7: ORSAC | AK7: REPIT PARENTAL | AL7: Clauses sociales | AM7: Autres (preciser) | AN7: COMMENTAIRES /OBSERVATION
L8: SITUATION | R8: (chiffres à cumuler / mois | S8: (chiffres à cumuler / mois | AN8: Commentaires | AP8: PROJET PRO
A9: 1 | B9: Madame | C9: ABATI | D9: Nazmije | E9: 61 | G9: Croix Blanche | H9: 45869 | I9: 45904 | N9: =M9+180 -> 180 | U9: Réorientation | V9: Social freins+ | X9: 45950 | Y9: P343
A10: 1 | B10: Monsieur | C10: ABDOULAYE ISSAKH | D10: Yaya | E10: 40 | G10: Pierre Goujon | H10: 45919 | I10: 45939 | K10: =+J10+180 -> 180 | N10: =M10+180 -> 180 | U10: Radié suite CLI | AN10: CLI - PAS DE RETOUR
A11: 1 | B11: Madame | C11: AIOUAZ | D11: Khadija | E11: 34 | G11: Croix Blanche | H11: 45915 | I11: 45938 | K11: =+J11+180 -> 180 | N11: =M11+180 -> 180 | U11: Réorientation | V11: Social freins+ | X11: 46220 | AN11: CDD petits cdd à voir rapidement / Convocation 25/11/25 / 2ABS justifiées 1ABS injustifiée / Relance le 120226 | AO11: Faire réo sociale si 3 mois d'absence | AQ11: AIOUAZ | AR11: Khadija
A12: 1 | B12: Madame | C12: ALI | D12: Mariama | E12: 32 | G12: Croix Blanche | H12: 45765 | I12: 45883 | N12: =M12+180 -> 180 | U12: Réorientation | V12: Sociale maternité
A13: 1 | B13: Madame | C13: ANTOINAT | D13: Jennifer | E13: 40 | G13: Pierre Goujon | H13: 45846 | I13: 45861 | N13: =M13+180 -> 180 | U13: Réorientation | V13: Social freins+ | X13: 45904
A14: 1 | B14: Madame | C14: ARARI | D14: Jennifer | E14: 39 | G14: Croix Blanche | H14: 45838 | I14: 45876 | N14: =M14+180 -> 180 | U14: Réorientation | V14: Social freins+
A15: 1 | B15: Madame | C15: BAITICHE | D15: Karima | E15: 30 | F15: Aucun diplôme | G15: Croix Blanche | H15: 45849 | I15: 45870 | J15: 45870 | K15: =+J15+180 -> 46050 | L15: Renouvellement | M15: 46055 | N15: =M15+180 -> 46235 | O15: Posture pro | P15: Santé mentale | Q15: Mobilité (utilisation TC) | R15: 2 | U15: Fin bilan parcours | V15: FT acc pro | X15: 46236 | Y15: P144 | AM15: Cap Rebond | AN15: CE OK / SIAE voir entreprise adaptée / Relance envoyée 130226 / SR si absence 270326 | AO15: resto social | AP15: SORTIE FT | AQ15: BAITICHE | AR15: Karima
A16: 1 | B16: Madame | C16: BARA | D16: Assetou | E16: 39 | F16: Aucun diplôme | G16: Pierre Goujon | H16: 46100 | I16: 46114 | J16: 46114 | K16: =+J16+180 -> 46294 | N16: =M16+180 -> 180 | U16: Réorientation | V16: BGE | W16: Créa | X16: 46133 | AP16: CREATION ENTREPRISE ENTRETIEN RESIDENCE
A17: 1 | B17: Monsieur | C17: BARAT | D17: Sayed | E17: 32 | G17: Croix Blanche | H17: 45846 | I17: 45889 | K17: =+J17+180 -> 180 | N17: =M17+180 -> 180 | U17: Radié suite CLI | AN17: CLI - pas repris contact
A18: 1 | B18: Madame | C18: BESSON | D18: Florence | E18: 59 | F18: CAP, BEP | G18: Croix Blanche | H18: 46233 | I18: 46245 | J18: 46245 | K18: =+J18+180 -> 46425 | U18: Positive | V18: BGE | W18: Créa | X18: 46272 | AP18: PROJET ENTREPRISE PRODUITS NETTOYAGE
A19: 1 | B19: Madame | C19: BLANC | D19: Mélissa | E19: 31 | F19: Aucun diplôme | G19: Croix Blanche | H19: 45849 | I19: 45867 | J19: 45867 | K19: =+J19+180 -> 46047 | L19: Renouvellement | M19: 46052 | N19: =M19+180 -> 46232 | U19: Fin DD | V19: FT acc pro | X19: 46223 | Y19: P340 | AN19: CE OK - OK Saisonniere 8 - 9 mois / an - recuperer les contrats | AO19: saisonniere | AP19: Fin DD 01/07/26 | AQ19: BLANC | AR19: Mélissa | AS19: melissa-blanc@live.com
A20: 1 | B20: Monsieur | C20: BONNET | D20: Cédric | E20: 31 | F20: CAP, BEP | G20: Croix Blanche | H20: 45840 | I20: 45859 | J20: 45859 | K20: =+J20+180 -> 46039 | L20: RENOUVELLEMENT | M20: 46044 | N20: =M20+180 -> 46224 | O20: Santé | U20: Fin bilan parcours | V20: FT acco glo | X20: 46225 | Y20: P127 | AH20: 1 | AN20: CE OK / Objectif entreprise adapté | AO20: Adapt | AP20: ESAT | AQ20: BONNET | AR20: Cédric | AS20: xeno6156@gmail.com
A21: 1 | B21: Madame | C21: BOTINAJ | D21: Lule | E21: 63 | F21: Aucun diplôme | G21: Pierre Goujon | H21: 45904 | I21: 45929 | N21: =M21+180 -> 180 | U21: Réorientation | V21: Social freins+ | X21: 45966
A22: 1 | B22: Monsieur | C22: BOUILLOUX | D22: Nikolas | E22: 45 | F22: Licence, licence professionnelle | G22: Croix Blanche | H22: 46006 | I22: 46014 | J22: 46050 | K22: =+J22+180 -> 46230 | N22: =M22+180 -> 180 | R22: 3 | U22: Réorientation | V22: FT acc pro | X22: 46174 | Y22: P874 | AN22: REPRISE DE DROITS ARE JUIN 2026 | AP22: RESTAURATION COMMERCE | AQ22: BOUILLOUX | AR22: Nikolas | AS22: bouilloux.niko@gmail.com
A23: 1 | B23: Madame | C23: BOURASSIN | D23: Gaelle | E23: 45 | G23: Pierre Goujon | H23: 45840 | I23: 45866 | N23: =M23+180 -> 180 | U23: Réorientation | V23: Social freins+ | X23: 45957 | Y23: P772
A24: 1 | B24: Madame | C24: BOUVET | D24: Christina | E24: 49 | F24: Aucun diplôme | G24: Pierre Goujon | H24: 45805 | I24: 45894 | J24: 45988 | K24: =+J24+180 -> 46168 | N24: =M24+180 -> 180 | O24: Santé | P24: Mobilité | U24: Fin DD | V24: FT acc pro | X24: 46082 | Y24: P280 | AN24: CE OK / Candidature Frip'One envoyée le 271125 - en interim depuis decembre
A25: 1 | B25: Madame | C25: BOUVIER | D25: Vanessa | E25: 36 | F25: CAP, BEP | G25: Croix Blanche | H25: 45838 | I25: 45919 | J25: 45968 | K25: =+J25+180 -> 46148 | N25: =M25+180 -> 180 | U25: Positive | W25: CDI >ou= 24h | X25: 46113 | Y25: P355 | AN25: CE OK travaille en ehpad en interim | AO25: SR si absence 090626 | AP25: AIDE SOIGNANTE Jardins de brou | AQ25: BOUVIER | AR25: Vanessa | AS25: vanessa.bouvier@hotmail.fr
A26: 1 | B26: Madame | C26: BRACH | D26: Fatiha | E26: 41 | G26: Croix Blanche | H26: 45825 | I26: 45894 | K26: =+J26+180 -> 180 | N26: =M26+180 -> 180 | U26: Radié suite CLI | AN26: CLI pas de nouvelle
A27: 1 | B27: Madame | C27: BRECANI | D27: Arjana | E27: 48 | F27: Aucun diplôme | G27: Pierre Goujon | H27: 45833 | I27: 45868 | J27: 45868 | K27: =+J27+180 -> 46048 | L27: Renouvellement | M27: 46053 | N27: =M27+180 -> 46233 | O27: Santé | U27: Fin bilan parcours | V27: FT acc pro | X27: 46262 | Y27: P143 | AN27: CE OK / En poste nbre d heures 15h/s (CDD à la semaine - Contrat pérenne à obtenir) / CDI 11/2025 ? | AO27: CDI 11,5h/semaine | AP27: REO SOCIALE / FT selon avis médical | AQ27: BRECANI | AR27: Arjana
A28: 1 | B28: Madame | C28: BRISSON | D28: Amelie | E28: 38 | F28: CAP, BEP | G28: Pierre Goujon | H28: 45917 | I28: 45946 | J28: 45946 | K28: =+J28+180 -> 46126 | N28: =M28+180 -> 180 | O28: Santé mentale | U28: Réorientation | V28: Social freins+ | X28: 46125 | Y28: P267 | AN28: Absence RDV 2 / Mail envoyé le 210126
A29: 1 | B29: Madame | C29: BRUNET | D29: Carole | E29: 37 | F29: CAP, BEP | G29: Croix Blanche | H29: 45812 | I29: 45902 | J29: 45902 | K29: =+J29+180 -> 46082 | L29: Renouvellement | M29: 46083 | N29: =M29+180 -> 46263 | O29: Santé mentale | P29: Permis suspendu | T29: 1 | U29: Fin bilan parcours | V29: FT acc pro | X29: 46267 | Y29: P279 | AN29: REO SOCIALE A ENVISAGER | AP29: SECRETARIAT MEDICAL | AQ29: BRUNET | AR29: Carole | AS29: carolebrunet@orange.fr
A30: 1 | B30: Monsieur | C30: BULINGE | D30: Corentin | E30: 26 | F30: Aucun diplôme | G30: Pierre Goujon | H30: 46057 | I30: 46066 | J30: 46066 | K30: =+J30+180 -> 46246 | N30: =M30+180 -> 180 | U30: Positive | W30: CDI >ou= 24h | X30: 46204 | Y30: P988 | AN30: CDI JUILLET 2026 | AO30: Interim Bressor | AP30: ARMEE DE TERRE | AQ30: BULINGE | AR30: Corentin | AS30: bulingecorentin@gmail.com
A31: 1 | B31: Madame | C31: CALARD | D31: Johanna | E31: 27 | F31: Aucun diplôme | G31: Croix Blanche | H31: 46036 | I31: 46050 | N31: =M31+180 -> 180 | U31: Réorientation | V31: Social freins+ | X31: 46077 | Y31: P1075
A32: 1 | B32: Madame | C32: CAMARA | D32: Mafoudia | E32: 35 | G32: Pierre Goujon | H32: 45826 | I32: 45868 | N32: =M32+180 -> 180 | U32: Radié suite CLI
A33: 1 | B33: Madame | C33: CEESAY | D33: Serra | E33: 26 | F33: Aucun diplôme | G33: Pierre Goujon | H33: 46008 | I33: 46031 | J33: 46031 | K33: =+J33+180 -> 46211 | N33: =M33+180 -> 180 | O33: Langue | P33: Garde enfant | U33: Fin DD | X33: 46113 | Y33: P939 | AN33: CE OK | AO33: RADIATION CAF | AP33: MENAGE
A34: 1 | B34: Monsieur | C34: CESSIN | D34: Patrick | E34: 31 | G34: Pierre Goujon | H34: 45869 | I34: 45924 | K34: =+J34+180 -> 180 | N34: =M34+180 -> 180 | U34: Radié suite CLI | AN34: CLI - pas de nouvelle
A35: 1 | B35: Madame | C35: CHACON COTOS | D35: Yesica | E35: 43 | G35: Pierre Goujon | H35: 45982 | I35: 46000 | J35: 46000 | K35: =+J35+180 -> 46180 | N35: =M35+180 -> 180 | U35: Fin DD | V35: FT acc pro | X35: 46128 | Y35: P360 | AN35: CE OK / BENEFICIAIRE ARE / En attente justif pour réo / Mail envoyé 270226 | AO35: REO FT / DROIT ARE
A36: 1 | B36: Monsieur | C36: CHARNI | D36: Hèdi | E36: 62 | G36: Pierre Goujon | H36: 45846 | I36: 45894 | N36: =M36+180 -> 180 | U36: Réorientation | V36: Social freins+
A37: 1 | B37: Madame | C37: CHOMETTON | D37: Lydie | E37: 34 | F37: CAP, BEP | G37: Pierre Goujon | H37: 45847 | I37: 45860 | J37: 45860 | K37: =+J37+180 -> 46040 | L37: Renouvellement | M37: 46045 | N37: =M37+180 -> 46225 | O37: Santé mentale | R37: 1 | U37: Réorientation | V37: Sociale AAH | X37: 46202 | Y37: P335 | AJ37: 1 | AN37: CE OK / Préco MDPH vers ORSAC a été hospit 3 mois | AO37: Candidature orsac | AP37: ORSAC | AQ37: CHOMETTON | AR37: Lydie | AS37: lilith01volturi@gmail.com
A38: 1 | B38: Madame | C38: COMBEAU | D38: Noémie | G38: Croix Blanche | I38: 45986 | N38: =M38+180 -> 180 | U38: Fin DD | X38: 46083
A39: 1 | B39: Madame | C39: COTOS REGALADO | D39: Nancy | E39: 63 | F39: Aucun diplôme | G39: Croix Blanche | H39: 45832 | I39: 45925 | N39: =M39+180 -> 180 | U39: Réorientation | V39: Sociale retraite | X39: 46023 | Y39: P341
A40: 1 | B40: Monsieur | C40: DAOUD | D40: Boina | E40: 45 | F40: Aucun diplôme | G40: Croix Blanche | H40: 45833 | I40: 45924 | J40: 45924 | K40: =+J40+180 -> 46104 | L40: Renouvellement | M40: 46106 | N40: =M40+180 -> 46286 | O40: Garde enfant | P40: Santé | U40: Fin bilan parcours | V40: FT acco glo | X40: 46290 | Y40: P275 | AN40: REO SOCIALE A ENVISAGER | AO40: ne veut pas faire garder ses enfants | AP40: ESPACE VERTS PROPRETE URBAINE | AQ40: DAOUD | AR40: Boina | AS40: boina.daoud79@gmail.com
A41: 1 | B41: Monsieur | C41: DEMIRKAZIK | D41: Ramazan | E41: 57 | G41: Croix Blanche | H41: 45883 | I41: 45916 | K41: =+J41+180 -> 180 | N41: =M41+180 -> 180 | U41: Radié suite CLI | AN41: CLI pas de nouvelle
A42: 1 | B42: Monsieur | C42: DIALLO | D42: Abdulaye | E42: 33 | G42: Croix Blanche | H42: 45855 | N42: =M42+180 -> 180 | U42: Réorientation | V42: FT acc pro | X42: 46185
A43: 1 | B43: Madame | C43: DOTHAL | D43: Justine | E43: 30 | F43: Aucun diplôme | G43: Croix Blanche | H43: 45870 | I43: 45908 | J43: 45908 | K43: =+J43+180 -> 46088 | L43: Réo FT | N43: =M43+180 -> 180 | O43: Santé | P43: Santé mentale | Q43: Aidante familiale | R43: 2 | U43: Positive | V43: BGE | W43: Créa | X43: 46105 | Y43: P331 | AN43: CE OK / Mail envoyé 210126 / REO SOCIALE A ENVISAGER | AO43: aidante f / reo sociale | AP43: ANIMATRICE GERONTOLOGIE ADMIN EHPAD
A44: 1 | B44: Madame | C44: DUCROZET | D44: Sylvianne | E44: 58 | F44: Baccalauréat | G44: Croix Blanche | H44: 46105 | I44: 46154 | J44: 46154 | K44: =+J44+180 -> 46334 | N44: =M44+180 -> 180 | O44: Santé mentale | U44: Réorientation | V44: Social freins+ | X44: 46176 | Y44: P1178 | AN44: REO SOCIALE A envisager
A45: 1 | B45: Madame | C45: DURMUS | D45: Alev | E45: 44 | G45: Pierre Goujon | H45: 45870 | I45: 45908 | N45: =M45+180 -> 180 | U45: Réorientation | V45: FT acc pro | X45: 45939
B46: Monsieur | C46: EL OUHIDI | D46: Abdellah | E46: 59 | G46: Croix Blanche | H46: 46245 | I46: 46260 | U46: Réorientation | V46: BGE | X46: 46260
A47: 1 | B47: Madame | C47: ESPRIT | D47: Jessicka | E47: 29 | F47: Baccalauréat | I47: 46042 | J47: SDP | K47: =+J47+180 -> #VALUE! | N47: =M47+180 -> 180 | U47: Positive | V47: BGE | W47: Créa | X47: 46129 | AN47: Projet Créa entreprise / Friperie itinérante | AO47: projet autoentreprise | AP47: CREA FRIPERIE ITINERANTE
A48: 1 | B48: Madame | C48: FAYDALI MANDEL | D48: Nahide | E48: 53 | F48: CAP, BEP | G48: Croix Blanche | H48: 46062 | I48: 46125 | J48: 46125 | K48: =+J48+180 -> 46305 | N48: =M48+180 -> 180 | O48: Santé mentale | U48: Réorientation | V48: Social freins+ | X48: 46132 | AN48: BURN OUT / REO SOLCIALE A ENVISAGER
A49: 1 | B49: Monsieur | C49: FERREIRA | D49: Julien | E49: 37 | F49: CAP, BEP | G49: Croix Blanche | H49: 45887 | I49: 45930 | J49: 45930 | K49: =+J49+180 -> 46110 | L49: Tripartite | N49: =M49+180 -> 180 | O49: Santé mentale | P49: Aidant familial | U49: Réorientation | V49: Social freins+ | X49: 46182 | Y49: P1069 | AN49: Réo sociale à envisager / Absence injustifiée 2ème RDV / Sms sans réponse | AO49: Aidant familial | AQ49: FERREIRA | AR49: Julien | AS49: sferreira47@yahoo.fr
A50: 1 | B50: Madame | C50: FETET | D50: Laura | E50: 31 | F50: CAP, BEP | G50: Pierre Goujon | H50: 45828 | I50: 45862 | J50: 45862 | K50: =+J50+180 -> 46042 | L50: Renouvellement | M50: 46047 | N50: =M50+180 -> 46227 | O50: Garde enfant | S50: 2 | U50: Fin bilan parcours | V50: FT acc pro | X50: 46262 | Y50: P334 | AN50: CE OK / CLI revenu / Projet assistante maternelle / Absence RDV 5 / Relance envoyée 230126 + 270226 | AP50: SORTIE FT | AQ50: FETET | AR50: Laura | AS50: laurafetet95@gmail.com
A51: 1 | B51: Madame | C51: GIORDANELLA | D51: Rachel | E51: 63 | G51: Pierre Goujon | H51: 45869 | I51: 45904 | N51: =M51+180 -> 180 | U51: Réorientation | V51: Sociale retraite | X51: 45904
A52: 1 | B52: Madame | C52: GOKBULUT | D52: Eda | E52: 27 | F52: CAP, BEP | G52: Croix Blanche | H52: 45855 | I52: 45869 | J52: 45869 | K52: =+J52+180 -> 46049 | L52: Renouvellement | M52: 46054 | N52: =M52+180 -> 46234 | O52: Garde enfant | P52: Mobilité | U52: Fin bilan parcours | V52: FT acc pro | X52: 46234 | Y52: P752 | AN52: CE OK / CLI repris contact ok | AP52: SORTIE FT | AQ52: GOKBULUT | AR52: Eda | AS52: eda.koc.0104@outlook.fr
A53: 1 | B53: Madame | C53: HASSAN | D53: Roueida | E53: 46 | F53: Aucun diplôme | G53: Pierre Goujon | H53: 45876 | I53: 45936 | J53: 45936 | N53: =M53+180 -> 180 | U53: Réorientation | V53: Social freins+ | X53: 45974 | Y53: P349
A54: 1 | B54: Madame | C54: JAMAI | D54: Miryam | E54: 30 | G54: Croix Blanche | H54: 45800 | I54: 45937 | N54: =M54+180 -> 180 | U54: Réorientation | V54: Sociale maternité
A55: 1 | B55: Madame | C55: KAYRE | D55: Fatou Kine | E55: 35 | F55: Licence, licence professionnelle | G55: Pierre Goujon | H55: 46029 | I55: 46044 | J55: 46044 | K55: =+J55+180 -> 46224 | N55: =M55+180 -> 180 | R55: 1 | S55: 2 | U55: Positive | W55: CDI >ou= 24h | X55: 46143 | Y55: P867 | AN55: CE OK | AO55: CDI | AP55: Projet BTS Compta | AQ55: KAYRE | AR55: Fatou Kine | AS55: kinekayre@gmail.com
B56: Madame | C56: KOLLER | D56: Tiffany | G56: Croix Blanche | H56: 46233 | I56: 46258 | U56: Réorientation | V56: Sociale maternité | X56: 46258
A57: 1 | B57: Madame | C57: KOSTURI-BASTRIU | D57: Nazime | E57: 45 | G57: Croix Blanche | H57: 45827 | I57: 45874 | N57: =M57+180 -> 180 | U57: Réorientation | V57: Social freins+ | X57: 46000
A58: 1 | B58: Madame | C58: KOUYATE | D58: Fanta | E58: 26 | G58: Croix Blanche | H58: 45821 | I58: 45891 | J58: 45891 | K58: 46075 | N58: =M58+180 -> 180 | U58: Positive | V58: FT acc pro | W58: SIAE (FT) | X58: 45952 | Y58: P297
A59: 1 | B59: Madame | C59: LAARABA | D59: Saida | E59: 47 | G59: Croix Blanche | H59: 45784 | I59: 45873 | K59: =+J59+180 -> 180 | N59: =M59+180 -> 180 | O59: Santé | U59: Radié suite CLI | AN59: CE OK / CLI pas de retour
A60: 1 | B60: Madame | C60: LAMBERT | D60: Jennifer | E60: 34 | G60: Croix Blanche | H60: 45800 | I60: 45894 | K60: =+J60+180 -> 180 | N60: =M60+180 -> 180 | U60: Radié suite CLI | AN60: CLI pas de nouvelle
A61: 1 | B61: Madame | C61: LENOIR | D61: Sabrina | E61: 45 | F61: Baccalauréat | G61: Croix Blanche | H61: 45870 | I61: 45919 | J61: 45919 | K61: =+J61+180 -> 46099 | N61: =M61+180 -> 180 | O61: Santé | P61: Enfants malades | U61: Déménagement | X61: 46113 | AN61: REO SOCIALE A ENVISAGER / CF PLANNING AIDANTE FAMILIALE / Absence injustifiée 2ème RDV mail envoyé 311025 / Relance 260126 | AO61: SUSPENSION REMOB
A62: 1 | B62: Madame | C62: LEONARDE | D62: Bibiane | E62: 28 | F62: Aucun diplôme | G62: Croix Blanche | H62: 45833 | I62: 45891 | J62: 45891 | K62: =+J62+180 -> 46071 | N62: =M62+180 -> 180 | O62: Santé mentale | U62: Fin DD | X62: 46066 | Y62: P273 | AN62: CE OK / Préco ESAT / Absence RDV 4 / Relance 260126
A63: 1 | B63: Monsieur | C63: LIKIDI | D63: Quektor | E63: 47 | F63: Aucun diplôme | G63: Pierre Goujon | H63: 46059 | I63: 46071 | J63: 46071 | K63: =+J63+180 -> 46251 | N63: =M63+180 -> 180 | R63: 2 | U63: Réorientation | V63: FT acc pro | W63: SIAE (FT) | X63: 46254 | Y63: P983 | AN63: CDDI jusqu'au 31/07 | AP63: INDUSTRIE ESPACES VERTS
A64: 1 | B64: Madame | C64: LOUCIF | D64: Ines | E64: 30 | F64: CAP, BEP | G64: Pierre Goujon | H64: 45833 | I64: 45866 | J64: 45866 | K64: =+J64+180 -> 46046 | L64: Renouvellement | M64: 46051 | N64: =M64+180 -> 46231 | O64: Santé mentale | P64: Garde enfant | R64: 2 | U64: Fin bilan parcours | V64: FT acc pro | X64: 46262 | Y64: P328 | AN64: CE OK travaille en auto entreprise | AP64: SORTIE FT | AQ64: LOUCIF | AR64: Ines | AS64: ines.loucif8595@gmail.com
A65: 1 | B65: Madame | C65: MATHON | D65: Emilie | E65: 45 | F65: Aucun diplôme | G65: Croix Blanche | H65: 45814 | I65: 45874 | J65: 45874 | K65: =J65+180 -> 46054 | N65: =M65+180 -> 180 | U65: Positive | V65: FT acc pro | W65: SIAE (FT) | X65: 46014 | Y65: P294
A66: 1 | B66: Monsieur | C66: MERCIER | D66: Florent | E66: 53 | G66: Croix Blanche | H66: 45826 | I66: 45868 | J66: 46233 | K66: =+J66+180 -> 46413 | L66: Renouvellement | M66: 46052 | N66: =M66+180 -> 46232 | O66: Santé | P66: Mobilité | U66: Fin bilan parcours | V66: Social freins+ | X66: 46234 | Y66: P1073 | AN66: CE OK / Absence injustifiée 2ème RDV pas de nouvelle CLI | AO66: Tripartite | AP66: SORTIE FT | AQ66: MERCIER | AR66: Florent
A67: 1 | B67: Monsieur | C67: MEUNIER | D67: Yann | E67: 45 | F67: CAP, BEP | G67: Pierre Goujon | H67: 45828 | I67: 45873 | J67: 45873 | K67: =+J67+180 -> 46053 | L67: Renouvellement | M67: 46058 | N67: =M67+180 -> 46238 | O67: Santé | U67: Fin bilan parcours | V67: FT acco glo | X67: 46239 | Y67: P359 | AN67: DDE REO SOCIALE FAITE AU CD01 le 300426 | AO67: RENOUVELLEMENT + REO SOCIALE | AP67: REO SOCIALE | AQ67: MEUNIER | AR67: Yann | AS67: ymeunier02@gmail.com
A68: 1 | B68: Monsieur | C68: MGALLES | D68: Khaled | E68: 39 | G68: Pierre Goujon | H68: 45856 | I68: 45876 | N68: =M68+180 -> 180 | U68: Fin DD | V68: FT acc pro | W68: France Travail
A69: 1 | B69: Madame | C69: MICHEL | D69: Elodie | E69: 38 | F69: DEUG, BTS, DUT, DEUST | G69: Pierre Goujon | H69: 45825 | I69: 45873 | N69: =M69+180 -> 180 | U69: Réorientation | V69: Social freins+ | X69: 46007 | Y69: P292
A70: 1 | B70: Madame | C70: MOISSONNIER | D70: Marie Claude | E70: 66 | G70: Pierre Goujon | H70: 45825 | I70: 45873 | N70: =M70+180 -> 180 | U70: Réorientation | V70: Sociale retraite | X70: 45877
A71: 1 | B71: Madame | C71: MONIN | D71: Nathalie | E71: 57 | F71: CAP, BEP | G71: Pierre Goujon | H71: 46107 | I71: 46128 | J71: 46128 | K71: =+J71+180 -> 46308 | N71: =M71+180 -> 180 | R71: 2 | U71: Réorientation | V71: Social freins+ | X71: 46272 | Y71: P1121 | AP71: Réo sociale (AM + 3 mois)
A72: 1 | B72: Monsieur | C72: MOREL | D72: Anthony | E72: 37 | G72: Pierre Goujon | H72: 45825 | I72: 45874 | N72: =M72+180 -> 180 | U72: Déménagement | X72: 46066 | Y72: P269
A73: 1 | B73: Monsieur | C73: MOREL | D73: Alexandre | E73: 27 | F73: Aucun diplôme | G73: Pierre Goujon | H73: 45855 | I73: 45866 | J73: 45866 | K73: =+J73+180 -> 46046 | L73: Renouvellement | M73: 46051 | N73: =M73+180 -> 46231 | O73: Santé | P73: Santé mentale | R73: 1 | U73: Fin bilan parcours | V73: FT acco glo | X73: 46226 | Y73: P142 | AN73: CE OK | AO73: Djamila / Annick | AP73: SORTIE FT | AQ73: MOREL | AR73: Alexandre | AS73: dragonyx.contact@gmail.com
A74: 1 | B74: Madame | C74: MOREL | D74: Virginie | E74: 47 | F74: Aucun diplôme | G74: Pierre Goujon | H74: 45800 | I74: 45875 | J74: 45875 | K74: =+J74+180 -> 46055 | L74: Renouvellement | M74: 46060 | N74: =M74+180 -> 46240 | O74: Logement | P74: Mobilité | R74: 1 | U74: Fin bilan parcours | V74: FT acco glo | X74: 46261 | Y74: P356 | AN74: CE OK / Candidature Orsac envoyé / Projet formation à monter polissage en bijouterie | AP74: JOAILLERIE | AQ74: MOREL | AR74: Virginie | AS74: calyps.1213@gmail.com
A75: 1 | B75: Madame | C75: MOSSMAN | D75: Tiaré | E75: 51 | F75: Aucun diplôme | G75: Pierre Goujon | H75: 45903 | I75: 46015 | J75: 46015 | K75: =+J75+180 -> 46195 | L75: Renouvellement | M75: 46198 | N75: =M75+180 -> 46378 | O75: Santé | U75: Réorientation | V75: Social freins+ | X75: 46225 | Y75: P750 | AH75: 1 | AN75: CE OK / Acco agent de santé envoyé 241225 | AO75: REO SOCIALE
A76: 1 | B76: Madame | C76: MOURADOV | D76: Zina | E76: 60 | G76: Pierre Goujon | U76: Fin DD | X76: 46259
A77: 1 | B77: Monsieur | C77: MOURAUD | D77: Kévin | E77: 36 | F77: Aucun diplôme | G77: Pierre Goujon | H77: 45825 | I77: 45875 | J77: 45875 | K77: 46239 | L77: Renouvellement | N77: =M77+180 -> 180 | O77: Santé mentale | P77: Expérience | Q77: Posture pro | U77: Réorientation | V77: Social freins+ | X77: 46182 | Y77: P332 | AN77: CE OK | AO77: CMP | AP77: SOCIAL | AQ77: MOURAUD | AR77: Kévin | AS77: kevinmouraud@yahoo.fr
A78: 0 | B78: Madame | C78: MOURSAL IBET | D78: Kaltouma | E78: 46 | G78: Croix Blanche | H78: 46028 | I78: 46121 | N78: =M78+180 -> 180 | O78: Santé | U78: Réorientation | V78: Social freins+ | X78: 46196 | AO78: Faire une réo sociale car 3 mois d'arret
A79: 1 | B79: Madame | C79: MURATI | D79: Anxhelina | E79: 23 | G79: Pierre Goujon | H79: 45856 | I79: 45897 | N79: =M79+180 -> 180 | U79: Réorientation | V79: Sociale maternité
A80: 1 | B80: Monsieur | C80: MURY | D80: Alexis | E80: 35 | F80: CAP, BEP | G80: Pierre Goujon | H80: 45887 | I80: 45932 | N80: =M80+180 -> 180 | U80: Fin DD | X80: 45975 | Y80: P266
A81: 1 | B81: Madame | C81: MZOURI | D81: Chama | E81: 41 | G81: Pierre Goujon | H81: 45811 | I81: 45876 | K81: =+J81+180 -> 180 | N81: =M81+180 -> 180 | U81: Radié suite CLI | AN81: CLI pas de nouvelle
A82: 1 | B82: Monsieur | C82: NABI ZADA | D82: Ghulam | E82: 61 | G82: Pierre Goujon | H82: 45911 | I82: 45936 | N82: =M82+180 -> 180 | U82: Réorientation | V82: Social freins+ | X82: 45985
A83: 1 | B83: Madame | C83: NAILLOD | D83: Amélie | E83: 36 | G83: Croix Blanche | H83: 45824 | I83: 45877 | N83: =M83+180 -> 180 | U83: Radié suite CLI
A84: 1 | B84: Madame | C84: NEUER | D84: Friederike | E84: 39 | G84: Pierre Goujon | H84: 45834 | I84: 45876 | N84: =M84+180 -> 180 | U84: Réorientation | V84: FT acc pro | X84: 45877
A85: 1 | B85: Madame | C85: NOEL | D85: Jennifer | E85: 39 | F85: Aucun diplôme | G85: Pierre Goujon | H85: 46101 | I85: 46121 | J85: 46121 | K85: =+J85+180 -> 46301 | N85: =M85+180 -> 180 | R85: 1 | U85: Fin DD | X85: 46266 | AN85: Mr en CDI temps plein Fin D&D 1026
A86: 1 | B86: Monsieur | C86: PANDOU | D86: Olivier | E86: 33 | F86: Aucun diplôme | G86: Pierre Goujon | H86: 45869 | I86: 45917 | J86: 45917 | K86: =J86+180 -> 46097 | N86: =M86+180 -> 180 | U86: Réorientation | V86: Social freins+ | X86: 46009 | Y86: P126
A87: 1 | B87: Madame | C87: PEKDURU | D87: Pembe | E87: 59 | F87: Aucun diplôme | G87: Pierre Goujon | H87: 45825 | I87: 45888 | J87: 45931 | K87: =+J87+180 -> 46111 | L87: REO SOCIALE | N87: =M87+180 -> 180 | O87: Santé | P87: Illetrisme | Q87: Aucune expérience professionnelle | U87: Fin DD | X87: 46269 | Y87: P347 | AN87: Introuvable SDP / Mail envoyé CDS 010726 + 040926 | AO87: souhait renonce rsa | AP87: D&D à valider | AQ87: PEKDURU | AR87: Pembe
A88: 1 | B88: Monsieur | C88: PERDRIX | D88: Dylan | E88: 28 | G88: Pierre Goujon | H88: 45827 | I88: 38603 | N88: =M88+180 -> 180 | U88: Réorientation | V88: Social freins+ | X88: 46014
A89: 1 | B89: Monsieur | C89: PERRIN | D89: Frédéric | E89: 54 | F89: CAP, BEP | G89: Pierre Goujon | H89: 45827 | I89: 45889 | N89: =M89+180 -> 180 | U89: Radié suite CLI | X89: 45952
A90: 1 | B90: Madame | C90: PIERROT | D90: Carmen | E90: 55 | G90: Pierre Goujon | H90: 45825 | I90: 45905 | N90: =M90+180 -> 180 | U90: Réorientation | V90: BGE | X90: 45905
A91: 1 | B91: Monsieur | C91: PINHEIRO | D91: Alexandre | E91: 43 | F91: CAP, BEP | G91: Croix Blanche | H91: 45862 | I91: 46013 | J91: 46042 | K91: =+J91+180 -> 46222 | N91: =M91+180 -> 180 | O91: Santé | U91: Réorientation | V91: Social freins+ | X91: 46182 | Y91: P937 | AN91: CE OK / REO SOCIALE A ENVISAGER | AO91: REO SOCIALE | AQ91: PINHEIRO | AR91: Alexandre | AS91: anniriviere2@gmail.com
A92: 1 | B92: Madame | C92: POTKI | D92: Sharifeh | E92: 53 | F92: Licence, licence professionnelle | G92: Pierre Goujon | H92: 45798 | I92: 45938 | J92: 45938 | K92: 46120 | N92: =M92+180 -> 180 | U92: Positive | V92: FT acc pro | W92: SIAE (FT) | X92: 45992 | Y92: P352
A93: 1 | B93: Monsieur | C93: RIBOLLA | D93: Fabien | E93: 44 | F93: CAP, BEP | G93: Pierre Goujon | H93: 45827 | I93: 45891 | J93: 45891 | K93: =+J93+180 -> 46071 | L93: Renouvellement | M93: 46076 | N93: =M93+180 -> 46256 | O93: Voiture | U93: Fin bilan parcours | V93: FT acco glo | X93: 46254 | Y93: P295 | AN93: SR si absence 2008 | AO93: PROJET CREATION | AP93: MACONNERIE | AQ93: RIBOLLA | AR93: Fabien | AS93: fabienspicy@gmail.com
A94: 1 | B94: Monsieur | C94: ROBARDEY | D94: Mathieu | E94: 36 | F94: Aucun diplôme | G94: Pierre Goujon | H94: 45854 | I94: 45931 | J94: 45931 | K94: =J94+180 -> 46111 | N94: =M94+180 -> 180 | U94: Positive | V94: BGE | W94: Créa | X94: 45981 | Y94: P339
A95: 1 | B95: Madame | C95: ROUSSEAU | D95: Stéphanie | E95: 42 | G95: Croix Blanche | H95: 45819 | I95: 45875 | N95: =M95+180 -> 180 | U95: Fin DD | X95: 45901
A96: 1 | B96: Monsieur | C96: ROUSSEAUX | D96: Frédéric | E96: 54 | F96: Aucun diplôme | G96: Pierre Goujon | H96: 45825 | I96: 45894 | J96: 45894 | K96: =+J96+180 -> 46074 | L96: Tripartite | M96: 46075 | N96: =M96+180 -> 46255 | O96: Santé mentale | P96: Addiction | U96: Fin bilan parcours | V96: FT acco glo | X96: 46260 | Y96: P326 | AN96: CE OK / Réo sociale à envisager / BDP ENVOYE | AO96: TRIPARTITE | AQ96: ROUSSEAUX | AR96: Frédéric
A97: 1 | B97: Madame | C97: SAEED | D97: Sumaia | E97: 43 | F97: Aucun diplôme | G97: Croix Blanche | H97: 45819 | I97: 45875 | J97: 45875 | K97: =+J97+180 -> 46055 | L97: Renouvellement | M97: 46060 | N97: =M97+180 -> 46240 | O97: Santé | P97: Langue | U97: Fin bilan parcours | V97: FT acco glo | X97: 46241 | Y97: P354 | AN97: CE OK / Projet Formation fleuriste ?? | AO97: Permis | AP97: FLEURISTE | AQ97: SAEED | AR97: Sumaia | AS97: sumaiasaeed015@gmail.com
A98: 1 | B98: Madame | C98: SALLERON | D98: Ophélie | E98: 32 | F98: CAP, BEP | G98: Pierre Goujon | H98: 45842 | I98: 45861 | J98: 45861 | K98: =J98+180 -> 46041 | M98: 46046 | N98: =M98+180 -> 46226 | U98: Réorientation | V98: Social freins+ | X98: 46078 | Y98: P345
A99: 1 | B99: Madame | C99: SATTA | D99: Saadia | E99: 45 | F99: Aucun diplôme | G99: Pierre Goujon | H99: 45846 | I99: 45891 | J99: 45891 | K99: =+J99+180 -> 46071 | L99: Renouvellement | M99: 46072 | N99: =M99+180 -> 46252 | O99: Langue | U99: Fin bilan parcours | V99: FT acco glo | X99: 46253 | Y99: P350 | Z99: 1 | AN99: CE OK / SIAE | AO99: Maison nette | AP99: MENAGE | AQ99: SATTA | AR99: Saadia | AS99: saadiasatta@gmail.com
A100: 1 | B100: Madame | C100: SAVOVA | D100: Snejana | E100: 46 | F100: Aucun diplôme | G100: Croix Blanche | H100: 45834 | I100: 45873 | J100: 45873 | K100: =+J100+180 -> 46053 | L100: Renouvellement | M100: 46058 | N100: =M100+180 -> 46238 | O100: Santé | U100: Fin bilan parcours | V100: FT acco glo | X100: 46262 | Y100: P353 | Z100: 1 | AH100: 1 | AN100: CE OK / REO SOCIALE INAPTITUDE santé | AP100: PETITE MANUTENTION | AQ100: SAVOVA | AR100: Snejana | AS100: savova0114@gmail.com
A101: 1 | B101: Madame | C101: SAYAH | D101: Fatma | E101: 42 | F101: Aucun diplôme | G101: Croix Blanche | H101: 45826 | I101: 45875 | J101: 45875 | K101: =+J101+180 -> 46055 | L101: RENOUVELLEMENT | M101: 46061 | N101: =M101+180 -> 46241 | O101: Langue | R101: 1 | U101: Fin bilan parcours | V101: FT acco glo | X101: 46261 | Y101: P298 | Z101: 1 | AN101: CE OK / Fracture pied / Convalescence en cours / BDP ENVOYE | AO101: France domicile services | AP101: AIDE A LA PERSONNE | AQ101: SAYAH | AR101: Fatma | AS101: sayahfatma@outlook.com
...

Sheet Sanctions + absence 
C1: Absence avant signature CE | E1: Absences 2026 cumulées par mois (rdv-atelier-forum-jobdating..) Après signature CE | Q1: Niveau 1 : AVERTISSEMENT AVANT SUSPENSION | W1: Niveau 2 : suspension remobilisation | Z1: Etape 3 : Etape pluridisciplinaire CLI | AA1: 2 eme manquement (process direct etape 3)
A2: Exemple: | C2: 1 | G2: 1 | Q2: 1 | R2: 46084 | S2: 46089 | T2: =S2+15 -> 46104 | U2: 0 | V2: 1 | W2: =T2+35 -> 46139 | X2: 0 | Y2: 1 | Z2: 46147 | AC2: =AB2+35 -> 35
A3: Nom | B3: Prénom | C3: 1ER RDV | D3: 2EME | E3: 1er mois | F3: 2e mois | G3: 3e mois | H3: 4e mois | I3: 5e mois | J3: 6e mois | K3: 7e mois | L3: 8e mois | M3: 9e mois | N3: 10e mois | O3: 11e mois | P3: 12e mois | Q3: Dde etude de situation. | R3: date de la demande | S3: Date courrier CDS (voir extraction transmise) | T3: Délai 15 jours pour contact | U3: Contact BRSA - 15 jours | V3: Mail INFO CDS | W3: Délai de 35 jours pour reprendre contact | X3: le BRSA s'est manifesté ? | Y3: Mail d'info au CDS manifestation ou non dans les 35 jours | Z3: Date CLI si le BRSA ne s'est pas manifesté au bout des 35 jours | AA3: date demande étude de situation (Mail CDS) | AB3: DATE courrier CDS | AC3: 35j pour reprendre contact date butoire | AD3: DATE CLI
A4: ='CROIX BLANCHE PG'!#REF! -> #REF! | B4: ='CROIX BLANCHE PG'!#REF! -> #REF! | C4: 1 | D4: 1 | Q4: 1 | R4: 45960 | T4: =S4+15 -> 15 | W4: =T4+35 -> 50 | AC4: =AB4+35 -> 35
A5: ='CROIX BLANCHE PG'!C9 -> AHMADI | B5: ='CROIX BLANCHE PG'!D9 -> Diba | T5: =S5+15 -> 15 | W5: =S5+50 -> 50 | AC5: =AB5+35 -> 35
A6: ='CROIX BLANCHE PG'!#REF! -> #REF! | B6: ='CROIX BLANCHE PG'!#REF! -> #REF! | C6: 1 | D6: 1 | T6: =S6+15 -> 15 | W6: =S6+50 -> 50 | AC6: =AB6+35 -> 35
A7: ALVES | B7: Merryl
A8: ='CROIX BLANCHE PG'!C13 -> AMARI | B8: ='CROIX BLANCHE PG'!D13 -> Yamina | C8: 1 | T8: =S8+15 -> 15 | W8: =S8+50 -> 50 | AC8: =AB8+35 -> 35
A9: ARARI | B9: Jennifer | Q9: 1 | R9: 45894
A10: ='CROIX BLANCHE PG'!C14 -> ARIFI | B10: ='CROIX BLANCHE PG'!D14 -> Sabrina | T10: =S10+15 -> 15 | W10: =S10+50 -> 50 | AC10: =AB10+35 -> 35
A11: ='CROIX BLANCHE PG'!C16 -> ATHOUMANI | B11: ='CROIX BLANCHE PG'!D16 -> Marie | T11: =S11+15 -> 15 | W11: =S11+50 -> 50 | AC11: =AB11+35 -> 35
A12: AYACH | B12: Samia | G12: 1
A13: ='CROIX BLANCHE PG'!C19 -> BACAR | B13: ='CROIX BLANCHE PG'!D19 -> Mariata | T13: =S13+15 -> 15 | W13: =S13+50 -> 50 | AC13: =AB13+35 -> 35
A14: ='CROIX BLANCHE PG'!C20 -> BAHAR | B14: ='CROIX BLANCHE PG'!D20 -> Laura | T14: =S14+15 -> 15 | W14: =S14+50 -> 50 | AC14: =AB14+35 -> 35
A15: ='BRSA SORTIES'!C15 -> BAITICHE | B15: ='BRSA SORTIES'!D15 -> Karima | T15: =S15+15 -> 15 | W15: =S15+50 -> 50 | AC15: =AB15+35 -> 35
A16: ='CROIX BLANCHE PG'!#REF! -> #REF! | B16: ='CROIX BLANCHE PG'!#REF! -> #REF! | C16: 1 | D16: 1 | Q16: 1 | R16: 45876 | T16: =S16+15 -> 15 | W16: =S16+50 -> 50 | AC16: =AB16+35 -> 35
A17: BASSUS | B17: Jason | F17: 1 | Q17: 1 | R17: 46197 | S17: 46202 | T17: =S17+15 -> 46217
A18: ='CROIX BLANCHE PG'!C25 -> BEKELE | B18: ='CROIX BLANCHE PG'!D25 -> Eteferahu | C18: 1 | T18: =S18+15 -> 15 | W18: =S18+50 -> 50 | AC18: =AB18+35 -> 35
A19: ='CROIX BLANCHE PG'!C26 -> BELFASSI | B19: ='CROIX BLANCHE PG'!D26 -> Maria Dolores | H19: 1 | Q19: 1 | R19: 46133 | S19: 46140 | T19: =S19+15 -> 46155 | W19: =S19+50 -> 46190 | Z19: 46205 | AC19: =AB19+35 -> 35
A20: ='CROIX BLANCHE PG'!C27 -> BENAISSA | B20: ='CROIX BLANCHE PG'!D27 -> Radia | T20: =S20+15 -> 15 | W20: =S20+50 -> 50 | AC20: =AB20+35 -> 35
A21: ='CROIX BLANCHE PG'!C29 -> BEN EL OUALI | B21: ='CROIX BLANCHE PG'!D29 -> Anouar | T21: =S21+15 -> 15 | W21: =S21+50 -> 50 | AC21: =AB21+35 -> 35
A22: BENMELLOUK | B22: Abdelkader | G22: 1
A23: ='CROIX BLANCHE PG'!C31 -> BENOIT | B23: ='CROIX BLANCHE PG'!D31 -> Xavier | C23: 1 | D23: 1 | H23: 1 | Q23: 1 | R23: 46176 | S23: 46204 | T23: =S23+15 -> 46219 | W23: =S23+50 -> 46254 | AC23: =AB23+35 -> 35
A24: ='CROIX BLANCHE PG'!C32 -> BENZEKHROUFA | B24: ='CROIX BLANCHE PG'!D32 -> Abdelghani | F24: 1 | Q24: 1 | R24: 46128 | T24: =S24+15 -> 15 | W24: =S24+50 -> 50 | AC24: =AB24+35 -> 35
A25: ='CROIX BLANCHE PG'!C34 -> BERTHILLOT | B25: ='CROIX BLANCHE PG'!D34 -> Léa | G25: 1 | T25: =S25+15 -> 15 | W25: =S25+50 -> 50 | AC25: =AB25+35 -> 35
A26: ='BRSA SORTIES'!C19 -> BLANC | B26: ='BRSA SORTIES'!D19 -> Mélissa | T26: =S26+15 -> 15 | W26: =S26+50 -> 50 | AC26: =AB26+35 -> 35
A27: ='BRSA SORTIES'!C20 -> BONNET | B27: ='BRSA SORTIES'!D20 -> Cédric | T27: =S27+15 -> 15 | W27: =S27+50 -> 50 | AC27: =AB27+35 -> 35
A28: ='BRSA SORTIES'!C22 -> BOUILLOUX | B28: ='BRSA SORTIES'!D22 -> Nikolas | C28: 1 | T28: =S28+15 -> 15 | W28: =S28+50 -> 50 | AC28: =AB28+35 -> 35
A29: ='CROIX BLANCHE PG'!#REF! -> #REF! | B29: ='CROIX BLANCHE PG'!#REF! -> #REF! | C29: 1 | T29: =S29+15 -> 15 | W29: =S29+50 -> 50 | AC29: =AB29+35 -> 35
A30: ='CROIX BLANCHE PG'!#REF! -> #REF! | B30: ='CROIX BLANCHE PG'!#REF! -> #REF! | C30: 1 | T30: =S30+15 -> 15 | W30: =S30+50 -> 50 | AC30: =AB30+35 -> 35
A31: ='CROIX BLANCHE PG'!#REF! -> #REF! | B31: ='CROIX BLANCHE PG'!#REF! -> #REF! | C31: 1 | D31: 1 | Q31: 1 | R31: 45898 | T31: =S31+15 -> 15 | W31: =S31+50 -> 50 | AC31: =AB31+35 -> 35
A32: ='BRSA SORTIES'!C27 -> BRECANI | B32: ='BRSA SORTIES'!D27 -> Arjana | T32: =S32+15 -> 15 | W32: =S32+50 -> 50 | AC32: =AB32+35 -> 35
A33: ='CROIX BLANCHE PG'!#REF! -> #REF! | B33: ='CROIX BLANCHE PG'!#REF! -> #REF! | T33: =S33+15 -> 15 | W33: =S33+50 -> 50 | AC33: =AB33+35 -> 35
A34: ='BRSA SORTIES'!C29 -> BRUNET | B34: ='BRSA SORTIES'!D29 -> Carole | T34: =S34+15 -> 15 | W34: =S34+50 -> 50 | AC34: =AB34+35 -> 35
A35: ='CROIX BLANCHE PG'!C42 -> BRUZEAU | B35: ='CROIX BLANCHE PG'!D42 -> Laura | T35: =S35+15 -> 15 | W35: =S35+50 -> 50 | AC35: =AB35+35 -> 35
A36: ='CROIX BLANCHE PG'!C43 -> BUATTIER | B36: ='CROIX BLANCHE PG'!D43 -> Christelle | Q36: 1 | R36: 46140 | S36: 46146 | T36: =S36+15 -> 46161 | W36: =S36+50 -> 46196 | Z36: 46205 | AC36: =AB36+35 -> 35
A37: ='CROIX BLANCHE PG'!#REF! -> #REF! | B37: ='CROIX BLANCHE PG'!#REF! -> #REF! | T37: =S37+15 -> 15 | W37: =S37+50 -> 50 | AC37: =AB37+35 -> 35
A38: CAMARA | B38: Mafoudia | Q38: 1 | R38: 45933
A39: ='CROIX BLANCHE PG'!#REF! -> #REF! | B39: ='CROIX BLANCHE PG'!#REF! -> #REF! | T39: =S39+15 -> 15 | W39: =S39+50 -> 50 | AC39: =AB39+35 -> 35
A40: ='CROIX BLANCHE PG'!#REF! -> #REF! | B40: ='CROIX BLANCHE PG'!#REF! -> #REF! | C40: 1 | D40: 1 | Q40: 1 | R40: 45933 | T40: =S40+15 -> 15 | W40: =S40+50 -> 50 | AC40: =AB40+35 -> 35
A41: ='CROIX BLANCHE PG'!#REF! -> #REF! | B41: ='CROIX BLANCHE PG'!#REF! -> #REF! | T41: =S41+15 -> 15 | W41: =S41+50 -> 50 | AC41: =AB41+35 -> 35
A42: ='CROIX BLANCHE PG'!C45 -> CHARNAY | B42: ='CROIX BLANCHE PG'!D45 -> Cindy | C42: 1 | D42: 1 | Q42: 1 | R42: 46065 | T42: =S42+15 -> 15 | W42: =S42+50 -> 50 | AC42: =AB42+35 -> 35
A43: CHARNI | B43: Hédi | Q43: 1 | R43: 45867
A44: ='CROIX BLANCHE PG'!C46 -> CHAVE | B44: ='CROIX BLANCHE PG'!D46 -> Baptiste | L44: 1 | T44: =S44+15 -> 15 | W44: =S44+50 -> 50 | AC44: =AB44+35 -> 35
A45: ='CROIX BLANCHE PG'!#REF! -> #REF! | B45: ='CROIX BLANCHE PG'!#REF! -> #REF! | T45: =S45+15 -> 15 | W45: =S45+50 -> 50 | AC45: =AB45+35 -> 35
A46: ='BRSA SORTIES'!C40 -> DAOUD | B46: ='BRSA SORTIES'!D40 -> Boina | T46: =S46+15 -> 15 | W46: =S46+50 -> 50 | AC46: =AB46+35 -> 35
A47: ='CROIX BLANCHE PG'!C48 -> DA SILVA GONCALVES | B47: ='CROIX BLANCHE PG'!D48 -> Samuel | T47: =S47+15 -> 15 | W47: =S47+50 -> 50 | AC47: =AB47+35 -> 35
A48: ='CROIX BLANCHE PG'!C49 -> DBIJA | B48: ='CROIX BLANCHE PG'!D49 -> Hafida | T48: =S48+15 -> 15 | W48: =S48+50 -> 50 | AC48: =AB48+35 -> 35
A49: ='CROIX BLANCHE PG'!C50 -> DECAILLON | B49: ='CROIX BLANCHE PG'!D50 -> Candide | K49: 1 | T49: =S49+15 -> 15 | W49: =S49+50 -> 50 | AC49: =AB49+35 -> 35
A50: ='CROIX BLANCHE PG'!#REF! -> #REF! | B50: ='CROIX BLANCHE PG'!#REF! -> #REF! | C50: 1 | D50: 1 | Q50: 1 | R50: 45938 | T50: =S50+15 -> 15 | W50: =S50+50 -> 50 | AC50: =AB50+35 -> 35
A51: ='CROIX BLANCHE PG'!#REF! -> #REF! | B51: ='CROIX BLANCHE PG'!#REF! -> #REF! | T51: =S51+15 -> 15 | W51: =S51+50 -> 50 | AC51: =AB51+35 -> 35
A52: DUCROZET | B52: Sylvianne
A53: ='CROIX BLANCHE PG'!C55 -> EL MOUSTAOUI | B53: ='CROIX BLANCHE PG'!D55 -> Sadik | C53: 1 | T53: =S53+15 -> 15 | W53: =S53+50 -> 50 | AC53: =AB53+35 -> 35
A54: ='CROIX BLANCHE PG'!#REF! -> #REF! | B54: ='CROIX BLANCHE PG'!#REF! -> #REF! | G54: 1 | T54: =S54+15 -> 15 | W54: =S54+50 -> 50 | AC54: =AB54+35 -> 35
A55: ='CROIX BLANCHE PG'!#REF! -> #REF! | B55: ='CROIX BLANCHE PG'!#REF! -> #REF! | T55: =S55+15 -> 15 | W55: =S55+50 -> 50 | AC55: =AB55+35 -> 35
A56: ='CROIX BLANCHE PG'!C56 -> FETET | B56: ='CROIX BLANCHE PG'!D56 -> Jennifer | T56: =S56+15 -> 15 | W56: =S56+50 -> 50 | AC56: =AB56+35 -> 35
A57: ='BRSA SORTIES'!C50 -> FETET | B57: ='BRSA SORTIES'!D50 -> Laura | D57: 1 | K57: 1 | Q57: 1 | R57: 45933 | T57: =S57+15 -> 15 | W57: =S57+50 -> 50 | AC57: =AB57+35 -> 35
A58: FIEMS | B58: Grégory | C58: 1
A59: ='CROIX BLANCHE PG'!C59 -> GOBERT | B59: ='CROIX BLANCHE PG'!D59 -> Edwige | K59: 1 | T59: =S59+15 -> 15 | W59: =S59+50 -> 50 | AC59: =AB59+35 -> 35
A60: ='CROIX BLANCHE PG'!#REF! -> #REF! | B60: ='CROIX BLANCHE PG'!#REF! -> #REF! | D60: 1 | Q60: 1 | R60: 45933 | T60: =S60+15 -> 15 | W60: =S60+50 -> 50 | AC60: =AB60+35 -> 35
A61: ='CROIX BLANCHE PG'!C60 -> HADZI-ALIJA | B61: ='CROIX BLANCHE PG'!D60 -> Erdan | C61: 1 | D61: 1 | Q61: 1 | R61: 45933 | T61: =S61+15 -> 15 | W61: =S61+50 -> 50 | AC61: =AB61+35 -> 35
A62: HAMMAMI | B62: Faysal | F62: 1 | Q62: 1 | R62: 46261 | S62: 46262 | T62: =S62+15 -> 46277
A63: ='CROIX BLANCHE PG'!C62 -> HAMMOUMI | B63: ='CROIX BLANCHE PG'!D62 -> Mohammed | T63: =S63+15 -> 15 | W63: =S63+50 -> 50 | AC63: =AB63+35 -> 35
A64: ='CROIX BLANCHE PG'!C64 -> HASSANI | B64: ='CROIX BLANCHE PG'!D64 -> Koulthoumi | T64: =S64+15 -> 15 | W64: =S64+50 -> 50 | AC64: =AB64+35 -> 35
A65: ='CROIX BLANCHE PG'!C65 -> HOUICHI | B65: ='CROIX BLANCHE PG'!D65 -> Hikmet | T65: =S65+15 -> 15 | W65: =S65+50 -> 50 | AC65: =AB65+35 -> 35
A66: IBADIOUNE | B66: Jamila
A67: IMMEDIATO | B67: Eva
A68: ='CROIX BLANCHE PG'!C68 -> KALINDA | B68: ='CROIX BLANCHE PG'!D68 -> Léopold | T68: =S68+15 -> 15 | W68: =S68+50 -> 50 | AC68: =AB68+35 -> 35
A69: ='CROIX BLANCHE PG'!C69 -> KARADAVUT | B69: ='CROIX BLANCHE PG'!D69 -> Pembe | C69: 1 | G69: 1 | T69: =S69+15 -> 15 | W69: =S69+50 -> 50 | AC69: =AB69+35 -> 35
A70: ='CROIX BLANCHE PG'!C70 -> KASEMI | B70: ='CROIX BLANCHE PG'!D70 -> Elsaïda | C70: 1 | Q70: 1 | R70: 46141 | T70: =S70+15 -> 15 | W70: =S70+50 -> 50 | AC70: =AB70+35 -> 35
A71: ='CROIX BLANCHE PG'!#REF! -> #REF! | B71: ='CROIX BLANCHE PG'!#REF! -> #REF! | T71: =S71+15 -> 15 | W71: =S71+50 -> 50 | AC71: =AB71+35 -> 35
A72: ='CROIX BLANCHE PG'!C71 -> KIM | B72: ='CROIX BLANCHE PG'!D71 -> Stéphane | T72: =S72+15 -> 15 | W72: =S72+50 -> 50 | AC72: =AB72+35 -> 35
A73: KOSTURI-BASTRIU | B73: Nazime | Q73: 1 | R73: 45933
A74: ='CROIX BLANCHE PG'!C72 -> KULIKOVA | B74: ='CROIX BLANCHE PG'!D72 -> Oléna | C74: 1 | D74: 1 | T74: =S74+15 -> 15 | W74: =S74+50 -> 50 | AC74: =AB74+35 -> 35
A75: ='CROIX BLANCHE PG'!#REF! -> #REF! | B75: ='CROIX BLANCHE PG'!#REF! -> #REF! | C75: 1 | D75: 1 | Q75: 1 | R75: 45933 | T75: =S75+15 -> 15 | W75: =S75+50 -> 50 | AC75: =AB75+35 -> 35
A76: ='CROIX BLANCHE PG'!#REF! -> #REF! | B76: ='CROIX BLANCHE PG'!#REF! -> #REF! | C76: 1 | D76: 1 | Q76: 1 | R76: 45912 | T76: =S76+15 -> 15 | W76: =S76+50 -> 50 | AC76: =AB76+35 -> 35
A77: ='CROIX BLANCHE PG'!#REF! -> #REF! | B77: ='CROIX BLANCHE PG'!#REF! -> #REF! | F77: 1 | Q77: 1 | R77: 46065 | T77: =S77+15 -> 15 | W77: =S77+50 -> 50 | AC77: =AB77+35 -> 35
A78: ='CROIX BLANCHE PG'!#REF! -> #REF! | B78: ='CROIX BLANCHE PG'!#REF! -> #REF! | T78: =S78+15 -> 15 | W78: =S78+50 -> 50 | AC78: =AB78+35 -> 35
A79: ='BRSA SORTIES'!C63 -> LIKIDI | B79: ='BRSA SORTIES'!D63 -> Quektor | I79: 1 | T79: =S79+15 -> 15 | W79: =S79+50 -> 50 | AC79: =AB79+35 -> 35
A80: ='BRSA SORTIES'!C64 -> LOUCIF | B80: ='BRSA SORTIES'!D64 -> Ines | T80: =S80+15 -> 15 | W80: =S80+50 -> 50 | AC80: =AB80+35 -> 35
A81: ='CROIX BLANCHE PG'!C73 -> MARRET | B81: ='CROIX BLANCHE PG'!D73 -> Alan | F81: 1 | H81: 1 | T81: =S81+15 -> 15 | W81: =S81+50 -> 50 | AC81: =AB81+35 -> 35
A82: MCHINDRA | B82: Yancoub | H82: 1
A83: ='BRSA SORTIES'!C66 -> MERCIER | B83: ='BRSA SORTIES'!D66 -> Florent | D83: 1 | Q83: 1 | R83: 45933 | T83: =S83+15 -> 15 | W83: =S83+50 -> 50 | AC83: =AB83+35 -> 35
A84: ='BRSA SORTIES'!C67 -> MEUNIER | B84: ='BRSA SORTIES'!D67 -> Yann | T84: =S84+15 -> 15 | W84: =S84+50 -> 50 | AC84: =AB84+35 -> 35
A85: ='CROIX BLANCHE PG'!C79 -> MOLL | B85: ='CROIX BLANCHE PG'!D79 -> Armand | G85: 1 | H85: 1 | T85: =S85+15 -> 15 | W85: =S85+50 -> 50 | AC85: =AB85+35 -> 35
A86: ='CROIX BLANCHE PG'!C80 -> MOLLA | B86: ='CROIX BLANCHE PG'!D80 -> Romina | C86: 1 | T86: =S86+15 -> 15 | W86: =S86+50 -> 50 | AC86: =AB86+35 -> 35
A87: ='BRSA SORTIES'!C73 -> MOREL | B87: ='BRSA SORTIES'!D73 -> Alexandre | T87: =S87+15 -> 15 | W87: =S87+50 -> 50 | AC87: =AB87+35 -> 35
A88: ='BRSA SORTIES'!C74 -> MOREL | B88: ='BRSA SORTIES'!D74 -> Virginie | N88: 1 | T88: =S88+15 -> 15 | W88: =S88+50 -> 50 | AC88: =AB88+35 -> 35
A89: ='CROIX BLANCHE PG'!C81 -> MOSES | B89: ='CROIX BLANCHE PG'!D81 -> Jal | T89: =S89+15 -> 15 | W89: =S89+50 -> 50 | AC89: =AB89+35 -> 35
A90: ='BRSA SORTIES'!C75 -> MOSSMAN | B90: ='BRSA SORTIES'!D75 -> Tiaré | T90: =S90+15 -> 15 | W90: =S90+50 -> 50 | AC90: =AB90+35 -> 35
A91: ='CROIX BLANCHE PG'!#REF! -> #REF! | B91: ='CROIX BLANCHE PG'!#REF! -> #REF! | T91: =S91+15 -> 15 | W91: =S91+50 -> 50 | AC91: =AB91+35 -> 35
A92: ='CROIX BLANCHE PG'!C82 -> MOUSTOIFFA | B92: ='CROIX BLANCHE PG'!D82 -> Zaïna | T92: =S92+15 -> 15 | W92: =S92+50 -> 50 | AC92: =AB92+35 -> 35
A93: ='CROIX BLANCHE PG'!C83 -> MTIMET | B93: ='CROIX BLANCHE PG'!D83 -> Ridha | C93: 1 | D93: 1 | Q93: 1 | R93: 45953 | T93: =S93+15 -> 15 | W93: =S93+50 -> 50 | AC93: =AB93+35 -> 35
A94: ='CROIX BLANCHE PG'!#REF! -> #REF! | B94: ='CROIX BLANCHE PG'!#REF! -> #REF! | C94: 1 | D94: 1 | Q94: 1 | R94: 45898 | T94: =S94+15 -> 15 | W94: =S94+50 -> 50 | AC94: =AB94+35 -> 35
A95: NAILLOD | B95: Amélie | Q95: 1 | R95: 45912
A96: NOEL | B96: Jennifer | F96: 1
A97: ='CROIX BLANCHE PG'!C87 -> OULAD AYAD | B97: ='CROIX BLANCHE PG'!D87 -> Loubna | T97: =S97+15 -> 15 | W97: =S97+50 -> 50 | AC97: =AB97+35 -> 35
A98: ='CROIX BLANCHE PG'!C88 -> OUSMANE | B98: ='CROIX BLANCHE PG'!D88 -> Tidiane | C98: 1 | F98: 1 | G98: 1 | T98: =S98+15 -> 15 | W98: =S98+50 -> 50 | AC98: =AB98+35 -> 35
A99: ='CROIX BLANCHE PG'!C89 -> PAGE | B99: ='CROIX BLANCHE PG'!D89 -> Francesca | T99: =S99+15 -> 15 | W99: =S99+50 -> 50 | AC99: =AB99+35 -> 35
A100: ='CROIX BLANCHE PG'!C90 -> PAUVIL | B100: ='CROIX BLANCHE PG'!D90 -> Pauline | F100: 1 | Q100: 1 | R100: 46080 | T100: =S100+15 -> 15 | W100: =S100+50 -> 50 | AC100: =AB100+35 -> 35
...

Sheet bilan de parcours  + démarches
A1: Exemples | C1: 5 | D1: 7 | E1: 9 | F1: 12 | G1: 15 | H1: 15 | I1: Renouvellement | J1: 46084 | K1: 1 | L1: 15 | M1: 15 | N1: 15 | O1: 15 | P1: 15 | Q1: 15 | R1: 46268 | S1: Reo FT
C3: nombres de démarches / par semaine | I3: 7 eme mois Bilan fin de parcours | L3: nombres de démarches / par semaine | R3: 14éme mois Bilan définitif
A4: nom | B4: prenom | C4: 1er mois | D4: 2e mois | E4: 3e mois | F4: 4e mois | G4: 5e mois | H4: 6e mois | I4: demande | J4: Date | K4: Renouvellement | L4: 8e mois | M4: 9e mois | N4: 10e mois | O4: 11e mois | P4: 12e mois | Q4: 13e mois | R4: Date | S4: Préco Réo
A5: ='CROIX BLANCHE PG'!#REF! -> #REF! | B5: ='CROIX BLANCHE PG'!#REF! -> #REF!
A6: ='CROIX BLANCHE PG'!C9 -> AHMADI | B6: ='CROIX BLANCHE PG'!D9 -> Diba | C6: 40 | D6: 40 | E6: 40 | I6: Renouvellement | J6: 46114 | K6: 1
A7: ='CROIX BLANCHE PG'!#REF! -> #REF! | B7: ='CROIX BLANCHE PG'!#REF! -> #REF!
A8: ALVES | B8: Merryl
A9: ='CROIX BLANCHE PG'!C13 -> AMARI | B9: ='CROIX BLANCHE PG'!D13 -> Yamina | I9: Renouvellement | J9: 46134 | K9: 1
A10: ='CROIX BLANCHE PG'!C14 -> ARIFI | B10: ='CROIX BLANCHE PG'!D14 -> Sabrina
A11: ='CROIX BLANCHE PG'!C16 -> ATHOUMANI | B11: ='CROIX BLANCHE PG'!D16 -> Marie | I11: Renouvellement | J11: 46115 | K11: 1
A12: ='CROIX BLANCHE PG'!C19 -> BACAR | B12: ='CROIX BLANCHE PG'!D19 -> Mariata | C12: 60 | D12: 60 | E12: 60 | F12: 60 | G12: 60 | H12: 60 | I12: Renouvellement | J12: 46143 | K12: 1
A13: ='CROIX BLANCHE PG'!C20 -> BAHAR | B13: ='CROIX BLANCHE PG'!D20 -> Laura
A14: ='BRSA SORTIES'!C15 -> BAITICHE | B14: ='BRSA SORTIES'!D15 -> Karima | C14: 10 | D14: 10 | E14: 10 | I14: Renouvellement | J14: 46055 | K14: 1
A15: ='CROIX BLANCHE PG'!#REF! -> #REF! | B15: ='CROIX BLANCHE PG'!#REF! -> #REF!
A16: BASSUS | B16: Jason
A17: ='CROIX BLANCHE PG'!C25 -> BEKELE | B17: ='CROIX BLANCHE PG'!D25 -> Eteferahu
A18: ='CROIX BLANCHE PG'!C26 -> BELFASSI | B18: ='CROIX BLANCHE PG'!D26 -> Maria Dolores | C18: 20 | D18: 20
A19: ='CROIX BLANCHE PG'!C27 -> BENAISSA | B19: ='CROIX BLANCHE PG'!D27 -> Radia | C19: 60 | D19: 60 | I19: Renouvellement | J19: 46163 | K19: 1
A20: ='CROIX BLANCHE PG'!C29 -> BEN EL OUALI | B20: ='CROIX BLANCHE PG'!D29 -> Anouar
A21: BENMELLOUK BENMESSA
A22: ='CROIX BLANCHE PG'!C31 -> BENOIT | B22: ='CROIX BLANCHE PG'!D31 -> Xavier
A23: ='CROIX BLANCHE PG'!C32 -> BENZEKHROUFA | B23: ='CROIX BLANCHE PG'!D32 -> Abdelghani
A24: BERGET
A25: ='CROIX BLANCHE PG'!C34 -> BERTHILLOT | B25: ='CROIX BLANCHE PG'!D34 -> Léa
A26: ='BRSA SORTIES'!C19 -> BLANC | B26: ='BRSA SORTIES'!D19 -> Mélissa | I26: Renouvellement | J26: 46052 | K26: 1
A27: ='BRSA SORTIES'!C20 -> BONNET | B27: ='BRSA SORTIES'!D20 -> Cédric | C27: 10 | D27: 10 | E27: 10 | I27: Renouvellement | J27: 46044 | K27: 1
A28: ='BRSA SORTIES'!C22 -> BOUILLOUX | B28: ='BRSA SORTIES'!D22 -> Nikolas
A29: ='CROIX BLANCHE PG'!#REF! -> #REF! | B29: ='CROIX BLANCHE PG'!#REF! -> #REF!
A30: ='CROIX BLANCHE PG'!#REF! -> #REF! | B30: ='CROIX BLANCHE PG'!#REF! -> #REF!
A31: BOYRAZ
A32: ='BRSA SORTIES'!C27 -> BRECANI | B32: ='BRSA SORTIES'!D27 -> Arjana | C32: 60 | D32: 60 | E32: 60 | I32: Renouvellement | J32: 46053 | K32: 1
A33: ='BRSA SORTIES'!C29 -> BRUNET | B33: ='BRSA SORTIES'!D29 -> Carole | I33: Renouvellement | J33: 46083
A34: ='CROIX BLANCHE PG'!C42 -> BRUZEAU | B34: ='CROIX BLANCHE PG'!D42 -> Laura | I34: Tripartite | J34: 46112
A35: ='CROIX BLANCHE PG'!C43 -> BUATTIER | B35: ='CROIX BLANCHE PG'!D43 -> Christelle
A36: ='CROIX BLANCHE PG'!#REF! -> #REF! | B36: ='CROIX BLANCHE PG'!#REF! -> #REF!
A37: ='CROIX BLANCHE PG'!#REF! -> #REF! | B37: ='CROIX BLANCHE PG'!#REF! -> #REF!
A38: ='CROIX BLANCHE PG'!C45 -> CHARNAY | B38: ='CROIX BLANCHE PG'!D45 -> Cindy
A39: ='CROIX BLANCHE PG'!C46 -> CHAVE | B39: ='CROIX BLANCHE PG'!D46 -> Baptiste | C39: 60 | D39: 60 | E39: 60 | F39: 60 | G39: 60 | H39: 60 | I39: Renouvellement | J39: 46114 | K39: 1
A40: ='CROIX BLANCHE PG'!#REF! -> #REF! | B40: ='CROIX BLANCHE PG'!#REF! -> #REF! | C40: 60 | D40: 60 | E40: 60 | F40: 60 | G40: 60 | H40: 60 | I40: Renouvellement | J40: 46100 | K40: 1
A41: ='BRSA SORTIES'!C40 -> DAOUD | B41: ='BRSA SORTIES'!D40 -> Boina | C41: 20 | D41: 20 | E41: 20 | F41: 20 | G41: 20 | H41: 20 | I41: Renouvellement | J41: 46106 | K41: 1
A42: ='CROIX BLANCHE PG'!C48 -> DA SILVA GONCALVES | B42: ='CROIX BLANCHE PG'!D48 -> Samuel | C42: 60 | D42: 60 | E42: 60 | F42: 60 | G42: 60 | H42: 60 | I42: Renouvellement | J42: 46105 | K42: 1
A43: ='CROIX BLANCHE PG'!C49 -> DBIJA | B43: ='CROIX BLANCHE PG'!D49 -> Hafida
A44: ='CROIX BLANCHE PG'!C50 -> DECAILLON | B44: ='CROIX BLANCHE PG'!D50 -> Candide | C44: 60 | D44: 60 | E44: 60 | F44: 60 | I44: Renouvellement | J44: 46090 | K44: 1
A45: ='CROIX BLANCHE PG'!C55 -> EL MOUSTAOUI | B45: ='CROIX BLANCHE PG'!D55 -> Sadik
A46: ='CROIX BLANCHE PG'!#REF! -> #REF! | B46: ='CROIX BLANCHE PG'!#REF! -> #REF!
A47: ='CROIX BLANCHE PG'!C56 -> FETET | B47: ='CROIX BLANCHE PG'!D56 -> Jennifer | C47: 60 | D47: 60 | E47: 60 | F47: 60 | G47: 60 | H47: 60 | I47: Renouvellement | J47: 46092 | K47: 1
A48: ='BRSA SORTIES'!C50 -> FETET | B48: ='BRSA SORTIES'!D50 -> Laura | C48: 60 | D48: 60 | E48: 60 | F48: 60 | G48: 60 | H48: 60 | I48: Renouvellement | J48: 46047 | K48: 1
A49: ='CROIX BLANCHE PG'!C59 -> GOBERT | B49: ='CROIX BLANCHE PG'!D59 -> Edwige | I49: Renouvellement | J49: 46108 | K49: 1
A50: ='CROIX BLANCHE PG'!#REF! -> #REF! | B50: ='CROIX BLANCHE PG'!#REF! -> #REF! | I50: Renouvellement | J50: 46054 | K50: 1
A51: ='CROIX BLANCHE PG'!C60 -> HADZI-ALIJA | B51: ='CROIX BLANCHE PG'!D60 -> Erdan
A52: ='CROIX BLANCHE PG'!C62 -> HAMMOUMI | B52: ='CROIX BLANCHE PG'!D62 -> Mohammed
A53: ='CROIX BLANCHE PG'!C64 -> HASSANI | B53: ='CROIX BLANCHE PG'!D64 -> Koulthoumi
A54: ='CROIX BLANCHE PG'!C65 -> HOUICHI | B54: ='CROIX BLANCHE PG'!D65 -> Hikmet | C54: 60 | D54: 60 | E54: 60 | F54: 60 | G54: 60 | H54: 60 | I54: Renouvellement | J54: 46105 | K54: 1
A55: IBADIOUNE
A56: IMMEDIATO | B56: Eva
A57: ='CROIX BLANCHE PG'!C68 -> KALINDA | B57: ='CROIX BLANCHE PG'!D68 -> Léopold | C57: 60 | D57: 60
A58: ='CROIX BLANCHE PG'!C69 -> KARADAVUT | B58: ='CROIX BLANCHE PG'!D69 -> Pembe
A59: ='CROIX BLANCHE PG'!C70 -> KASEMI | B59: ='CROIX BLANCHE PG'!D70 -> Elsaïda
A60: ='CROIX BLANCHE PG'!#REF! -> #REF! | B60: ='CROIX BLANCHE PG'!#REF! -> #REF!
A61: ='CROIX BLANCHE PG'!C71 -> KIM | B61: ='CROIX BLANCHE PG'!D71 -> Stéphane
A62: ='CROIX BLANCHE PG'!C72 -> KULIKOVA | B62: ='CROIX BLANCHE PG'!D72 -> Oléna
A63: ='CROIX BLANCHE PG'!#REF! -> #REF! | B63: ='CROIX BLANCHE PG'!#REF! -> #REF!
A64: ='BRSA SORTIES'!C63 -> LIKIDI | B64: ='BRSA SORTIES'!D63 -> Quektor
A65: ='BRSA SORTIES'!C64 -> LOUCIF | B65: ='BRSA SORTIES'!D64 -> Ines | C65: 60 | D65: 60 | E65: 60 | F65: 60 | G65: 60 | H65: 60 | I65: Renouvellement | J65: 46051 | K65: 1
A66: ='CROIX BLANCHE PG'!C73 -> MARRET | B66: ='CROIX BLANCHE PG'!D73 -> Alan
A67: MCHINDRA | B67: Yancoub | I67: Renouvellement | J67: 46142 | K67: 1
A68: ='BRSA SORTIES'!C66 -> MERCIER | B68: ='BRSA SORTIES'!D66 -> Florent | I68: Renouvellement | J68: 46052 | K68: 1
A69: ='BRSA SORTIES'!C67 -> MEUNIER | B69: ='BRSA SORTIES'!D67 -> Yann | C69: 20 | D69: 20 | E69: 20 | F69: 20 | G69: 20 | I69: Renouvellement | J69: 46058 | K69: 1
A70: ='CROIX BLANCHE PG'!C79 -> MOLL | B70: ='CROIX BLANCHE PG'!D79 -> Armand
A71: ='CROIX BLANCHE PG'!C80 -> MOLLA | B71: ='CROIX BLANCHE PG'!D80 -> Romina | C71: 20 | D71: 20 | I71: Renouvellement | J71: 46197 | K71: 1
A72: MONIN
A73: ='BRSA SORTIES'!C73 -> MOREL | B73: ='BRSA SORTIES'!D73 -> Alexandre | C73: 60 | D73: 60 | E73: 60 | F73: 60 | G73: 60 | H73: 60 | I73: Renouvellement | J73: 46051 | K73: 1
A74: ='BRSA SORTIES'!C74 -> MOREL | B74: ='BRSA SORTIES'!D74 -> Virginie | C74: 60 | D74: 60 | E74: 60 | F74: 60 | I74: Renouvellement | J74: 46060 | K74: 1
A75: ='CROIX BLANCHE PG'!C81 -> MOSES | B75: ='CROIX BLANCHE PG'!D81 -> Jal | C75: 60
A76: ='BRSA SORTIES'!C75 -> MOSSMAN | B76: ='BRSA SORTIES'!D75 -> Tiaré | C76: 20 | I76: Renouvellement | J76: 46198 | K76: 1
A77: ='CROIX BLANCHE PG'!#REF! -> #REF! | B77: ='CROIX BLANCHE PG'!#REF! -> #REF! | C77: 20 | D77: 20 | E77: 20 | F77: 20 | G77: 20 | H77: 20 | I77: Renouvellement | J77: 46098 | K77: 1
A78: ='CROIX BLANCHE PG'!C82 -> MOUSTOIFFA | B78: ='CROIX BLANCHE PG'!D82 -> Zaïna | I78: Renouvellement | J78: 46193 | K78: 1
A79: ='CROIX BLANCHE PG'!C83 -> MTIMET | B79: ='CROIX BLANCHE PG'!D83 -> Ridha
A80: NOEL
A81: ='CROIX BLANCHE PG'!C87 -> OULAD AYAD | B81: ='CROIX BLANCHE PG'!D87 -> Loubna
A82: ='CROIX BLANCHE PG'!C88 -> OUSMANE | B82: ='CROIX BLANCHE PG'!D88 -> Tidiane
A83: ='CROIX BLANCHE PG'!C89 -> PAGE | B83: ='CROIX BLANCHE PG'!D89 -> Francesca | C83: 60 | D83: 60 | E83: 60 | I83: Renouvellement | J83: 46143 | K83: 1
A84: ='CROIX BLANCHE PG'!C90 -> PAUVIL | B84: ='CROIX BLANCHE PG'!D90 -> Pauline | I84: Renouvellement | J84: 46112
A85: ='BRSA SORTIES'!C87 -> PEKDURU | B85: ='BRSA SORTIES'!D87 -> Pembe | I85: REO SOCIALE
A86: ='CROIX BLANCHE PG'!C95 -> PIERRE-LOUIS | B86: ='CROIX BLANCHE PG'!D95 -> Stephen
A87: ='CROIX BLANCHE PG'!#REF! -> #REF! | B87: ='CROIX BLANCHE PG'!#REF! -> #REF! | C87: 20
A88: ='CROIX BLANCHE PG'!C96 -> PINTO | B88: ='CROIX BLANCHE PG'!D96 -> Jason | C88: 60 | D88: 60 | E88: 60 | I88: Renouvellement | J88: 46134 | K88: 1
A89: POCHEBONNE | B89: Prescillia
A90: ='CROIX BLANCHE PG'!C99 -> PUZIN | B90: ='CROIX BLANCHE PG'!D99 -> Jacky
A91: RAMOUL
A92: ='CROIX BLANCHE PG'!C101 -> RHAZI | B92: ='CROIX BLANCHE PG'!D101 -> Abdelhakim | I92: Renouvellement | J92: 46039 | K92: 1 | R92: 46219 | S92: Fin bilan parcours
A93: ='CROIX BLANCHE PG'!#REF! -> #REF! | B93: ='CROIX BLANCHE PG'!#REF! -> #REF! | C93: 20 | D93: 20 | E93: 20 | F93: 20 | G93: 20 | H93: 20 | I93: Renouvellement | J93: 46076 | K93: 1
A94: ='CROIX BLANCHE PG'!C102 -> ROIDA | B94: ='CROIX BLANCHE PG'!D102 -> Hamid
A95: ='BRSA SORTIES'!C96 -> ROUSSEAUX | B95: ='BRSA SORTIES'!D96 -> Frédéric | C95: 20 | D95: 20 | E95: 20 | I95: TRIPARTITE | J95: 46098
A96: ='CROIX BLANCHE PG'!C103 -> RUSITI | B96: ='CROIX BLANCHE PG'!D103 -> Silvano
A97: ='BRSA SORTIES'!C97 -> SAEED | B97: ='BRSA SORTIES'!D97 -> Sumaia | C97: 60 | D97: 60 | E97: 60 | I97: Renouvellement | J97: 46060 | K97: 1
A98: ='BRSA SORTIES'!C99 -> SATTA | B98: ='BRSA SORTIES'!D99 -> Saadia | C98: 30 | D98: 30 | E98: 30 | H98: Radiée SDP TS | I98: Renouvellement
A99: ='BRSA SORTIES'!C100 -> SAVOVA | B99: ='BRSA SORTIES'!D100 -> Snejana | C99: 20 | D99: 20 | E99: 20 | F99: 20 | I99: Renouvellement | J99: 46058 | K99: 1
A100: ='CROIX BLANCHE PG'!C104 -> SAWAS | B100: ='CROIX BLANCHE PG'!D104 -> Fatina
A101: ='BRSA SORTIES'!C101 -> SAYAH | B101: ='BRSA SORTIES'!D101 -> Fatma | C101: 60 | D101: 60 | E101: 60 | F101: 60 | G101: 60 | I101: Renouvellement | J101: 46061 | K101: 1
...

Sheet Tableau croisé NE PAS TOUCHER 
A3: Sanction et Absence | E3: Bilan de parcours + démarches
A4: Nombre de 1ER RDV | B4: 32 | E4: Somme de 1er mois | F4: 1540
A5: Somme de 2EME | B5: 20 | E5: Somme de 2e mois | F5: 1390
A6: Nombre de 1er mois | E6: Somme de 3e mois | F6: 1090
A7: Nombre de 2e mois | E7: Somme de 4e mois | F7: 500
A8: Somme de 3e mois | E8: Somme de 5e mois | F8: 420
A9: Somme de 4e mois | E9: Somme de 6e mois | F9: 160
A10: Somme de 5e mois | E10: Nombre de demande
A11: Nombre de 6e mois | E11: Somme de Renouvellement
A12: Nombre de 7e mois | E12: Somme de 8e mois
A13: Nombre de 8e mois | E13: Somme de 9e mois
A14: Nombre de 9e mois | E14: Somme de 10e mois
A15: Nombre de 10e mois | E15: Somme de 11e mois
A16: Nombre de 11e mois | E16: Somme de 12e mois
A17: Nombre de 12e mois | E17: Somme de Préco Réo
A18: Somme de date demande étude de situation (Mail CDS)
A19: Somme de Dde etude de situation.
A21: Valeurs | C21: SEXE | D21: Nombre de H/F | E21: SORTIES | F21: Nombre de Motif de sortie | G21: Nombre de MOTIF de la REO
A22: Moyenne de âge | B22: 40.956044 | C22: Madame | D22: 114 | E22: Déménagement | F22: 3
A23: Nombre de C.E SIGNE | B23: 126 | C23: Monsieur | D23: 71 | E23: (vide) | F23: 3
A24: Nombre de BILAN PARCOURS (7eme mois) | B24: 55 | C24: (vide) | E24: Fin DD | F24: 8 | G24: 2
A25: Somme de PMSMP (1 = oui) | B25: 1 | C25: Total général | D25: 185 | E25: FT acc pro | F25: 2 | G25: 2
A26: Nombre de H/F | B26: 185 | E26: (vide) | F26: 6
A27: Nombre de Saisie FSE | B27: 123 | E27: Positive | F27: 10 | G27: 7
A28: Nombre de AIDE FINANCIERE | E28: BGE | F28: 3 | G28: 3
E29: FT acc pro | F29: 4 | G29: 4
E30: (vide) | F30: 3
A31: SORTIES POSITIVES | B31: Nombre de types | E31: Renonciation RSA | F31: 1
A32: CDI >ou= 24h | B32: 3 | E32: (vide) | F32: 1
A33: Créa | B33: 5 | E33: Réorientation | F33: 42 | G33: 42
A34: (vide) | E34: BGE | F34: 5 | G34: 5
A35: SIAE (FT) | B35: 3 | E35: FT acc pro | F35: 5 | G35: 5
A36: France Travail | B36: 1 | E36: Social freins+ | F36: 24 | G36: 24
A37: Stagiaire de la formation | B37: 1 | E37: Sociale retraite | F37: 4 | G37: 4
A38: Total général | B38: 13 | E38: Sociale maternité | F38: 4 | G38: 4
E39: (vide)
E40: (vide)
E41: Radié suite CLI | F41: 12
E42: (vide) | F42: 12
E43: Total général | F43: 76 | G43: 51

Sheet liste deroulante
A1: Années après le Bac | B1: Titre du diplôme | C1: Niveau de diplôme | F1: Réorientation | H1: Motifs Sorties | J1: Sorties
B2: Aucun diplôme | F2: Sociale AAH | G2: Emploi | H2: Positive | J2: CDI >ou= 24h
A3: - | B3: CAP, BEP | C3: 3 (anciennement V) | E3: H | F3: Sociale retraite | G3: Formation | H3: Réorientation | J3: CDD +6mois >ou=254h
A4: Bac | B4: Baccalauréat | C4: 4 (anciennement IV) | E4: F | F4: Sociale maternité | G4: Créa entreprise | H4: Déménagement | J4: Créa
A5: Bac+2 | B5: DEUG, BTS, DUT, DEUST | C5: 5 (anciennement III) | F5: Social freins+ | G5: France Travail | H5: Fin DD | J5: Interim>ou= à 970h cumulées / an
A6: Bac+3 | B6: Licence, licence professionnelle | C6: 6 (anciennement II) | F6: Arret mal longue durée | H6: Décès | J6: Stagiaire de la formation
A7: Bac+4 | B7: Maîtrise, master 1 | C7: 6 (anciennement II) | F7: BGE | H7: Renonciation RSA | J7: SIAE (FT)
A8: Bac+5 | B8: Master, diplôme d'études approfondies, diplôme d'études supérieures spécialisées, diplôme d'ingénieur | C8: 7 (anciennement I) | F8: MSA | H8: Incarcération
A9: Bac+8 | B9: Doctorat, habilitation à diriger des recherches | C9: 8 (anciennement I) | F9: FT acc pro | H9: Mauvaise orientation
F10: FT acco glo | H10: Fin bilan parcours
D11: CLI | H11: Radié suite CLI
B12: freins | D12: 1
B13: mobilité | D13: 0
B14: garde enfants
E15: OUI
A16: CDS | B16: Oyonnax | E16: NON | G16: Resultat bilan parcours
B17: Nantua | G17: Réo FT | H17: Reo FT
B18: Belley | G18: Renouvellement | H18: Réo sociale
B19: Valserhone | G19: Tripartite
B20: Pays de Gex | G20: BGE
B21: Croix Blanche
B22: Pierre Goujon
B23: Montrevel
B24: Pont de Vaux
B25: St Didier sur Chalaronne
B26: Trevoux
B27: Chatillon sur Chalaronne
B28: Amberieu
B29: Lagnieu
B30: Miribel

Sheet CODIFICATION ACTIVITE
A3: Besoin
A4: Ordre | B4: Code | C4: Libellé | D4: Libellé | E4: Libellé | F4: Volume horaire Hedbomadaire
A5: 1 | B5: P01 | C5: Choisir un métier | D5: Identification de ses points forts et de ses compétences | E5: Identifier ses points forts et ses compétences | F5: 3
D6: Information sur un métier ou un secteur d'activité | E6: S'informer sur un métier ou un secteur d'activité | F6: 3
D7: Observation en entreprise | E7: Réaliser une observation en entreprise | F7: 3
D8: Enquête métier afin de mieux connaître un métier | E8: Réaliser une enquête métier | F8: 3
D9: Participation à un salon ou un forum pour s'informer sur un métier | E9: Participer à un salon ou un forum pour s'informer sur un métier | F9: 3
A10: 2 | B10: P02 | C10: Se former | D10: Information sur un projet de formation ou de Validation des acquis de l'expérience | E10: S'informer sur un projet de formation ou de validation des acquis de l'expérience | F10: 3
D11: Montage d'un dossier d’inscription à une formation | E11: Monter son dossier de formation | F11: 3
D12: Participation à une formation | E12: Participer à une formation | F12: 35
D13: Participation à un salon ou un forum formation | E13: Participer à un salon ou un forum formation | F13: 3
D14: Initiation à l'informatique ou à Internet | E14: S'initier à l'informatique ou à Internet | F14: 3
D15: Participation à un dispositif d'insertion | E15: Participer à un dispositif d'insertion | F15: 35
A16: 3 | B16: P03 | C16: Préparer sa candidature | D16: Réalisation d'une démarche de VAE | E16: Réaliser une démarche de VAE | F16: 3
D17: Préparation de ses candidatures (CV, lettre de motivation, book) | E17: Réaliser ou mettre à jour son CV sa lettre de motivation ou son portfolio | F17: 3
E18: Développer son réseau | F18: 3
E19: S'inscrire ou compléter son profil sur un réseau professionnel | F19: 3
E20: Réaliser des activités de bénévolat | F20: 5
E21: Organiser ses démarches de recherche d’emploi | F21: 3
E22: Compléter ou publier son profil de compétence | F22: 3
A23: 4 | C23: Trouver un emploi | D23: Recherche d'offres d'emploi ou d'entreprises | E23: Rechercher des offres d'emploi ou d'entreprises | F23: 3
D24: Participation à un salon ou un forum pour rechercher des offres | E24: Participer à un salon ou un forum pour rechercher des offres d'emploi | F24: 3
D25: Réponse à des offres d'emploi | E25: Répondre à des offres d'emploi | F25: 3
D26: Candidatures spontanées | E26: Effectuer des candidatures spontanées | F26: 3
D27: Réalisation du suivi de ses candidatures et relance des recruteurs | E27: Réaliser le suivi de ses candidatures et relancer des recruteurs | F27: 3
D28: Préparation des entretiens d'embauche | E28: Préparer un entretien d'embauche | F28: 3
D29: Réalisation d'entretiens d'embauche | E29: Réaliser un entretien d'embauche | F29: 3
D30: Passation de tests de recrutement (concours, casting…) | E30: Passer des tests de recrutement (concours, casting…) | F30: 3
D31: Réalisation d'une mise en situation professionnelle dans une entreprise | E31: Réaliser une mise en situation professionnelle dans une entreprise | F31: 35
D32: Recherche de missions de service civique | E32: Rechercher des missions de service civique | F32: 3
E33: S'inscrire sur une plateforme de recrutement (agence d'intérim, cabinet de recrutement, site spécialisé…) | F33: 3
A34: 5 | B34: P05 | C34: Ma création et reprise d'entreprise | D34: Recherches pour créer ou reprendre une entreprise | E34: Effectuer des recherches pour créer ou reprendre une entreprise | F34: 3
D35: Réalisation d'une étude de marché auprès de prospects/clients /fournisseurs | E35: Réaliser une étude de marché auprès de prospects/clients /fournisseurs | F35: 3
D36: Participation à un salon ou forum pour s'informer sur la création entreprise | E36: Participer à un salon ou forum pour s'informer sur la création d'entreprise | F36: 3
D37: Réalisation d'un business plan afin de préparer la création de son entreprise | E37: Réaliser un business plan afin de préparer la création de son entreprise | F37: 3
D38: Prise de RDV avec des organismes financiers | E38: Prendre rendez-vous avec des organismes financiers | F38: 3
D39: Réalisation de démarches juridiques de création d'entreprise | E39: Réaliser des démarches juridiques de création d'entreprise | F39: 3
D40: Réalisation d'actions de communication pour faire connaitre son entreprise | E40: Réaliser des actions de communication pour faire connaître son entreprise | F40: 3
D41: Prospection pour développer sa clientèle | E41: Prospecter pour développer sa clientèle | F41: 3
D42: Développement de nouveaux partenariats | E42: Développer de nouveaux partenariats | F42: 3
D43: Mise en œuvre d'actions de fidélisation de ses clients ou utilisateurs | E43: Mettre en œuvre des actions de fidélisation de ses clients ou utilisateurs | F43: 3
D44: Organisation de son activité de dirigeant et de gestion de son entreprise | E44: Organiser son activité de dirigeant et la gestion de son entreprise | F44: 3
D45: Diversification de ses activités en proposant de nouveaux services ou produits | E45: Développer son entreprise en diversifiant ses activités | F45: 3
D46: Développement de son entreprise en procédant à des recrutements | E46: Développer son entreprise en procédant à des recrutements | F46: 3
D47: Réalisation d'autres actions pour développer son entreprise | E47: Réaliser d'autres actions pour développer son entreprise | F47: 3
A48: 6 | B48: P06 | C48: Entretiens avec un conseiller | D48: Réaliser un entretien avec un conseiller | E48: Réaliser un entretien avec un conseiller | F48: 1
A49: 8 | B49: P08 | C49: Développer sa mobilité | E49: Réaliser une démarche pour accéder aux transports en commun | F49: 1
E50: Mobiliser le réseau de transports à la demande | F50: 3
E51: Acquérir un moyen de locomotion | F51: 2
E52: Mobiliser un garage solidaire | F52: 3
E53: Constituer un dossier de financement pour l'achat d'un véhicule | F53: 5
E54: Louer un moyen de locomotion | F54: 1
E55: Participer à un rendez-vous avec un partenaire mobilité | F55: 1
E56: Constituer un dossier d'aide à la mobilité | F56: 3
E57: Résoudre ses problématiques de mobilité psychologique | F57: 3
E58: Entretenir ou réparer son véhicule | F58: 3
E59: Mettre en place une solution de covoiturage | F59: 3
E60: S'inscrire en auto-école | F60: 1
E61: Participer à un cours de code/conduite | F61: 1
... E64: Récupérer son permis de conduire | F64: 1
A65: 9 | B65: P09 | C65: Accéder au numérique et en maîtriser les fondamentaux | E65: Acquérir un équipement informatique | F65: 3
E66: Accéder à une connexion Internet | F66: 3
E67: Réaliser le test PIX | F67: 1
E68: Participer à un rendez-vous avec un partenaire "numérique" | F68: 1
E69: Participer à un cours d'initiation à l'informatique/internet | F69: 5
E70: S'informer/se former à la confidentialité sur internet (RGPD…) | F70: 3
E71: Solliciter l'écrivain public numérique | F71: 2
E72: Participer à une formation numérique (PIX) | F72: 7
D73: Evaluation des compétences numériques | E73: Évaluer ses compétences numériques | F73: 1
A74: 10 | B74: P10 | C74: Faire face à des difficultés administratives et juridiques | E74: S'informer sur les voies de recours suite à une discrimination | F74: 3
E75: Réaliser des démarches administratives liées à l'état civil | F75: 3
E76: Participer à un rendez-vous avec un partenaire "administratif" | F76: 1
E77: Réaliser une demande de procédure judiciaire | F77: 2
E78: Participer à un rendez-vous avec un partenaire "juridique" | F78: 1
E79: Faire une demande d'aide juridictionnelle, conseil juridique | F79: 3
E80: Réaliser une déclaration de situation (impôt, CAF…) | F80: 1
E81: Réaliser une demande à la préfecture | F81: 4
E82: Classer ses documents administratifs | F82: 2
E83: Réaliser une demande de prestation ou droit (CAF, MSA…) | F83: 3
E84: Accéder aux informations et aides disponibles pour les aidants | F84: 3
E85: S'actualiser et rester inscrit à France Travail | F85: 1
A86: 11 | B86: P11 | C86: Faire face à des difficultés de logement | E86: Participer à un rendez-vous avec un partenaire logement | F86: 1
E87: Réaliser un diagnostic de précarité énergétique | F87: 5
E88: Réaliser une demande d'aide d'amélioration de l'habitat | F88: 3
E89: Monter un dossier de demande d'aide au logement (DALO, DAHO…) | F89: 3
E90: Appeler le 115 | F90: 2
E91: Réaliser une demande de logement social | F91: 3
E92: Réaliser une visite de logement | F92: 3
E93: Réaliser une demande de domiciliation auprès d'un CCAS | F93: 3
E94: Réaliser des démarches dans le cadre du maintien dans le logement | F94: 3
E95: Effectuer des démarches dans le cadre d'une procédure d'expulsion | F95: 3
A96: 12 | B96: P12 | C96: Faire face à des difficultés financières | E96: Réaliser une demande de plan de surendettement | F96: 5
E97: Faire valoir ses droits à une pension (retraite, réversion...) | F97: 2
E98: Réaliser une demande d'aide alimentaire | F98: 1
E99: Participer à un rendez-vous avec un partenaire "Budget/Finance" | F99: 1
E100: Ouvrir un compte bancaire | F100: 3
E101: Réaliser une demande de micro-crédit social | F101: 2
E102: Réaliser une demande de carte solidaire (SNCF, Pass Solidaire) | F102: 3
E103: Monter un dossier financier (microcrédit, FIP, FSL, FAJ...) | F103: 8
E104: Se rendre dans un point conseil budget | F104: 3
...

Sheet Feuil1
A1: Nom | B1: Prénom | C1: 1er mois | D1: 2e mois | E1: 3e mois | F1: 4e mois | G1: 5e mois | H1: 6e mois | I1: 7e mois | J1: 8e mois | K1: 9e mois | L1: 10e mois | M1: 11e mois | N1: 12e mois | O1: Dde etude de situation. | P1: date de la demande | Q1: Date courrier CDS (voir extraction transmise) | R1: Délai 15 jours pour contact | S1: Contact BRSA - 15 jours | T1: Mail INFO CDS | U1: Délai de 35 jours pour reprendre contact | V1: le BRSA s'est manifesté ? | W1: Mail d'info au CDS manifestation ou non dans les 35 jours | X1: Date CLI si le BRSA ne s'est pas manifesté au bout des 35 jours | Y1: date demande étude de situation (Mail CDS) | Z1: DATE courrier CDS | AA1: 35j pour reprendre contact date butoire | AB1: DATE CLI
A2: AHAMADA | B2: Fatima | E2: 1 | F2: 1 | O2: 1 | P2: 46052 | Q2: 46057 | R2: 46072 | S2: 0 | T2: 1 | U2: 46107 | Y2: 1 | Z2: 46122 | AA2: 46157
A3: XHAFAJ | B3: IGBALLE | R3: 15 | U3: 50 | AA3: 35
A4: AKKAOUI | B4: Badr | O4: 1 | P4: 46049 | Q4: 46054 | R4: 46069 | U4: 46104 | AA4: 35
A5: ALI ABDULLEH | B5: Maymoun | R5: 15 | U5: 50 | AA5: 35
A6: AMIRAT | B6: Saliha | R6: 15 | U6: 50 | AA6: 35
A7: BA | B7: N Dela | F7: 1 | G7: 1 | O7: 1 | P7: 46049 | Q7: 46054 | R7: 46069 | S7: 1 | T7: 1 | U7: 46104 | AA7: 35
A8: BAKHTOKHIL | B8: Hayatullah | E8: 5 | R8: 15 | U8: 50 | AA8: 35
A9: BAUDHUIN | B9: Claire | G9: 5 | R9: 15 | U9: 50 | AA9: 35
A10: BENOIT GONIN | B10: Lucas | R10: 15 | U10: 50 | AA10: 35
A11: BOUJLOUD | B11: Zeneb | R11: 15 | U11: 50 | AA11: 35
A12: CANI | B12: Rilinda | R12: 15 | U12: 50 | AA12: 35
A13: CELEBI | B13: Bekir | G13: 5 | R13: 15 | U13: 50 | AA13: 35
A14: CERVANTES | B14: Sabrina | R14: 15 | U14: 50 | AA14: 35
A15: CHANAL-MOGUET | B15: Virginie | D15: 5 | R15: 15 | U15: 50 | AA15: 35
A16: CHAUME | B16: Stephanie | R16: 15 | U16: 50 | AA16: 35
A17: DAMIRON | B17: Arthur | O17: 1 | P17: 46049 | Q17: 46054 | R17: 46069 | S17: 1 | T17: 1 | U17: 46104 | AA17: 35
A18: EL ARKOUBI | B18: Touria | R18: 15 | U18: 50 | AA18: 35
A19: EL BAHMANI | B19: Naima | R19: 15 | U19: 50 | AA19: 35
A20: ERASLAN | B20: Eren | O20: 1 | P20: 46049 | Q20: 46054 | R20: 46069 | U20: 46104 | AA20: 35
A21: GILBERT | B21: Stéphanie | R21: 15 | U21: 50 | AA21: 35
A22: HIDA | B22: Soumaya | O22: 1 | P22: 46049 | Q22: 46054 | R22: 46069 | U22: 46104 | AA22: 35
A23: HUMBERT | B23: Jolan | O23: 1 | P23: 46049 | Q23: 46054 | R23: 46069 | U23: 46104 | AA23: 35
A24: KABA | B24: M'balou | R24: 15 | U24: 50 | AA24: 35
A25: KACEM | B25: Houaria | R25: 15 | U25: 50 | AA25: 35
A26: KASEMRATH | B26: Melanie | R26: 15 | U26: 50 | AA26: 35
A27: LAHJAR | B27: Nadia | R27: 15 | U27: 50 | AA27: 35
A28: LAHU | B28: Fabien | R28: 15 | U28: 50 | AA28: 35
A29: LAZRAK | B29: Rajae | R29: 15 | U29: 50 | AA29: 35
A30: MALKI | B30: Hanane | R30: 15 | U30: 50 | AA30: 35
A31: MITKOVA | B31: Marusya | O31: 1 | P31: 46049 | Q31: 46054 | R31: 46069 | S31: 1 | T31: 1 | U31: 46104 | AA31: 35
A32: M'MADI | B32: Zaidine | R32: 15 | U32: 50 | AA32: 35
A33: PATEL | B33: Virginie | R33: 15 | U33: 50 | AA33: 35
A34: ROBERT | B34: Olivier | R34: 15 | U34: 50 | AA34: 35
A35: SIOUDA | B35: Tourkia | R35: 15 | U35: 50 | AA35: 35
A36: SOEUM | B36: Justine | R36: 15 | U36: 50 | AA36: 35
A37: SOUCANE | B37: Pascale | R37: 15 | U37: 50 | AA37: 35
A38: SYED RASHAD | B38: Ayesha | R38: 15 | U38: 50 | AA38: 35
A39: YILMAZ | B39: Talip | R39: 15 | U39: 50 | AA39: 35
A40: AIT YOUSSEF | B40: Maryam | R40: 15 | U40: 50 | AA40: 35
A41: BAGHDADI | B41: Edith | R41: 15 | U41: 50 | AA41: 35
A42: BOUCHIAR | B42: Sérine | R42: 15 | U42: 50 | AA42: 35
A43: CARMINATI | B43: Pierre Yves | R43: 15 | U43: 50 | AA43: 35
A44: CHENET | B44: Maxime | R44: 15 | U44: 50 | AA44: 35
A45: DURAND RAPPELER RANDSTAD | B45: Loren | O45: 1 | P45: 46071 | R45: 15 | U45: 50 | AA45: 35
A46: MESE | B46: Hafiza | R46: 15 | U46: 50 | AA46: 35
A47: RIFATI | B47: Bajram | O47: 1 | P47: 46049 | Q47: 46054 | R47: 46069 | S47: 1 | T47: 1 | U47: 46104 | AA47: 35
A48: SOK | B48: Huy | R48: 15 | U48: 50 | AA48: 35
A49: ESCOBAR | B49: Simon | R49: 15 | U49: 50 | AA49: 35
A50: OKUMUS | B50: OKAN | R50: 15 | U50: 50 | AA50: 35
A51: MOUSTAID | B51: Hichem | O51: 1 | P51: 46049 | Q51: 46054 | R51: 46069 | U51: 46104 | AA51: 35
A52: CAO | B52: Marie | R52: 15 | U52: 50 | AA52: 35
A53: ATTAR | B53: Karim | R53: 15 | U53: 50 | AA53: 35
A54: MARNISSI | B54: Nesrine | R54: 15 | U54: 50 | AA54: 35
A55: BARROS | B55: Mélanie | R55: 15 | U55: 50 | AA55: 35
A56: FABBRI | B56: Kelly | R56: 15 | U56: 50 | AA56: 35
A57: MAHAMAT ABDALLAH | B57: Wossil | R57: 15 | U57: 50 | AA57: 35
A58: AZZAOUI | B58: Hafida | R58: 15 | U58: 50 | AA58: 35
A59: BENJAHA | B59: Hafida | R59: 15 | U59: 50 | AA59: 35
A60: GJONGECAJ | B60: Anxhela | R60: 15 | U60: 50 | AA60: 35
A61: TEIXEIRA FERREIRA | B61: Antonio | R61: 15 | U61: 50 | AA61: 35
A62: HINDI | B62: Sihame | O62: 1 | P62: 46049 | Q62: 46054 | R62: 46069 | U62: 46104 | AA62: 35
A63: AOURAGH | B63: Salima | R63: 15 | U63: 50 | AA63: 35
A64: DIAS LANDIM | B64: Vania | R64: 15 | U64: 50 | AA64: 35
A65: RENARD | B65: Anaïs | R65: 15 | U65: 50 | AA65: 35
A66: MARQUES | B66: Patrick | R66: 15 | U66: 50 | AA66: 35
A67: KARA | B67: Fadime | R67: 15 | U67: 50 | AA67: 35
A68: MARGAROLI | B68: Marie-Astrid | R68: 15 | U68: 50 | AA68: 35
A69: EL HACHMI | B69: Fadoua | R69: 15 | U69: 50 | AA69: 35
A70: VARELA LOPES | B70: Joao Domingos | R70: 15 | U70: 50 | AA70: 35
A71: DANTAN | B71: Théo | R71: 15 | U71: 50 | AA71: 35
A72: DERARIDJ | B72: Karl | R72: 15 | U72: 50 | AA72: 35
A73: DAYI | B73: Gulseren | R73: 15 | U73: 50 | AA73: 35
A74: BEDIR | B74: Murat | R74: 15 | U74: 50 | AA74: 35
... A102: KHOUAKHI | B102: Jihane | R102: 15 | U102: 50 | AA102: 35
A103: ERASLAN | B103: Mustafa | O103: 1 | R103: 15 | U103: 50 | AA103: 35
A104: GATINEAU | B104: Richard | R104: 15 | U104: 50 | AA104: 35
A105: BOIS | B105: ALEXIS | R105: 15 | U105: 50 | AA105: 35
A106: D'ORAZIO | B106: ENZO | R106: 15 | U106: 50 | AA106: 35
A107: VELON | B107: Alicia | R107: 15 | U107: 50 | AA107: 35
A108: SOGOJEVA | B108: Kushtrim | R108: 15 | U108: 50 | AA108: 35
A109: AOUDIA | B109: Nouara | R109: 15 | U109: 50 | AA109: 35
